Workbook

Sheet Overview
A1: ccc
B2: Key | F2: Example | I2: Key Focus | J2: KPI (Monthly)
B3: Tier 1 | C3: Top International Media Outlets | F3: Forbes, Bloomberg etc. | H3: Shoaib | I3: Target Tier 1 Media with macro news | J3: 2 Micro-papers + 5 Tier 1 mentions
B4: Tier 2 | C4: Regional Media Outlets | F4: The National, Khaleej | H4: Ameerah | I4: Lifestyle + Reach outs (Radio/Podcast/Lunches) | J4: 2 Top 50 Mentions + 4radio/podcast appearances
B5: Tier 3 | C5: International mentions from small outlets | H5: Jade | I5: Real estate general content | J5: 30 mentiones + Beat our competitors
B8: Period | C8: Tier 1 | D8: Tier 2 | E8: Tier 3 | F8: Total Mentions
B9: 2021 | C9: - | D9: 19 | E9: 12 | F9: =D9+E9 -> 31
B10: 2022 | C10: =COUNTIFS('2022'!$B:$B,C$8) -> 19 | D10: =COUNTIFS('2022'!$B:$B,D$8) -> 121 | E10: =COUNTIFS('2022'!$B:$B,E$8) -> 62 | F10: =D10+E10 -> 183
B11: 2023 | C11: =COUNTIFS('2023'!$B:$B,C$8) -> 39 | D11: =COUNTIFS('2023'!$B:$B,D$8) -> 139 | E11: =COUNTIFS('2023'!$B:$B,E$8) -> 108 | F11: =SUM(C11:E11) -> 286
B12: 2024 | C12: =COUNTIFS('2024'!$B:$B,C$8) -> 7 | D12: =COUNTIFS('2024'!$B:$B,D$8) -> 125 | E12: =COUNTIFS('2024'!$B:$B,E$8) -> 78 | F12: =SUM(C12:E12) -> 210 | I12: 2024 - 210 | J12: 210
B13: 2025 | C13: =COUNTIFS('2025'!$C:$C,C$8) -> 0 | D13: =COUNTIFS('2025'!$C:$C,D$8) -> 77 | E13: =COUNTIFS('2025'!$C:$C,E$8) -> 119 | F13: =SUM(C13:E13) -> 196 | I13: 2025 - Nov -
B27: Period | C27: Tier 1 | D27: Tier 2 | E27: Tier 3
B28: 2022 H1 | C28: =COUNTIFS('2022'!$B:$B,C$8,'2022'!$A:$A,"<"&DATE(2022,7,1)) -> 3 | D28: =COUNTIFS('2022'!$B:$B,D$8,'2022'!$A:$A,"<"&DATE(2022,7,1)) -> 27 | E28: =COUNTIFS('2022'!$B:$B,E$8,'2022'!$A:$A,"<"&DATE(2022,7,1)) -> 11
B29: 2023 H1 | C29: =COUNTIFS('2023'!$B:$B,C$8,'2023'!$A:$A,"<"&DATE(2023,7,1)) -> 27 | D29: =COUNTIFS('2023'!$B:$B,D$8,'2023'!$A:$A,"<"&DATE(2023,7,1)) -> 58 | E29: =COUNTIFS('2023'!$B:$B,E$8,'2023'!$A:$A,"<"&DATE(2023,7,1)) -> 65
B30: Change | C30: =C29/C28-1 -> 8 | D30: =D29/D28-1 -> 1.1481481 | E30: =E29/E28-1 -> 4.9090909
B33: Core
B34: Period | C34: Tier 1 | D34: Tier 2 | E34: Tier 3
B35: 2022 H1 | C35: =COUNTIFS('2022'!$B:$B,C$8,'2022'!$A:$A,"<"&DATE(2022,7,1),'2022'!$F:$F,"Betterhomes") -> 3 | D35: =COUNTIFS('2022'!$B:$B,D$8,'2022'!$A:$A,"<"&DATE(2022,7,1),'2022'!$F:$F,"Betterhomes") -> 18 | E35: =COUNTIFS('2022'!$B:$B,E$8,'2022'!$A:$A,"<"&DATE(2022,7,1),'2022'!$F:$F,"Betterhomes") -> 9
B36: 2023 H1 | C36: =COUNTIFS('2023'!$B:$B,C$8,'2023'!$A:$A,"<"&DATE(2023,7,1),'2023'!$F:$F,"Betterhomes") -> 26 | D36: =COUNTIFS('2023'!$B:$B,D$8,'2023'!$A:$A,"<"&DATE(2023,7,1),'2023'!$F:$F,"Betterhomes") -> 50 | E36: =COUNTIFS('2023'!$B:$B,E$8,'2023'!$A:$A,"<"&DATE(2023,7,1),'2023'!$F:$F,"Betterhomes") -> 65
B37: Change | C37: =C36/C35-1 -> 7.6666667 | D37: =D36/D35-1 -> 1.7777778 | E37: =E36/E35-1 -> 6.2222222
B40: Prime
B41: Period | C41: Tier 1 | D41: Tier 2 | E41: Tier 3
B42: 2022 H1 | C42: =COUNTIFS('2022'!$B:$B,C$8,'2022'!$A:$A,"<"&DATE(2022,7,1),'2022'!F:F,"PRIME") -> 0 | D42: =COUNTIFS('2022'!$B:$B,D$8,'2022'!$A:$A,"<"&DATE(2022,7,1),'2022'!F:F,"PRIME") -> 0 | E42: =COUNTIFS('2022'!$B:$B,E$8,'2022'!$A:$A,"<"&DATE(2022,7,1),'2022'!F:F,"PRIME") -> 0
B43: 2023 H1 | C43: =COUNTIFS('2023'!$B:$B,C$8,'2023'!$A:$A,"<"&DATE(2023,7,1),'2023'!$F:$F,"Prime by Betterhomes") -> 1 | D43: =COUNTIFS('2023'!$B:$B,D$8,'2023'!$A:$A,"<"&DATE(2023,7,1),'2023'!$F:$F,"Prime by Betterhomes") -> 7 | E43: =COUNTIFS('2023'!$B:$B,E$8,'2023'!$A:$A,"<"&DATE(2023,7,1),'2023'!$F:$F,"Prime by Betterhomes") -> 0
B44: Change | C44: =C43/C42-1 -> #DIV/0! | D44: =D43/D42-1 -> #DIV/0! | E44: =E43/E42-1 -> #DIV/0!
B46: Period | C46: Tier 1 | D46: Tier 2 | E46: Tier 3 | F46: Total Mentions
B47: January | C47: 5 | D47: 8 | E47: 26 | F47: 39
B48: February | C48: 5 | D48: 8 | E48: 14 | F48: 27
B49: March | C49: 6 | D49: 12 | E49: 5 | F49: 23
B50: April | C50: 4 | D50: 8 | E50: 4 | F50: 16
B51: May | C51: 0 | D51: 10 | E51: 6 | F51: 16
B52: June | C52: 7 | D52: 12 | E52: 10 | F52: 29
B53: July | C53: 2 | D53: 25 | E53: 5 | F53: 32
B54: August | C54: 2 | D54: 9 | E54: 2 | F54: 13
B55: September | C55: 0 | D55: 7 | E55: 7 | F55: 16
B56: October | C56: 1 | D56: 18 | E56: 3 | F56: 22
B57: November | C57: 6 | D57: 12 | E57: 14 | F57: 32
B58: December | C58: 1 | D58: 8 | E58: 12 | F58: 21
B60: Key points
B61: We are just half way through the year and I already have more mentions from Tier one outlets than the whole of last year
B62: Reached nearly 70% of the total mentions thats were reached last year
B63: Initial and only KPI ever set was to reach 16 mentions per month, even with the event this was still attained

Sheet 2026
A1: cc | B1: Media Tier | C1: Media | D1: Cost | E1: Reach | F1: Title | G1: Link | H1: Link | I1: Brand
A2: 46023 | B2: Tier 1 Local | C2: Khaleej Times | D2: 2200 | E2: 500000 | F2: Dubai South to draw more end-users as DWC expansion creates more jobs | G2: https://www.khaleejtimes.com/uae/dubai-south-properties-dwc-expansion
A3: 46030 | B3: Tier 1 Local | C3: Khaleej Times | D3: 2200 | E3: 500000 | F3: Dubai real estate outlook 2026: steady demand, selective cooling, and a tech‑driven turn | G3: https://www.khaleejtimes.com/business/property/dubai-real-estate-outlook-2026-steady-demand-selective-cooling-and-a-techdriven-turn | I3: betterhomes
A4: 46034 | B4: Tier 1 Local | C4: Khaleej Times | D4: 2200 | E4: 500000 | F4: Why Dubai’s property boom is built to last for a long time | G4: https://www.khaleejtimes.com/business/property/why-dubais-property-boom-is-built-to-last-for-a-long-time | I4: betterhomes
A5: 46035 | B5: Tier 3 | C5: Press Reader | F5: Why Dubai’s property boom is built to last for a long time | G5: https://www.pressreader.com/uae/khaleej-times/20260112/281788520445913
A6: 46035 | B6: Tier 1 Local | C6: Construction Week | D6: 3000 | E6: 40000 | F6: What’s next for Dubai’s real estate landscape? | G6: https://www.constructionweekonline.com/business/insights/dubai-real-estate-2026-2
A7: 46034 | B7: Tier 2 | C7: Zawya | D7: 1000 | E7: 100000 | F7: The 3rd edition of Dubai's Top 50 Homes revealed - ZAWYA | G7: The 3rd edition of Dubai's Top 50 Homes revealed - ZAWYA
A8: 15 Januaury 2026 | B8: Tier 2 | C8: Zawya | D8: 1000 | E8: 100000 | F8: Dubai records strongest residential year in 2025; nets $149bln in sales | G8: https://www.tradingview.com/news/reuters.com,2026-01-15:newsml_Zaw6LVJmF:0-zawya-sng-dubai-records-strongest-residential-year-in-2025-nets-149bln-in-sales/ | I8: betterhomes
A9: 46036 | B9: Tier 1 Local | C9: Arabian Business | D9: 9500 | E9: 250000 | F9: Dubai property market hits record $149bn in 2025 as demand and prices strengthen | G9: https://www.arabianbusiness.com/industries/real-estate/dubai-property-market-hits-record-149bn-in-2025-as-demand-and-prices-strengthen | I9: betterhomes
A10: 46036 | B10: Tier 1 Local | C10: Khaleej Times | D10: 2200 | E10: 500000 | F10: Dubai closes 2025 with a record Dh547b property market | G10: https://www.khaleejtimes.com/business/property/dubai-closes-2025-with-a-record-dh547b-property-market?amp=1
A11: 46039 | B11: Tier 1 Local | C11: Khaleej Times | D11: 2200 | E11: 500000 | F11: The off-plan segment will not only continue to dominate, but also increase its share in the Dubai property market | G11: https://www.khaleejtimes.com/business/property/dubai-properties-buying-off-plan-2026
A12: 46042 | B12: Tier 1 Local | C12: Construction Week | D12: 3000 | E12: 40000 | F12: Dubai property market 2026: Where are smart investors looking next? | G12: Dubai property market 2026: Where are smart investors looking next?
A13: 46044 | B13: Tier 1 Local | C13: Construction Week | D13: 3000 | E13: 40000 | F13: Dubai property market 2025-26: Questions global investors are asking right now | G13: https://www.constructionweekonline.com/analysis/dubai-property-market-2026
A14: 46050 | B14: Tier 1 Local | C14: Construction Week | D14: 3000 | E14: 40000 | F14: betterhomes appoints Alex Leigh as Director of Operations | G14: https://www.constructionweekonline.com/people/appointments/betterhomes-alex-leigh
A15: 46051 | B15: Tier 3 | C15: The Economic Times | F15: Indians, Britons top Dubai property buys in 2025 as rupee falls | G15: https://economictimes.indiatimes.com/nri/invest/indians-britons-top-dubai-property-buys-in-2025-as-rupee-falls/articleshow/127730830.cms?from=mdr&utm_source=contentofinterest&utm_medium=text&utm_campaign=cppstt
A16: 46051 | B16: Tier 2 | C16: Zawya | D16: 1000 | E16: 100000 | F16: Dubai rental boom defies inflation as demand surges but rents stay flat | G16: https://www.tradingview.com/news/reuters.com,2026-01-29:newsml_Zaw4HPJHJ:0-zawya-pressr-dubai-rental-boom-defies-inflation-as-demand-surges-but-rents-stay-flat/
A17: 46052 | B17: Tier 1 Local | C17: Khaleej Times | D17: 2200 | E17: 500000 | F17: Dubai rents hold steady as families reshape demand in record‑setting 2025 | Khaleej Times | G17: Dubai rents hold steady as families reshape demand in record‑setting 2025 | Khaleej Times
A18: 46058 | B18: Tier 1 Local | C18: Arabian Business | D18: 9500 | E18: 250000 | F18: Dubai off-plan homes dominate property market with record 65% of transactions | G18: Dubai off-plan homes dominate property market with record 65% of transactions
A19: 46058 | B19: Tier 1 Local | C19: Construction Week | D19: 3000 | E19: 40000 | F19: 132,000 homes sold: Dubai’s off-plan sales reach $78 bn in 2025 | G19: 132,000 homes sold: Dubai’s off-plan sales reach $78 bn in 2025
A20: 46058 | B20: Tier 3 | C20: Trade Arabia | F20: Dubai off-plan sales hit 130,000 homes; value touches $77.88bn - TradeArabia | G20: Dubai off-plan sales hit 130,000 homes; value touches $77.88bn - TradeArabia
A21: 46057 | B21: Tier 3 | C21: Money Control | F21: Why Indian investors are increasingly buying property in Dubai | G21: https://www.moneycontrol.com/news/business/personal-finance/why-indian-investors-are-increasingly-buying-property-in-dubai-13774469.html
A22: 46063 | B22: Tier 1 Local | C22: Construction Week | D22: 3000 | E22: 40000 | F22: Dubai’s January property sales hit AED55 bn | G22: https://www.constructionweekonline.com/analysis/dubai-january-property-sales
A23: 46063 | B23: Tier 1 Local | C23: Arabian Business | D23: 9500 | E23: 250000 | F23: Dubai residential sales hit AED55.2bn in January as transactions rise | G23: https://www.arabianbusiness.com/industries/real-estate/dubai-residential-sales-hit-aed55-2bn-in-january-as-transactions-rise
A24: 46069 | B24: Tier 2 | C24: Zawya | D24: 1000 | E24: 100000 | F24: Abu Dhabi property market records $3.2bln in January sales | G24: Abu Dhabi property market records $3.2bln in January sales
A25: 46067 | B25: Tier 1 Local | C25: Arabian Business | D25: 9500 | E25: 250000 | F25: Abu Dhabi property market hits $3.27bn in January sales as off-plan dominates 83 per cent of deals | G25: Abu Dhabi property market hits $3.27bn in January sales as off-plan dominates 83 per cent of deals
A26: 46063 | B26: Tier 1 Local | C26: Construction Week | D26: 3000 | E26: 40000 | F26: Ellington Properties unveils The Meriva Collection on Dubai Islands | G26: https://www.constructionweekonline.com/projects-tenders/ellington-properties-the-meriva
A27: 46063 | B27: Tier 2 | C27: Zawya | D27: 1000 | E27: 100000 | F27: ZAWYA-PRESSR: Ellington Properties unveils The Meriva Collection, a hospitality-led beachfront destination on Dubai Islands | G27: https://www.tradingview.com/news/reuters.com,2026-02-10:newsml_ZawPnl2M:0-zawya-pressr-ellington-properties-unveils-the-meriva-collection-a-hospitality-led-beachfront-destination-on-dubai-islands/
A28: 46063 | B28: Tier 1 Local | C28: Construction Week | D28: 3000 | E28: 40000 | F28: Abu Dhabi property market kicks off 2026 with $3.2bn sales surge - Construction Week | G28: Abu Dhabi property market kicks off 2026 with $3.2bn sales surge - Construction Week
A29: 46079 | B29: Tier 1 Local | C29: Arabian Business | D29: 9500 | E29: 250000 | F29: Dubai property sales hit $10.6bn during Ramadan 2025 as betterhomes forecasts up 12% growth in 2026 | G29: https://www.arabianbusiness.com/real-estate/dubai-property-sales-hit-10-6bn-during-ramadan-2025-as-betterhomes-forecasts-up-12-growth-in-2026
A30: 46076 | B30: Tier 3 | C30: One Ville News | F30: Blue Square Development: A trusted regional partner bringing decades of expertise to Dubai’s residential landscape | G30: https://onevillenews.com/2026/02/23/blue-square-development-a-trusted-regional-partner-bringing-decades-of-expertise-to-dubais-residential-landscape/
A31: 46078 | B31: Tier 1 Local | C31: Arabian Business | D31: 9500 | E31: 250000 | F31: Dubai property sales hit $10.6bn during Ramadan 2025 as betterhomes forecasts up 12% growth in 2026 | G31: https://www.arabianbusiness.com/real-estate/dubai-property-sales-hit-10-6bn-during-ramadan-2025-as-betterhomes-forecasts-up-12-growth-in-2026
A32: 46079 | B32: Tier 1 Local | C32: Khaleej Times | D32: 2200 | E32: 500000 | F32: Dubai real estate activity to rise 8–12% during Ramadan 2026 | G32: https://www.khaleejtimes.com/business/dubai-real-estate-activity-to-rise-812-during-ramadan-2026
A34: March | D34: =SUM(D18:D32) -> 63700 | E34: =SUM(E18:E32) -> 2110000
A35: 46086 | B35: Tier 1 International | C35: Reuters | D35: 20000 | E35: 1000000 | F35: UAE's property sector faces reckoning after Iran strikes | G35: https://www.reuters.com/world/middle-east/uaes-property-sector-faces-reckoning-after-iran-strikes-2026-03-05/
A36: 46090 | B36: Tier 1 Local | C36: Arabian Business | D36: 9500 | E36: 250000 | F36: Dubai property market remains active despite dip in enquiries: betterhomes | G36: https://www.arabianbusiness.com/real-estate/dubai-property-market-active
A37: 46090 | B37: Tier 3 | C37: MENAFN | F37: Dubai Property Market Continues To Move Despite Quieter Conditions, Says Betterhomes | G37: Dubai Property Market Continues To Move Despite Quieter Conditions, Says Betterhomes
A38: 46092 | B38: Tier 1 Local | C38: The National News | D38: 9300 | E38: 200000 | F38: Stability, not panic': Dubai real estate companies have faith despite Iran war | The National | G38: Stability, not panic': Dubai real estate companies have faith despite Iran war | The National
A39: 46093 | B39: Tier 1 Local | C39: Gulf Business Daily | D39: 1000 | E39: 100000 | F39: UAE Business: Dubai's leasing market continues to move despite regional uncertainty, says expert | G39: UAE Business: Dubai's leasing market continues to move despite regional uncertainty, says expert
A40: 46093 | B40: Tier 1 Local | C40: Khaleej Times | D40: 2200 | E40: 500000 | F40: Dubai property defies uncertainty: Investors prioritise stability - Khaleej Times | G40: Dubai property defies uncertainty: Investors prioritise stability - Khaleej Times
A41: 46094 | B41: Tier 2 | C41: MSN | F41: Dubai rental market weathers regional tensions with flexible payment plans - MSN | G41: Dubai rental market weathers regional tensions with flexible payment plans - MSN
A42: 46095 | B42: Tier 1 Local | C42: Khaleej Times | D42: 2200 | E42: 500000 | F42: Dubai rental market weathers regional tensions with flexible payment plans - Khaleej Times | G42: Dubai rental market weathers regional tensions with flexible payment plans - Khaleej Times
A43: 46093 | B43: Tier 3 | C43: Mid-eastinfo | F43: Dubai property market continues to move despite quieter conditions, says betterhomes | G43: Dubai property market continues to move despite quieter conditions, says betterhomes
A44: 46089 | B44: Tier 3 | C44: India news | F44: Iran conflict rattles Dubai and Abu Dhabi real estate | G44: Iran conflict rattles Dubai and Abu Dhabi real estate - India's News
A45: 46089 | B45: Tier 3 | C45: Big news network | F45: Iran strikes threaten UAE property boom built on foreign money - Big News Network.com | G45: Iran strikes threaten UAE property boom built on foreign money - Big News Network.com
A46: 46089 | B46: Tier 3 | C46: Greatandhra | F46: Iran Strikes Shake UAE Property Boom, Investors Turn Cautious - Greatandhra.com | G46: Iran Strikes Shake UAE Property Boom, Investors Turn Cautious - Greatandhra.com
A47: 46087 | B47: Tier 1 Local | C47: Construction Week | D47: 3000 | E47: 40000 | F47: Are Dubai property prices about to drop? - Construction Week Online | G47: Are Dubai property prices about to drop? - Construction Week Online
A48: 46087 | B48: Tier 3 | C48: RBC Ukraine | F48: UAE property market tumbles after Iranian attacks - RBC-Ukraine | G48: UAE property market tumbles after Iranian attacks - RBC-Ukraine
A49: 46087 | B49: Tier 3 | C49: International Business Times, Singapore Edition | F49: UAE's Top Property Stocks Face 5% Erosion After Iranian Strikes Rattle Investor Confidence | G49: UAE's Top Property Stocks Face 5% Erosion After Iranian Strikes Rattle Investor Confidence
A50: 46087 | B50: Tier 3 | C50: ET Realty | F50: UAE's property sector faces reckoning after Iran strikes - ET Realty | G50: UAE's property sector faces reckoning after Iran strikes - ET Realty
A51: 46087 | B51: Tier 3 | C51: Dawn.com | F51: UAE's property sector faces reckoning after Iran strikes - DAWN.COM | G51: UAE's property sector faces reckoning after Iran strikes - DAWN.COM
A52: 46087 | B52: Tier 3 | C52: The Times of India | F52: UAE property boom faces first major test after Iran strikes shake investor confidence | G52: UAE property boom faces first major test after Iran strikes shake investor confidence
A53: 46087 | B53: Tier 3 | C53: News18 | F53: Will Gulf Tensions Dent Dubai's Luxury Property Market? Experts Weigh In - News18 | G53: Will Gulf Tensions Dent Dubai's Luxury Property Market? Experts Weigh In - News18
A54: 46105 | B54: Tier 1 Local | C54: Arabian Business | D54: 9500 | E54: 250000 | F54: Dubai property enquiries jump 38% as buyers take ‘measured approach’ despite softer market activity | G54: https://www.arabianbusiness.com/real-estate/dubai-property-enquiries-jump-38-as-buyers-take-measured-approach-despite-softer-market-activity
A55: 46105 | C55: Press Reader | F55: Prop­erty buy­ers take a meas­ured approach as mar­ket holds steady | G55: https://www.pressreader.com/uae/khaleej-times/20260324/281818585360450
A56: 46104 | B56: Tier 1 Local | C56: Khaleej Times | D56: 2200 | E56: 500000 | F56: Dubai property buyers take a more 'measured approach' as market holds steady | G56: https://www.khaleejtimes.com/business/property/dubai-property-buyers-take-a-more-measured-approach-as-market-holds-steady?amp=1
A57: 46109 | B57: Tier 1 Local | C57: Arabian Business | D57: 9500 | E57: 250000 | F57: Dubai off-plan property market holds steady as investors eye long-term gains, transactions hit $6.26bn | G57: https://www.arabianbusiness.com/real-estate/dubai-off-plan-property-market-holds-steady-as-investors-eye-long-term-gains-transactions-hit-6-26bn
A58: 46111 | B58: Tier 1 Local | C58: The National News | F58: Dubai rental listings rise as tenants seek better pricing and flexibility | G58: https://www.thenationalnews.com/business/property/2026/03/30/dubai-rental-listings-rise-as-tenants-seek-better-pricing-and-flexibility/
A59: 46111 | B59: Tier 1 Local | C59: MSN | F59: Dubai rental listings rise as tenants seek better pricing and flexibility | G59: https://www.msn.com/en-ae/money/news/dubai-rental-listings-rise-as-tenants-seek-better-pricing-and-flexibility/ar-AA1ZJItn?ocid=finance-verthp-feeds
A60: 46111 | B60: Tier 2 | C60: Gulf Daily News | F60: Dubai leasing market adjusts as rental listings increase: report | G60: https://www.gdnonline.com/Details/1379971/Dubai-leasing-market-adjusts-as-rental-listings-increase-report
B61: Tier 1 Local | C61: MSN | F61: Dubai’s commercial property prices jump 28% in March despite regional conflict | G61: https://www.msn.com/en-ae/money/news/dubai-s-commercial-property-prices-jump-28-in-march-despite-regional-conflict/ar-AA1ZZ8qy?ocid=finance-verthp-feeds
A62: 46112 | C62: Khaleej Times | D62: 2200 | E62: 500000 | F62: While tenant enquiries have softened compared with last year’s exceptionally strong cycle, analysts say the market is adjusting rather than weakening | G62: https://www.khaleejtimes.com/business/property/dubai-rentals-steady-as-landlords-hold-firm-despite-tensions
A64: April
A65: 46114 | B65: Tier 1 Local | C65: Khaleej Times | D65: 2200 | E65: 500000 | F65: Several communities saw growth in per-square-meter prices with Dubai Investment Park Second witnessing 323% increase YoY, while Al Safouh was up by 286% during February 28 and March 19 | G65: https://www.khaleejtimes.com/business/property/dubais-commercial-property-prices-jump-28-in-march-despite-regional-conflict
A66: 46118 | B66: Tier 1 Local | C66: Khaleej Times | D66: 2200 | E66: 500000 | F66: Dubai real estate steadies as fundamentals stay strong | G66: https://www.khaleejtimes.com/business/property/dubai-real-estate-steadies-as-fundamentals-stay-strong
A67: 46120 | B67: Tier 2 | C67: Zawya | D67: 1000 | E67: 100000 | F67: Dubai’s off-plan market 'more selective now, but long-term confidence remains' | G67: https://www.zawya.com/en/business/real-estate/dubais-off-plan-market-more-selective-now-but-long-term-confidence-remains-l1gcgfft
A68: 46119 | B68: Tier 2 International | C68: Republica.com | F68: Betterhomes: el mercado inmobiliario de Dubái se enfría sin caer en pánico | G68: https://republica.com/inmobiliaria/betterhomes-el-mercado-inmobiliario-de-dubai-se-enfria-sin-caer-en-panico-20264712304
A69: 46122 | B69: Tier 2 | C69: Zawya | D69: 1000 | E69: 100000 | F69: Dubai property prices may soften, but segment variation likely: expert | G69: https://www.zawya.com/en/business/real-estate/dubai-property-prices-may-soften-but-segment-variation-likely-expert-w1thh8mh
A70: 46124 | B70: Tier 1 Local | C70: Khaleej Times | D70: 2200 | E70: 500000 | F70: Dubai property prices unlikely to soften across every segment | G70: https://www.khaleejtimes.com/business/property/dubai-property-prices-unlikely-to-soften-across-every-segment
A71: 46122 | B71: Tier 2 | C71: Gulf Daily News | F71: Dubai property prices may soften, but segment variation likely: expert | G71: https://www.gdnonline.com/Details/1381057/Dubai-property-prices-may-soften,-but-segment-variation-likely-expert
A72: 17/04/2026 | B72: Tier 2 | C72: Arqam.news | F72: Dubai Commercial Real Estate Enters Value-Driven Growth Phase in Q1 2026 with AED 37.9 Billion Sales | G72: https://arqam.news/555926/
A73: 17/04/2026 | B73: Tier 2 | C73: Zawya | D73: 1000 | E73: 100000 | F73: Dubai commercial property market sales value tops $10bln in Q1, up 30% | G73: https://www.zawya.com/en/business/real-estate/dubai-commercial-property-market-sales-value-tops-10bln-in-q1-up-30-au8nk1vm
A74: 20/04/2026 | B74: Tier 1 Local | C74: Arabian Business | D74: 9500 | E74: 250000 | F74: Dubai rents 12.5% below March 2025 levels as leasing market becomes more competitive | G74: https://www.arabianbusiness.com/real-estate/dubai-rents-12-5-below-march-2025-levels-as-leasing-market-becomes-more-competitive
A75: 19/04/2026 | B75: Tier 1 Local | C75: The National News | F75: Dubai rents defy regional tensions as first quarter values reach $8.8bn | G75: https://www.thenationalnews.com/business/property/2026/04/19/dubai-rents-war-property/
A76: 22/04/2026 | B76: Tier 1 Local | C76: Khaleej Times | D76: 2200 | E76: 100000 | F76: Rents in Dubai: Landlords pricing units correctly are able to let as market softens | G76: https://www.khaleejtimes.com/business/property/rents-in-dubai-landlords-pricing-units-correctly-are-able-to-let-as-market-softens
A77: 23/04/2026 | B77: Tier 2 International | C77: The Economic Times | F77: Dubai home prices record first decline after post-pandemic boom | G77: https://economictimes.indiatimes.com/nri/invest/dubai-home-prices-record-first-decline-after-post-pandemic-boom/articleshow/130460937.cms?from=mdr
A78: 23/04/2026 | B78: Tier 1 International | C78: Bloomberg | F78: Dubai home prices drop for first time since post-pandemic boom | G78: https://www.bloomberg.com/news/articles/2026-04-23/dubai-home-prices-post-first-declines-after-post-pandemic-boom?utm_source=website&utm_medium=share&utm_campaign=linkedin?sref=FLEECBjF
A79: 23/04/2026 | B79: Tier 2 | C79: Arqam.news | F79: betterhomes: DIFC’s AI-native expansion reinforces long-term appeal of central Dubai living | G79: https://arqam.news/557688/
A80: 23/04/2026 | B80: Tier 2 International | C80: Info Nasional | F80: Dubai Home Prices Experience First Decline Since 2020 Amid Regional Conflict | G80: https://world.infonasional.com/dubai-property-prices-fall-regional-conflict
A81: 23/04/2026 | B81: Tier 1 International | C81: MSN | F81: Dubai home prices record first decline after post-pandemic boom | G81: https://www.msn.com/en-in/money/topstories/dubai-home-prices-record-first-decline-after-post-pandemic-boom/ar-AA21x7ld?apiversion=v2&domshim=1&noservercache=1&noservertelemetry=1&batchservertelemetry=1&renderwebcomponents=1&wcseo=1&bundles=feat-es2020-c
A82: 23/04/2026 | B82: Tier 2 International | C82: The Business Times | F82: Dubai home prices drop for first time since post-pandemic boom | G82: https://www.businesstimes.com.sg/international/dubai-home-prices-drop-first-time-post-pandemic-boom
A83: 23/04/2026 | B83: Tier 2 International | C83: News Karnataka | F83: Dubai property prices fall after pandemic boom | G83: https://newskarnataka.com/business/dubai-property-prices-fall-after-pandemic-boom/23042026
A84: 24/04/2026 | B84: Tier 2 International | C84: Business Today | F84: Dubai home prices fall for first time since the pandemic boom: Report | G84: https://www.businesstoday.in/personal-finance/real-estate/story/dubai-home-prices-fall-for-first-time-since-the-pandemic-boom-report-527128-2026-04-24
A85: 24/04/2026 | B85: Tier 2 International | C85: Business Standard | F85: After 70% surge, Dubai housing sees first price drop since the pandemic | G85: https://www.business-standard.com/finance/personal-finance/after-70-surge-dubai-housing-sees-first-price-drop-since-the-pandemic-126042400181_1.html
A86: 24/04/2026 | B86: Tier 2 International | C86: Realty.com (Economic Times) | F86: Dubai home prices record first decline after post-pandemic boom | G86: https://realty.economictimes.indiatimes.com/news/international/dubai-home-prices-decline-post-pandemic-boom-faces-geopolitical-challenges/130482529
A87: 23/04/2026 | B87: Tier 2 International | C87: MENA FM | F87: Betterhomes: DIFC's AI-Native Expansion Reinforces Long-Term Appeal Of Central Dubai Living | G87: https://menafn.com/1111021770/Betterhomes-DIFCs-AI-Native-Expansion-Reinforces-Long-Term-Appeal-Of-Central-Dubai-Living
A88: 23/04/2026 | B88: Tier 2 | C88: Zawya | F88: ZAWYA: Rently: Tackling the challenges of modern rentals | G88: https://www.tradingview.com/news/reuters.com,2026-04-23:newsml_Zaw9l1kxN:0-zawya-rently-tackling-the-challenges-of-modern-rentals/
A89: 25/04/2026 | B89: Tier 1 Local | C89: Khaleej Times | F89: No pause button: The UAE’s real estate machine | G89: https://www.khaleejtimes.com/supplements/no-pause-button-the-uaes-real-estate-machine?amp=1
B90: Tier 2 International | C90: The Economic Times | F90: Dubai plotting a comeback as Iran war hammers its hottest market | G90: https://economictimes.indiatimes.com/nri/dubai-real-estate-plotting-a-comeback-as-us-iran-war-hammers-its-hottest-property-market/articleshow/130672295.cms?from=mdr
A91: 27th April 2026 | B91: Tier 1 Local | C91: Lovin Dubai | F91: Dubai’s property market is starting to cool off 🏙️📉 After years of rapid growth, prices dipped for the first time in 6 years!⁠ | G91: https://www.instagram.com/p/DXoRnx3oMlB/?img_index=4&hl=fr
A93: May
A94: 4th May 2026 | B94: Tier 3 | C94: One Ville News | F94: betterhomes exclusively launches City Tower, redefining long-term leasing in Central Dubai | G94: https://onevillenews.com/2026/05/04/betterhomes-exclusively-launches-city-tower-redefining-long-term-leasing-in-central-dubai/
A95: 4th May 2026 | B95: Tier 2 International | C95: Gulf Daily News | F95: betterhomes announces exclusive launch of 93-storey Dubai tower | G95: https://www.gdnonline.com/Details/1393610/betterhomes-announces-exclusive-launch-of-93-storey-Dubai-tower
A96: 4th May 2026 | B96: Tier 2 | C96: Zawya | F96: Betterhomes exclusively launches City Tower, redefining long-term leasing in Central Dubai | G96: https://www.zawya.com/en/press-release/companies-news/betterhomes-exclusively-launches-city-tower-redefining-long-term-leasing-in-central-dubai-tnioca7e
A97: 4th May 2026 | B97: Tier 2 | C97: Trade Arabia | F97: betterhomes announces exclusive launch of 93-storey Dubai tower | G97: https://www.tradearabia.com/News/462096/betterhomes-announces-exclusive-launch-of-93-storey-Dubai-tower
A98: 5th May 2026 | B98: Tier 2 | C98: Mechanical Electrical Plumbing | F98: Betterhomes Announces Exclusive Launch Of 93-Storey Dubai Tower | G98: https://www.mepmiddleeast.com/news/betterhomes-announces-exclusive-launch-of-93-storey-dubai-tower
A99: 5th May 2026 | B99: Tier 1 Local | C99: Khaleej Times | F99: Dubai residential transactions hit Dh139.2 billion in Q1 | G99: https://www.khaleejtimes.com/business/dubai-residential-transactions-hit-dh1392-billion-in-q1
A100: 5th May 2026 | B100: Tier 1 International | C100: MSN | F100: Dubai residential transactions hit Dh139.2 billion in Q1 | G100: https://www.msn.com/en-ae/money/news/dubai-residential-transactions-hit-dh139-2-billion-in-q1/ar-AA22rd30?ocid=finance-verthp-feeds
A101: 5th May 2026 | B101: Tier 1 Local | C101: Arabian Business | F101: Dubai real estate: Residential transactions records $37.9bn in Q1 2026 | G101: https://www.arabianbusiness.com/real-estate/dubai-real-estate-residential-transactions-records-37-9bn-in-q1-2026
A102: 6th May 2026 | B102: Tier 2 | C102: Trade Arabia | F102: Jamal Living announces new Al Barsha residential launch | G102: https://www.tradearabia.com/News/462193/Jamal-Living-announces-new-Al-Barsha-residential-launch
A103: 7th May 2026 | B103: Tier 2 | C103: International Business Magazine | F103: Jamal Living to launch Al Barsha residential in Dubai | G103: https://intlbm.com/2026/05/07/jamal-living-to-launch-al-barsha-residential-in-dubai/
...

Sheet 2026 Overview
A1: 2025 | C1: January | D1: February | E1: March | F1: April | G1: May | H1: June | I1: July | J1: August | K1: September | L1: October | M1: November | N1: December
A2: BH | B2: Tier 1 Intl
B3: Tier 1 Local
B4: Tier 2
B5: Tier 3
B6: Grand Total
A8: Competitor Press Mentions | C8: January | D8: February | E8: March | F8: April | G8: May | H8: June | I8: July | J8: August | K8: September | L8: October | M8: November | N8: December
A9: BH
A10: Allsopp&Allsopp
A11: Haus&Haus
A12: Engel&Volkers

Sheet 2025
A1: Month | B1: Date | C1: Media Tier | D1: Media | E1: Cost | F1: Reach | G1: Title | H1: Link | I1: Link | J1: Brand
A2: =TEXT(B2, "MMMM") -> January | B2: 45658 | C2: Tier 2 | D2: AGBI | E2: 1000 | F2: 30000 | G2: Burj Khalifa at 15: Ups and downs of the world's tallest skyscraper | H2: https://www.agbi.com/real-estate/2025/01/burj-khalifa-at-15-ups-and-downs-of-the-worlds-tallest-skyscraper/ | I2: {=HYPERLINK(H2:H1086, "ARTICLELINK")} -> #REF! | J2: Betterhomes
A3: =TEXT(B3, "MMMM") -> January | B3: 45661 | C3: Tier 1 Local | D3: Khaleej Times | E3: 2200 | F3: 500000 | G3: Burj Khalifa turns 15: How much it costs to rent a home at the world's tallest building in Dubai | H3: https://www.khaleejtimes.com/uae/burj-khalifa-turns-15-how-much-it-costs-to-rent-a-home-at-the-worlds-tallest-building-in-dubai | J3: Betterhomes
A4: =TEXT(B4, "MMMM") -> January | B4: 45662 | C4: Tier 3 | D4: MSN | G4: Dubai's Burj Khalifa charges Rs 70061 per sq ft in annual rent; here's how much it costs to rent a 1-bedroom flat in world's tallest building | H4: https://www.msn.com/en-in/money/topstories/dubai-s-burj-khalifa-charges-rs-70061-per-sq-ft-in-annual-rent-here-s-how-much-it-costs-to-rent-a-1-bedroom-flat-in-world-s-tallest-building/ar-AA1wXCUw?ocid=finance-verthp-feeds | J4: Betterhomes
A5: =TEXT(B5, "MMMM") -> January | B5: 45666 | C5: Tier 1 Local | D5: Construction Week | E5: 3000 | F5: 40000 | G5: Betterhomes CEO steps down, takes over as Cencorp boss | H5: https://www.constructionweekonline.com/news/betterhomes-ceo-steps-down-takes-over-as-cencorp-boss | J5: Betterhomes/Cencorp
A6: =TEXT(B6, "MMMM") -> January | B6: 45666 | C6: Tier 1 Local | D6: Arabian Business | E6: 9500 | F6: 250000 | G6: Dubai real estate firm Betterhomes announces two major leadership changes | H6: https://www.arabianbusiness.com/jobs/dubai-real-estate-firm-betterhomes-announces-two-major-leadership-changes | J6: Betterhomes/Cencorp
A7: =TEXT(B7, "MMMM") -> January | B7: 45666 | C7: Tier 3 | D7: The Arabian Marketer | G7: Betterhomes Has Announced Two Major Leadership Changes | H7: https://arabianmarketer.ae/betterhomes-has-announced-two-major-leadership-changes/ | J7: Betterhomes/Cencorp
A8: =TEXT(B8, "MMMM") -> January | B8: 45666 | C8: Tier 2 | D8: Zawya | E8: 1000 | F8: 100000 | G8: Betterhomes has announced two major leadership changes | H8: https://www.zawya.com/en/press-release/people-in-the-news/betterhomes-has-announced-two-major-leadership-changes-eul65s4o | J8: Betterhomes/Cencorp
A9: =TEXT(B9, "MMMM") -> January | B9: 45667 | C9: Tier 3 | D9: The Globe and Mail | G9: Betterhomes Reveals Dubai as the World’s Premier Property Investment Destination | H9: https://www.theglobeandmail.com/investing/markets/markets-news/Plentisoft/30388136/betterhomes-reveals-dubai-as-the-worlds-premier-property-investment-destination/ | J9: Betterhomes
A10: =TEXT(B10, "MMMM") -> January | B10: 45668 | C10: Tier 3 | D10: Travel and Tour World | G10: Richard Waind Becomes CEO of Cencorp, While Louis Harding Takes Over as Betterhomes CEO to Drive Dubai Real Estate Growth | H10: https://www.travelandtourworld.com/news/article/richard-waind-becomes-ceo-of-cencorp-while-louis-harding-takes-over-as-betterhomes-ceo-to-drive-dubai-real-estate-growth/ | J10: Betterhomes/Cencorp
A11: =TEXT(B11, "MMMM") -> January | B11: 45668 | C11: Tier 3 | D11: Markets Insider | G11: Betterhomes Reveals Dubai as the World’s Premier Property Investment Destination | H11: https://markets.businessinsider.com/news/stocks/betterhomes-reveals-dubai-as-the-world-s-premier-property-investment-destination-1034215635 | J11: Betterhomes
A12: =TEXT(B12, "MMMM") -> January | B12: 45670 | C12: Tier 3 | D12: Street Insider | G12: Betterhomes Reveals Dubai as the World’s Premier Property Investment Destination | H12: https://www.streetinsider.com/Evertise+Financial/Betterhomes+Reveals+Dubai+as+the+World%E2%80%99s+Premier+Property+Investment+Destination/24196773.html | J12: Betterhomes
A13: =TEXT(B13, "MMMM") -> January | B13: 45670 | C13: Tier 3 | D13: Digital Journal | G13: Betterhomes Reveals Dubai as the World’s Premier Property Investment Destination | H13: https://www.digitaljournal.com/pr/news/vehement-media/betterhomes-reveals-dubai-world-s-premier-1912448123.html | J13: Betterhomes
A14: =TEXT(B14, "MMMM") -> January | B14: 45672 | C14: Tier 1 Local | D14: Arabian Business | E14: 9500 | F14: 250000 | G14: Dubai real estate sets record breaking transaction record with $115bn of sales in 2024; $65.5m villa and $74.8m apartment top charts | H14: https://www.arabianbusiness.com/industries/real-estate/dubai-real-estate-sets-record-breaking-transaction-record-with-115bn-of-sales-in-2024-65-5m-villa-and-74-8m-apartment-top-charts | J14: Betterhomes
A15: =TEXT(B15, "MMMM") -> January | B15: 45672 | C15: Tier 1 Local | D15: Khaleej Times | E15: 2200 | F15: 500000 | G15: Price surge may moderate as Dubai set to add 72,000 housing units | H15: https://www.khaleejtimes.com/business/realty/price-surge-may-moderate-as-dubai-set-to-add-72000-housing-units | J15: Betterhomes
A16: =TEXT(B16, "MMMM") -> January | B16: 45672 | C16: Tier 2 | D16: Zawya | E16: 1000 | F16: 100000 | G16: FY2024 Dubai real estate market highlights: A year of growth and transition | H16: https://www.zawya.com/en/press-release/research-and-studies/fy2024-dubai-real-estate-market-highlights-a-year-of-growth-and-transition-esni838i | J16: Betterhomes
A17: =TEXT(B17, "MMMM") -> January | B17: 45674 | C17: Tier 3 | D17: MENAFN | G17: Price Surge May Moderate As Dubai Set To Add 72,000 Housing Units | H17: https://menafn.com/1109100000/Price-Surge-May-Moderate-As-Dubai-Set-To-Add-72000-Housing-Units | J17: Betterhomes
A18: =TEXT(B18, "MMMM") -> January | B18: 45678 | C18: Tier 1 Local | D18: Gulf News | E18: 1000 | F18: 150000 | G18: Buying freehold property in Dubai: Your guide to securing full ownership | H18: https://gulfnews.com/living-in-uae/housing/how-to-buy-freehold-property-in-dubai-how-to-secure-full-ownership-1.500019993 | J18: Betterhomes
A19: =TEXT(B19, "MMMM") -> January | B19: 45678 | C19: Tier 1 Local | D19: Arabian Business | E19: 9500 | F19: 250000 | G19: Dubai villa rent prices surge 52%, Palm Jumeirah sees biggest spike in 2024: Report | H19: https://www.arabianbusiness.com/industries/real-estate/dubai-villa-rent-prices-surge-52-palm-jumeirah-sees-biggest-spike-in-2024-report | J19: Betterhomes
A20: =TEXT(B20, "MMMM") -> January | B20: 45680 | C20: Tier 1 Local | D20: Arabian Business | E20: 9500 | F20: 250000 | G20: Dubai commercial property market records 24% jump in growth, rakes in $24.5bn in value in 2024 | H20: https://www.arabianbusiness.com/industries/real-estate/dubai-commercial-property-market-records-24-jump-in-growth-rakes-in-24-5bn-in-value-in-2024 | J20: Betterhomes/CRC
A21: =TEXT(B21, "MMMM") -> January | B21: 45680 | C21: Tier 3 | D21: mid east info | G21: FY2024 Dubai Real Estate Market Highlights: A Year of Growth and Transition | H21: https://mid-east.info/fy2024-dubai-real-estate-market-highlights-a-year-of-growth-and-transition/ | J21: Betterhomes
A22: =TEXT(B22, "MMMM") -> January | B22: 45680 | C22: Tier 3 | D22: MENAFN | G22: FY2024 Dubai Real Estate Market Highlights: A Year Of Growth And Transition | H22: https://menafn.com/1109122274/FY2024-Dubai-Real-Estate-Market-Highlights-A-Year-Of-Growth-And-Transition | J22: Betterhomes
A23: =TEXT(B23, "MMMM") -> January | B23: 45682 | C23: Tier 3 | D23: MENAFN | G23: A 23% Rise in Tenant Demand at Betterhomes | H23: https://menafn.com/1109127970/A-23-Rise-in-Tenant-Demand-at-Betterhomes | J23: Betterhomes
A24: =TEXT(B24, "MMMM") -> January | B24: 45684 | C24: Tier 1 Local | D24: Khaleej Times | E24: 2200 | F24: 500000 | G24: Dubai: Tenants move to cheaper areas, lock long-term leases before commercial rental index rollout | H24: https://www.khaleejtimes.com/uae/dubai-tenants-relocating-to-cheaper-areas-securing-long-term-leases-ahead-of-commercial-rental-ind?amp=1 | J24: Betterhomes/CRC
A25: =TEXT(B25, "MMMM") -> January | B25: 45685 | C25: Tier 1 Local | D25: Arabian Business | E25: 9500 | F25: 250000 | G25: Dubai real estate: DLD opens freehold property conversion for Sheikh Zayed Road, Al Jaddaf – everything you need to know | H25: https://www.arabianbusiness.com/industries/real-estate/dubai-real-estate-dld-opens-freehold-property-conversion-for-sheikh-zayed-road-al-jaddaf-everything-you-need-to-know?utm_medium=email&utm_medium=email&utm_campaign=UK%20millionaires%20head%20for%20Dubai%20Abu%20Dhabi%20DLD%20freehold%20property%20conversion%20explainer%20UAE%20BNPL%20platforms%20set%20new%20limit%20081603%20AM&utm_content=UK%20millionaires%20head%20for%20Dubai%20Abu%20Dhabi%20DLD%20freehold%20property%20conversion%20explainer%20UAE%20BNPL%20platforms%20set%20new%20limit%20081603%20AM+CID_1576cdc239b534957231a5f1f1d0dd95&utm_source=Newsletters&utm_term=Dubai%20real%20estate%20DLD%20opens%20freehold%20property%20conversion%20for%20Sheikh%20Zayed%20Road%20Al%20Jaddaf%20%20everything%20you%20need%20to%20know | J25: Betterhomes
A26: =TEXT(B26, "MMMM") -> January | B26: 45685 | C26: Tier 1 Local | D26: Khaleej Times | E26: 2200 | F26: 500000 | G26: Dubai rent hikes to slow down in 2025 as property market set for record supply | H26: https://www.khaleejtimes.com/business/realty/dubai-rent-hikes-to-slow-down-in-2025-as-property-market-set-for-record-supply | J26: Betterhomes
A27: =TEXT(B27, "MMMM") -> January | B27: 45685 | C27: Tier 3 | D27: MENAFN | G27: Dubai Rent Hikes To Slow Down In 2025 As Property Market Set For Record Supply | H27: https://menafn.com/1109137391/Dubai-Rent-Hikes-To-Slow-Down-In-2025-As-Property-Market-Set-For-Record-Supply | J27: Betterhomes
A28: =TEXT(B28, "MMMM") -> January | B28: 45685 | C28: Tier 3 | D28: Press Reader | G28: Tenants shifting to cheaper areas as commercial rental index looms | H28: https://www.pressreader.com/uae/khaleej-times/20250128/281651080785914 | J28: Betterhomes
A29: =TEXT(B29, "MMMM") -> January | B29: 45685 | C29: Tier 3 | D29: MENAFN | G29: 2024 Sees Supply Delays as Developers Set Sights on Record-Breaking 2025 Completions | H29: https://menafn.com/1109138635/2024-Sees-Supply-Delays-as-Developers-Set-Sights-on-Record-Breaking-2025-Completions | J29: Betterhomes
A30: =TEXT(B30, "MMMM") -> January | B30: 45686 | C30: Tier 3 | D30: Press Reader | G30: Record supply likely to ease Dubai rents in ’25 | H30: https://www.pressreader.com/uae/khaleej-times/20250129/281638195886222 | J30: Betterhomes
A31: =TEXT(B31, "MMMM") -> February | B31: 45690 | C31: Tier 3 | D31: MENAFN | G31: Investor Confidence Soars as Off-Plan Dominates Dubai’s Residential Real Estate Market in 2024 | H31: https://www.google.com/url?rct=j&sa=t&url=https://menafn.com/1109155855/Investor-Confidence-Soars-as-Off-Plan-Dominates-Dubais-Residential-Real-Estate-Market-in-2024&ct=ga&cd=CAEYACoUMTU5MzQwNzI3MjY2NzM5MzgzOTkyGmYxMGNhMzlmN2NmNGIzNmM6Y29tOmVuOlVT&usg=AOvVaw2_sIONQqVXBX_dd-Hp5QSc | J31: Betterhomes
A32: =TEXT(B32, "MMMM") -> February | B32: 45691 | C32: Tier 1 Local | D32: Arabian Business | E32: 9500 | F32: 250000 | G32: Dubai real estate: High-end villas, luxury apartments to lead city’s rental price gains in 2025 | H32: https://www.arabianbusiness.com/industries/real-estate/dubai-real-estate-high-end-villas-luxury-apartments-to-lead-citys-rental-price-gains-in-2025 | J32: Betterhomes
A33: =TEXT(B33, "MMMM") -> February | B33: 45692 | C33: Tier 1 Local | D33: Khaleej Times | E33: 2200 | F33: 500000 | G33: Dubai: Most tenants renew leases due to high rents, but this could change; here’s why | H33: https://www.khaleejtimes.com/uae/dubai-most-tenants-renew-leases-due-to-high-rents-but-this-could-change-heres-why | J33: Betterhomes
A34: =TEXT(B34, "MMMM") -> February | B34: 45693 | C34: Tier 3 | D34: Property News Time | G34: Dubai Real Estate Market sets new records in 2024 with AED 423.36 Billion in sales | H34: https://www.propnewstime.com/getdetailsStories/MTQ3MTI=/dubai-real-estate-market-sets-new-records-in-2024-with-aed-423-36-billion-in-sales | J34: Betterhomes
A35: =TEXT(B35, "MMMM") -> February | B35: 45693 | C35: Tier 3 | D35: PressReader.com | G35: Tenants prefer lease renewals as new contracts prove costlier | H35: https://www.pressreader.com/uae/khaleej-times/20250205/281522231784879 | J35: Betterhomes
A36: =TEXT(B36, "MMMM") -> February | B36: 45694 | C36: Tier 3 | D36: Property News Time | G36: Dubai's property market set for 171% rise in completions in 2025 | H36: https://www.propnewstime.com/getdetailsStories/MTQ3MTY=/dubai-s-property-market-set-for-171-rise-in-completions-in-2025 | J36: Betterhomes
A37: =TEXT(B37, "MMMM") -> February | B37: 45694 | C37: Tier 2 | D37: Zawya | E37: 1000 | F37: 100000 | G37: Dubai’s property market kicks off 2025 with a bang: AED 35bln in sales | H37: https://www.zawya.com/en/press-release/research-and-studies/dubais-property-market-kicks-off-2025-with-a-bang-aed-35bln-in-sales-ydbkolcn | J37: Betterhomes
A38: =TEXT(B38, "MMMM") -> February | B38: 45693 | C38: Tier 1 International | D38: The Guardian | E38: 9000 | F38: 700000 | G38: Dubai: Buying the Dream | H38: https://www.theguardian.com/tv-and-radio/2025/feb/05/tv-tonight-the-hilarious-spin-off-from-sharon-horgans-motherland | J38: Betterhomes
A39: =TEXT(B39, "MMMM") -> February | B39: 45695 | C39: Tier 1 Local | D39: Arabian Business | E39: 9500 | F39: 250000 | G39: Dubai real estate: Average prices for apartments, townhouses and villas revealed as sales hit $9.5bn in January | H39: https://www.arabianbusiness.com/industries/real-estate/dubai-real-estate-average-prices-for-apartments-townhouses-and-villas-revealed-as-sales-hit-9-5bn-in-january | J39: Betterhomes
A40: =TEXT(B40, "MMMM") -> February | B40: 45697 | C40: Tier 1 Local | D40: Khaleej Times | E40: 2200 | F40: 500000 | G40: Dubai’s realty off to strong start with Dh35b first month sales | H40: https://www.khaleejtimes.com/business/dubais-realty-off-to-strong-start-with-dh35b-first-month-sales | J40: Betterhomes
A41: =TEXT(B41, "MMMM") -> February | B41: 45698 | C41: Tier 3 | D41: MENAFN | G41: Dubai's Property Market Kicks Off 2025 With A Bang: AED 35 Billion In Sales | H41: https://menafn.com/1109186794/Dubais-Property-Market-Kicks-Off-2025-With-A-Bang-AED-35-Billion-In-Sales#gsc.tab=0 | J41: Betterhomes
A42: =TEXT(B42, "MMMM") -> February | B42: 45698 | C42: Tier 3 | D42: MENAFN | G42: Dubai's Realty Off To Strong Start With Dh35b First Month Sales | H42: https://menafn.com/1109186085/Dubais-Realty-Off-To-Strong-Start-With-Dh35b-First-Month-Sales | J42: Betterhomes
A43: =TEXT(B43, "MMMM") -> February | B43: 45698 | C43: Tier 3 | D43: Property News Time | G43: Dubai's property market begins 2025 with strong sales worth AED 35 billion | H43: https://www.google.com/url?rct=j&sa=t&url=https://propnewstime.com/getdetailsStories/MTQ5ODg%3D/dubai-s-property-market-begins-2025-with-strong-sales-worth-aed-35-billion&ct=ga&cd=CAEYACoUMTA3MjIxOTA0NjEzOTMzMzA1NTQyGmYxMGNhMzlmN2NmNGIzNmM6Y29tOmVuOlVT&usg=AOvVaw321PS3MyvkITJPO_rh2ga8 | J43: Betterhomes
A44: =TEXT(B44, "MMMM") -> February | B44: 45702 | C44: Tier 3 | D44: Economy Middle East | G44: Dubai’s Danube Properties launches game-changing convertible 1BHK apartment at the price of a studio | H44: https://economymiddleeast.com/news/dubai-danube-properties-launches-game-changing-convertible-1bhk-apartment-at-the-price-of-a-studio/ | J44: Betterhomes
A45: =TEXT(B45, "MMMM") -> February | B45: 45705 | C45: Tier 3 | D45: MSN | G45: Dubai villa rented out for Dh15.5 million a year in emirate's largest leasing deal | H45: https://www.msn.com/en-ae/news/featured/dubai-villa-rented-out-for-dh155-million-a-year-in-emirates-largest-leasing-deal/ar-AA1smMdm?apiversion=v2&noservercache=1&domshim=1&renderwebcomponents=1&wcseo=1&batchservertelemetry=1&noservertelemetry=1 | J45: Betterhomes
A46: =TEXT(B46, "MMMM") -> February | B46: 45706 | C46: Tier 3 | D46: GlobalNewsWire | G46: FY2024 Dubai Real Estate Market Highlights: A Year of Growth and Transition | H46: https://www.globenewswire.com/news-release/2025/02/18/3028195/0/en/FY2024-Dubai-Real-Estate-Market-Highlights-A-Year-of-Growth-and-Transition.html | J46: Betterhomes
A47: =TEXT(B47, "MMMM") -> February | B47: 45706 | C47: Tier 3 | D47: Market Insider | G47: FY2024 Dubai Real Estate Market Highlights: A Year of Growth and Transition | H47: https://markets.businessinsider.com/news/stocks/fy2024-dubai-real-estate-market-highlights-a-year-of-growth-and-transition-1034372522
A48: =TEXT(B48, "MMMM") -> February | B48: 45711 | C48: Tier 1 Local | D48: Khaleej Times | E48: 2200 | F48: 500000 | G48: Dubai properties: Developers dismiss concerns around market slowdown in 2025 | H48: https://www.khaleejtimes.com/business/property/dubai-properties-developers-dismiss-concerns-around-market-slowdown-in-2025?amp=1 | J48: Betterhomes
A49: =TEXT(B49, "MMMM") -> February | B49: 45714 | C49: Tier 1 Local | D49: Arabian Business | E49: 9500 | F49: 250000 | G49: Dubai real estate: Ramadan ‘a golden window’ for property market investment, says new report | H49: https://www.arabianbusiness.com/industries/real-estate/dubai-real-estate-ramadan-a-golden-window-for-property-market-investment-says-new-report?utm_medium=email&utm_medium=email&utm_campaign=Ramadan%20a%20golden%20window%20for%20Dubai%20property%20market%20Dubais%20most%20expensive%20schools%20Bitcoin%20plunges%20below%2090000%20094646%20AM&utm_content=Ramadan%20a%20golden%20window%20for%20Dubai%20property%20market%20Dubais%20most%20expensive%20schools%20Bitcoin%20plunges%20below%2090000%20094646%20AM+CID_c10e95892f4d0890707e37add1328e31&utm_source=Newsletters&utm_term=Dubai%20real%20estate%20Ramadan%20a%20golden%20window%20for%20property%20market%20investment%20says%20new%20report | J49: Betterhomes
A50: =TEXT(B50, "MMMM") -> February | B50: 45715 | C50: Tier 2 | D50: Zawya | E50: 1000 | F50: 100000 | G50: Betterhomes awarded Best Real Estate Agency in Arabia at the International Property Awards | H50: https://www.zawya.com/en/press-release/companies-news/betterhomes-awarded-best-real-estate-agency-in-arabia-at-the-international-property-awards-t6ekdgob | J50: Betterhomes
A51: =TEXT(B51, "MMMM") -> March | B51: 45719 | C51: Tier 3 | D51: The Economic Times | G51: Thinking of buying a property in Dubai? Consider FEMA limits, hidden costs, developers and zone-type before taking a call | H51: https://economictimes.indiatimes.com/wealth/real-estate/thinking-of-buying-a-property-in-dubai-consider-fema-limits-hidden-costs-developers-and-zone-type-before-taking-a-call/articleshow/118642147.cms?from=mdr | J51: Betterhomes
A52: =TEXT(B52, "MMMM") -> March | B52: 45719 | C52: Tier 3 | D52: MSN | G52: Meet the owner of Dubai's Burj Khalifa, world's tallest building? Not Sultan of UAE, Dubai king, the name is... | H52: https://www.msn.com/en-in/money/real-estate/meet-the-owner-of-dubai-s-burj-khalifa-world-s-tallest-building-not-sultan-of-uae-dubai-king-the-name-is/ar-AA1zQCjB?ocid=BingNewsVerp&apiversion=v2&noservercache=1&domshim=1&renderwebcomponents=1&wcseo=1&batchservertelemetry=1&noservertelemetry=1 | J52: Betterhomes
A53: =TEXT(B53, "MMMM") -> March | B53: 45721 | C53: Tier 3 | D53: Business Recorder | G53: 2024: Pakistanis among top 5 buyers of real estate in Dubai, Indians top list | H53: https://www.brecorder.com/news/40351232/pakistanis-among-top-5-buyers-of-real-estate-in-dubai-indians-top-list | J53: Betterhomes
A54: =TEXT(B54, "MMMM") -> March | B54: 45726 | C54: Tier 2 | D54: Zawya | E54: 1000 | F54: 100000 | G54: DG 129 now exclusively managed by Betterhomes | H54: https://www.zawya.com/en/press-release/companies-news/dg-129-now-exclusively-managed-by-betterhomes-sfrxelru | J54: Betterhomes
A55: =TEXT(B55, "MMMM") -> March | B55: 45727 | C55: Tier 1 Local | D55: Arabian Business | E55: 9500 | F55: 250000 | G55: Dubai real estate: Betterhomes takes over management of DG 129 in Discovery Gardens | H55: https://www.arabianbusiness.com/industries/real-estate/dubai-real-estate-betterhomes-takes-over-management-of-dg-129-in-discovery-gardens | J55: Betterhomes
A56: =TEXT(B56, "MMMM") -> March | B56: 45727 | C56: Tier 2 | D56: AGBI | E56: 1000 | F56: 30000 | G56: Egyptians show sudden interest in Dubai property | H56: https://www.agbi.com/real-estate/2025/03/egyptians-show-sudden-interest-in-dubai-property/ | J56: Betterhomes
A57: =TEXT(B57, "MMMM") -> March | B57: 45727 | C57: Tier 3 | D57: MENAFN | G57: Dubai’s Real Estate Boom During Ramadan: Why the Market Surges Instead of Slowing | H57: https://menafn.com/1109300107/Dubais-Real-Estate-Boom-During-Ramadan-Why-the-Market-Surges-Instead-of-Slowing | J57: Betterhomes
A58: =TEXT(B58, "MMMM") -> March | B58: 45728 | C58: Tier 1 Local | D58: Khaleej Times | E58: 2200 | F58: 500000 | G58: Dubai: Rent increases slow down as more inventory comes online | H58: https://www.khaleejtimes.com/uae/dubai-rent-rise-slow-down-2025 | J58: Betterhomes
A59: =TEXT(B59, "MMMM") -> March | B59: 45728 | C59: Tier 3 | D59: Aaj TV News | G59: Pakistan ranks fifth among top property buyers in Dubai | H59: https://english.aaj.tv/news/330406793/pakistan-ranks-fifth-among-top-property-buyers-in-dubai | J59: Betterhomes
A60: =TEXT(B60, "MMMM") -> March | B60: 45728 | C60: Tier 3 | D60: Pro Pakistani | G60: Pakistan Ranks Fifth Among Top Property Buyers in Dubai | H60: https://propakistani.pk/2025/03/12/pakistan-ranks-fifth-among-top-property-buyers-in-dubai/#google_vignette | J60: Betterhomes
A61: =TEXT(B61, "MMMM") -> March | B61: 45729 | C61: Tier 1 Local | D61: Gulf News | E61: 1000 | F61: 150000 | G61: Dubai rents: More signs emerge of rent increases slowing down | H61: https://gulfnews.com/business/property/dubai-rents-more-signs-emerge-of-rent-increases-slowing-down-1.500058309 | J61: Betterhomes
A62: =TEXT(B62, "MMMM") -> March | B62: 45729 | C62: Tier 3 | D62: The Globe and Mail | G62: FY2024 Dubai Real Estate Market Highlights: A Year of Growth and Transition | H62: https://www.theglobeandmail.com/investing/markets/markets-news/GetNews/31397304/fy2024-dubai-real-estate-market-highlights-a-year-of-growth-and-transition/ | J62: Betterhomes
A63: =TEXT(B63, "MMMM") -> March | B63: 45729 | C63: Tier 3 | D63: Open PR | G63: FY2024 Dubai Real Estate Market Highlights: A Year of Growth and Transition | H63: https://www.openpr.com/news/3915763/fy2024-dubai-real-estate-market-highlights-a-year-of-growth
A64: =TEXT(B64, "MMMM") -> March | B64: 45729 | C64: Tier 3 | D64: MEED | G64: Dubai property market rebounds in February | H64: https://www.meed.com/dubai-property-market-rebounds-in-february | J64: Betterhomes
A65: =TEXT(B65, "MMMM") -> March | B65: 45731 | C65: Tier 3 | D65: Business Outreach | G65: Dubai Real Estate Market Surges to AED 41 Billion in February Sales | H65: https://www.businessoutreach.in/dubai-real-estate-market-surges-to-aed-41-billion-in-february-sales/ | J65: Betterhomes
A66: =TEXT(B66, "MMMM") -> March | B66: 45731 | C66: Tier 1 Local | D66: Arabian Business | E66: 9500 | F66: 250000 | G66: Dubai real estate: Property sales surge 17% to $11.16bn in February 2025 | H66: https://www.arabianbusiness.com/industries/real-estate/dubai-real-estate-property-sales-surge-17-to-11-16bn-in-february-2025 | J66: Betterhomes
A67: =TEXT(B67, "MMMM") -> March | B67: 45731 | C67: Tier 1 Local | D67: Khaleej Times | E67: 2200 | F67: 500000 | G67: Dubai: New affordable housing project to serve residents across income levels, says top official | H67: https://www.khaleejtimes.com/uae/dubai-affordable-housing-residents-income | J67: Betterhomes
A68: =TEXT(B68, "MMMM") -> March | B68: 45732 | C68: Tier 1 Local | D68: Khaleej Times | E68: 2200 | F68: 500000 | G68: Dubai realty shatters records as prices hit new highs | H68: https://www.khaleejtimes.com/business/property/dubai-realty-shatters-records-as-prices-hit-new-highs | J68: Betterhomes
A69: =TEXT(B69, "MMMM") -> March | B69: 45734 | C69: Tier 3 | D69: Property News Time | G69: Dubai real estate market maintains strong momentum with record prices and rising sales volumes | H69: https://propnewstime.com/getdetailsStories/MTYwNDM=/dubai-real-estate-market-maintains-strong-momentum-with-record-prices-and-rising-sales-volumes | J69: Betterhomes
A70: =TEXT(B70, "MMMM") -> March | B70: 45735 | C70: Tier 1 Local | D70: Khaleej Times | E70: 2200 | F70: 500000 | G70: Egyptians emerge as a rising force in Dubai’s real estate | H70: https://www.khaleejtimes.com/business/property/egyptians-emerge-as-a-rising-force-in-dubais-real-estate | J70: Betterhomes
A71: =TEXT(B71, "MMMM") -> March | B71: 45735 | C71: Tier 1 Local | D71: Arabian Business | E71: 9500 | F71: 250000 | G71: Dubai real estate: Indians, British and Italians lead property purchases as Egyptian numbers surge | H71: https://www.arabianbusiness.com/industries/real-estate/dubai-real-estate-indians-british-and-italians-lead-property-purchases-as-egyptian-numbers-surge | J71: Betterhomes
A72: =TEXT(B72, "MMMM") -> March | B72: 45736 | C72: Tier 2 | D72: The National News | E72: 9300 | F72: 200000 | G72: Big Fed rate cut needed for ‘noticeable’ changes in UAE mortgage borrowing costs | H72: https://www.thenationalnews.com/business/money/2025/03/20/fed-rate-cut-uae-mortgages/ | J72: Betterhomes
A73: =TEXT(B73, "MMMM") -> March | B73: 45737 | C73: Tier 3 | D73: MENAFN | G73: Dubai’s Rental Market Stabilises as Tenant Choices Expand | H73: https://menafn.com/1109342229/Dubais-Rental-Market-Stabilises-as-Tenant-Choices-Expand | J73: Betterhomes
A74: =TEXT(B74, "MMMM") -> March | B74: 45743 | C74: Tier 1 Local | D74: Khaleej Times | E74: 2200 | F74: 500000 | G74: How can we decode the relentless property boom in Dubai? | H74: https://www.khaleejtimes.com/business/property/how-can-we-decode-the-relentless-property-boom-in-dubai | J74: Cencorp/Betterhomes
A75: =TEXT(B75, "MMMM") -> March | B75: 45745 | C75: Tier 1 Local | D75: Arabian Business | E75: 9500 | F75: 250000 | G75: Dubai real estate: Mortgage transactions rise 4.76% as fed holds rates steady | H75: https://www.arabianbusiness.com/industries/real-estate/dubai-real-estate-mortgage-transactions-rise-4-76-as-fed-holds-rates-steady | J75: Betterhomes/Lomond
A76: =TEXT(B76, "MMMM") -> March | B76: 45746 | C76: Tier 1 Local | D76: Arabian Business | E76: 9500 | F76: 250000 | G76: Dubai real estate: Property market records 35.5% surge transactions as off-plan market draws global investors | H76: https://www.arabianbusiness.com/industries/real-estate/dubai-real-estate-property-market-records-35-5-surge-transactions-as-off-plan-market-draws-global-investors | J76: Betterhomes
A77: =TEXT(B77, "MMMM") -> March | B77: 45746 | C77: Tier 1 Local | D77: Khaleej Times | E77: 2200 | F77: 500000 | G77: Mortgage landscape in Dubai remains resilient as Fed holds rates steady | H77: https://www.khaleejtimes.com/business/mortgage-landscape-in-dubai-remains-resilient-as-fed-holds-rates-steady | J77: Betterhomes/Lomond
A78: =TEXT(B78, "MMMM") -> April | B78: 45748 | C78: Tier 2 | D78: The National News | E78: 9300 | F78: 200000 | G78: Chart of the week: Dubai properties deliver more for your million | H78: https://www.thenationalnews.com/news/2025/04/01/chart-of-the-week-dubai-properties-deliver-more-for-your-million/ | J78: Betterhomes
A79: =TEXT(B79, "MMMM") -> April | B79: 45749 | C79: Tier 3 | D79: Property News Time | G79: Dubai's mortgage market remains strong in 2025 amid stable interest rates and high demand | H79: https://propnewstime.com/getdetailsStories/MTY1MDc=/dubai-s-mortgage-market-remains-strong-in-2025-amid-stable-interest-rates-and-high-demand | J79: Betterhomes
A80: =TEXT(B80, "MMMM") -> April | B80: 45754 | C80: Tier 2 | D80: The National News | E80: 9300 | F80: 200000 | G80: Here's what Dh1 million gets you today in Dubai's boom town property market | H80: https://www.thenationalnews.com/news/uae/2025/04/07/dubai-dh1-million-property-market/ | I80: ARTICLELINK | J80: Betterhomes
A81: =TEXT(B81, "MMMM") -> April | B81: 45757 | C81: Tier 1 Local | D81: Khaleej Times | E81: 2200 | F81: 500000 | G81: Dubai: Why global investors are buying more plots of land | H81: https://www.khaleejtimes.com/business/why-are-global-investors-in-dubai-shifting-their-focus-to-plots | J81: Betterhomes
A82: =TEXT(B82, "MMMM") -> April | B82: 45756 | C82: Tier 2 | D82: Zawya | E82: 1000 | F82: 100000 | G82: New real estate trend: Foreign investors in Dubai shift focus from apartments to plots | H82: https://www.zawya.com/en/press-release/research-and-studies/new-real-estate-trend-foreign-investors-in-dubai-shift-focus-from-apartments-to-plots-pgkh4ij0 | J82: Betterhomes
A83: =TEXT(B83, "MMMM") -> April | B83: 45758 | C83: Tier 3 | D83: Press Reader | G83: Global investors shifting focus to plots in Dubai | H83: https://www.pressreader.com/uae/khaleej-times/20250411/281629606101470 | J83: Betterhomes
A84: =TEXT(B84, "MMMM") -> April | B84: 45758 | C84: Tier 3 | D84: Property News Time | G84: Foreign investors in Dubai shift gears as land plots outshine apartments | H84: https://propnewstime.com/getdetailsStories/MTcwNzk=/foreign-investors-in-dubai-shift-gears-as-land-plots-outshine-apartments | J84: Betterhomes
A85: =TEXT(B85, "MMMM") -> April | B85: 45759 | C85: Tier 1 Local | D85: Arabian Business | E85: 9500 | F85: 250000 | G85: Dubai real estate: Property transactions surge 35.5% as off-plan market thrives in 2025 | H85: https://www.arabianbusiness.com/industries/real-estate/dubai-property-2025 | J85: Betterhomes
A86: =TEXT(B86, "MMMM") -> April | B86: 45760 | C86: Tier 1 Local | D86: Khaleej Times | E86: 2200 | F86: 500000 | G86: Offplan transactions drive Dubai real estate growth in first quarter | H86: https://www.khaleejtimes.com/business/offplan-transactions-drive-dubai-real-estate-growth-in-first-quarter | J86: Betterhomes
A87: =TEXT(B87, "MMMM") -> April | B87: 45761 | C87: Tier 3 | D87: The Economic Times | G87: Expats boosted Dubai’s 70% property rally, now Trump's tariffs threaten to undo all gains | H87: https://economictimes.indiatimes.com/nri/invest/dubais-70-property-rally-faces-threat-from-tariff-turmoil/articleshow/120278896.cms?from=mdr | J87: Betterhomes
A88: =TEXT(B88, "MMMM") -> April | B88: 45761 | C88: Tier 1 International | D88: Bloomberg Middle East | E88: 20000 | F88: 300000 | G88: Dubai’s 70% Property Rally Faces Threat From Tariff Turmoil | H88: https://www.bloomberg.com/news/articles/2025-04-14/dubai-property-boom-faces-pressure-as-oil-falls-trump-tariffs-test-demand | J88: Betterhomes
A89: =TEXT(B89, "MMMM") -> April | B89: 45765 | C89: Tier 1 Local | D89: Khaleej Times | E89: 2200 | F89: 500000 | G89: Dubai: Are rents dropping in some communities after double-digit hikes? | H89: https://www.khaleejtimes.com/uae/dubai-rents-drop-post-pandemic-plateau?fbclid=IwY2xjawJuwkBleHRuA2FlbQIxMQABHuMDwAQR3ZZyW3oqSAoTN2PVh_N4ia64InteRYxHTzU_PR_udOCOMoRXNaOD_aem_v6i6qaBtaZ8lRHmBNNTOTg | J89: Betterhomes
A90: =TEXT(B90, "MMMM") -> April | B90: 45766 | C90: Tier 1 International | D90: Forbes Middle East | E90: 20000 | F90: 100000 | G90: Exclusive: Talal Moafaq Al Gaddah On MAG’s $13.6B Push Into Wellness Real Estate | H90: https://www.forbesmiddleeast.com/industry/real-estate/talal-moafaq-al-gaddah
A91: =TEXT(B91, "MMMM") -> April | B91: 45759 | C91: Tier 1 Local | D91: Arabian Business | E91: 9500 | F91: 250000 | G91: Dubai real estate: Is it the right time to invest in the property market? Experts weigh in | H91: https://www.arabianbusiness.com/industries/real-estate/dubai-real-estate-is-it-the-right-time-to-invest-in-the-property-market-experts-weigh-in | J91: Betterhomes
A92: =TEXT(B92, "MMMM") -> April | B92: 45769 | C92: Tier 1 Local | D92: Arabian Business | E92: 9500 | F92: 250000 | G92: Dubai real estate market grows 23% in Q1 2025 as villa sales lead surge: Report | H92: https://www.arabianbusiness.com/industries/real-estate/dubai-real-estate-market-grows-23-in-q1-2025-as-villa-sales-lead-surge-report?utm_medium=email&utm_medium=email&utm_campaign=Dubai%20real%20estate%20market%20up%2023%20Emaar%20invests%201bn%20in%20Dubais%20global%20identity%20Metallica%20in%20Abu%20Dhabi%20081304%20AM&utm_content=Dubai%20real%20estate%20market%20up%2023%20Emaar%20invests%201bn%20in%20Dubais%20global%20identity%20Metallica%20in%20Abu%20Dhabi%20081304%20AM+CID_e7b2d6ef60047341d0b0bf63cf3e4273&utm_source=Newsletters&utm_term=Dubai%20real%20estate%20market%20grows%2023%20in%20Q1%202025%20as%20villa%20sales%20lead%20surge | J92: Betterhomes
A93: =TEXT(B93, "MMMM") -> April | B93: 45769 | C93: Tier 1 Local | D93: Khaleej Times | E93: 2200 | F93: 500000 | G93: Villa market outshines as Dubai realty posts big Q1 sales surge | H93: https://www.khaleejtimes.com/business/villa-market-outshines-as-dubai-realty-posts-big-q1-sales-surge | J93: Betterhomes
A94: =TEXT(B94, "MMMM") -> April | B94: 45770 | C94: Tier 3 | D94: Web Release | G94: Inside Dubai’s Property Surge: Betterhomes Q1 2025 Real Estate Market Insights | H94: https://web-release.com/inside-dubais-property-surge-betterhomes-q1-2025-real-estate-market-insights/ | J94: Betterhomes
A95: =TEXT(B95, "MMMM") -> April | B95: 45770 | C95: Tier 3 | D95: Yahoo Finance | G95: Betterhomes - Record-Breaking Start to 2025 for Dubai Real Estate: Transactions Surge 23% in Q1 | H95: https://finance.yahoo.com/news/betterhomes-record-breaking-start-2025-100800890.html?guccounter=1&guce_referrer=aHR0cHM6Ly93d3cuZ29vZ2xlLmNvbS8&guce_referrer_sig=AQAAAK9ItZrecG5iJiJwnXylExjxK0YMewpPAFuiI7U-C0RgaEOVwdpFnPXekdt5pgHKtCGPTgXwQcrSbfNOV074KfUQ9J-CpkPhHqobtt8s9GOJUOlWHYuxDh3aeNr5PDKjjjFKvl1df2LDFRdYeFdlAVLrKtA1titfIBL1bYoje8oP | J95: Betterhomes
A96: =TEXT(B96, "MMMM") -> April | B96: 45771 | C96: Tier 3 | D96: One Ville News | G96: Betterhomes Cements Its Position as UAE’s Leading Property Management Company with IPS 2025 Win | H96: https://onevillenews.com/2025/04/23/betterhomes-cements-its-position-as-uaes-leading-property-management-company-with-ips-2025-win/ | J96: Betterhomes PMGT
A97: =TEXT(B97, "MMMM") -> April | B97: 45771 | C97: Tier 3 | D97: The Brew News | G97: Dubai property market sees AED 114 billion boom in Q1 2025 | H97: https://thebrewnews.com/thebrew-news/uae/dubai-property-market-q1-2025/ | J97: Betterhomes
A98: =TEXT(B98, "MMMM") -> April | B98: 45771 | C98: Tier 2 | D98: Gulf Business | E98: 5000 | F98: 50000 | G98: Dubai property is booming: What every investor should know | H98: https://gulfbusiness.com/dubai-property-is-booming-what-every-investor-should-know/ | J98: Betterhomes
A99: =TEXT(B99, "MMMM") -> April | B99: 45772 | C99: Tier 3 | D99: Web Release | G99: Betterhomes Cements Its Position as UAE’s Leading Property Management Company with IPS 2025 Win | H99: https://web-release.com/betterhomes-cements-its-position-as-uaes-leading-property-management-company-with-ips-2025-win/ | J99: Betterhomes
A100: =TEXT(B100, "MMMM") -> April | B100: 45773 | C100: Tier 3 | D100: Market Insider | G100: Betterhomes Reports Strong Start to 2025 as Dubai Real Estate Transactions Rise Sharply in First Quarter | H100: https://markets.businessinsider.com/news/stocks/betterhomes-reports-strong-start-to-2025-as-dubai-real-estate-transactions-rise-sharply-in-first-quarter-1034629417 | J100: Betterhomes
...

Sheet Pivot Table 2

Sheet 2023
A1: Date | B1: Media Tier | C1: Media | D1: Title | E1: Link | F1: Brand
A2: 44941 | B2: Tier 1 | C2: Thomson Reuters | D2: Dubai property price rises may slow further in 2023, real-estate consultancy says | E2: https://www.reuters.com/world/middle-east/dubai-property-price-rises-seen-slowing-further-2023-betterhomes-2023-01-15/ | F2: Betterhomes
A3: 44941 | B3: Tier 3 | C3: Latest LY | D3: Dubai Property Price Rises Seen Slowing Further in 2023 - Betterhomes | E3: https://www.latestly.com/socially/sports/cricket/virat-kohli-does-a-ms-dhoni-star-india-batter-hits-helicopter-shot-for-six-in-ind-vs-sl-3rd-odi-2023-watch-video-4716180.html | F3: Betterhomes
A4: 44941 | B4: Tier 3 | C4: Zone Bourse (France) | D4: Dubai property price growth set to slow further in 2023 | E4: https://www.zonebourse.com/actualite-bourse/La-hausse-des-prix-de-l-immobilier-a-Dubai-devrait-encore-ralentir-en-2023-Betterhomes--42738330/?utm_medium=RSS&utm_content=20230115 | F4: Betterhomes
A5: 44941 | B5: Tier 2 | C5: Khaleej Times | D5: Dubai property price rises seen slowing further in 2023: Betterhomes | E5: https://www.khaleejtimes.com/business/dubai-property-price-rises-seen-slowing-further-in-2023-betterhomes | F5: Betterhomes
A6: 44942 | B6: Tier 3 | C6: Manager (Bulgaria) | D6: Russians have become the biggest buyers of luxury properties in Dubai | E6: https://manager.bg/%D0%B1%D0%B8%D0%B7%D0%BD%D0%B5%D1%81/rusnacite-stanaha-nai-golemite-kupuvachi-na-luksozni-imoti-v-dubai | F6: Betterhomes
A7: 44942 | B7: Tier 3 | C7: Titulares (Spain) | D7: Dubai reaches record number of real estate transactions of more than $143,000 million after years of crisis | E7: https://titulares.ar/dubai-alcanza-cifra-record-de-transacciones-inmobiliarias-de-mas-de-143-000-millones-tras-anos-de-crisis/ | F7: Betterhomes
A8: 44942 | B8: Tier 3 | C8: Foco (Spain) | D8: Why did Dubai achieve record real estate transactions in 2022? | E8: https://foco.lanacion.com.py/2023/01/16/por-que-dubai-logro-record-de-transacciones-inmobiliarias-en-2022/ | F8: Betterhomes
A9: 44942 | B9: Tier 2 | C9: Arab News | D9: UAE In-Focus — US, UAE allocate $20bn to fund 15 GW of clean energy projects | E9: https://www.arabnews.com/node/2233301/business-economy | F9: Betterhomes
A10: 44942 | B10: Tier 3 | C10: Dagens Industri (Sweeden) | D10: Russian money drugs Dubai's real estate market - reaches new record level | E10: https://www.di.se/live/ryska-pengar-dopar-dubais-fastighetsmarknad-nar-ny-rekordniva/ | F10: Betterhomes
A11: 44942 | B11: Tier 3 | C11: Finanzemarkt (Germany) | D11: Real estate: That's how massive Russian money is pouring into Dubai | E11: https://finanzmarktwelt.de/immobilien-so-massiv-stroemt-russisches-geld-nach-dubai-258253/ | F11: Betterhomes
A12: 44942 | B12: Tier 3 | C12: Il Matinno (Italy) | D12: Abramovich, Rybolovlev and the others: the anti-sanctions moves. Here's how (and how much) Russian oligarchs invest in Dubai | E12: https://www.ilmattino.it/primopiano/esteri/abramovich_oligarchi_russi_investimenti_dubai_cosa_sta_succedendo-7173231.html | F12: Betterhomes
A13: 44942 | B13: Tier 1 | C13: Forbes (Ukarain) | D13: Property sales in Dubai have risen to a record high due to an increase in the number of buyers from Russia | E13: https://forbes.ua/news/prodazh-nerukhomosti-v-dubai-zris-do-rekordnogo-rivnya-cherez-zbilshennya-kilkosti-pokuptsiv-z-rosii-16012023-11091 | F13: Betterhomes
... A180: 45135 | B180: Tier 2 | C180: Time Out Dubai | D180: House-hunting? Download these real estate apps in Dubai | E180: https://www.timeoutdubai.com/moving-to-dubai/real-estate-apps-in-dubai | F180: Betterhomes
A181: 45136 | B181: Tier 3 | C181: Watson (France) | D181: From Switzerland to Dubai: Russian oligarchs move their money | E181: https://www.watson.ch/fr/economie/russie/982986502-de-la-paradeplatz-a-dubai-les-riches-russes-deplacent-leur-argent
A182: 45137 | B182: Tier 3 | C182: Prian (Russia) | D182: The most Russian districts of Dubai: where investors from the Russian Federation buy real estate | E182: https://prian.ru/pub/samye-russkie-rayony-dubaya-gde-pokupayut-nedvizhimost-investory-iz-rf.html | F182: Betterhomes
A183: 45138 | B183: Tier 2 | C183: The National | D183: What's next for the Dubai property market? | E183: https://www.thenationalnews.com/weekend/2023/07/28/whats-next-for-the-dubai-property-market/ | F183: Betterhomes
A184: 45140 | B184: Tier 2 | C184: Khaleej Times | D184: Rents in Dubai: Up to Dh20,000 discount on fewer cheque payments | E184: https://www.khaleejtimes.com/life-and-living/housing-in-uae/rents-in-dubai-up-to-dh20000-discount-on-fewer-cheque-payments?_refresh=true | F184: Betterhomes
A185: 45140 | B185: Tier 2 | C185: Zawya | D185: Rents in Dubai: Up to $5,500 discount on fewer cheque payments | E185: https://www.zawya.com/en/business/real-estate/rents-in-dubai-up-to-5-500-discount-on-fewer-cheque-payments-snyex3vu | F185: Betterhomes
A186: 45141 | B186: Tier 2 | C186: Khaleej Times | D186: How is off-plan investment different from investing in ready properties? | E186: https://www.khaleejtimes.com/business/how-is-off-plan-investment-different-from-investing-in-ready-properties#:~:text=Unlike%20off%2Dplan%20investments%2C%20ready,in%20the%20completion%20of%20construction. | F186: Betterhomes
A187: 45153 | B187: Tier 1 | C187: CNN | D187: Which is better.. buying or renting real estate? The experts answer | E187: https://cnnbusinessarabic.com/real-estate-construction/34375/%D8%A3%D9%8A%D9%87%D9%85%D8%A7-%D8%A3%D9%81%D8%B6%D9%84-%D8%B4%D8%B1%D8%A7%D8%A1-%D8%A7%D9%84%D8%B9%D9%82%D8%A7%D8%B1%D8%A7%D8%AA-%D8%A3%D9%85-%D8%A7%D8%B3%D8%AA%D8%A6%D8%AC%D8%A7%D8%B1%D9%87%D8%A7%D8%9F-%D8%A7%D9%84%D8%AE%D8%A8%D8%B1%D8%A7%D8%A1-%D9%8A%D8%AC%D9%8A%D8%A8%D9%88%D9%86 | F187: Betterhomes
A188: 45155 | B188: Tier 2 | C188: Mena FN | D188: The Surge Of Custom-Built Villas In Palm Jumeirah: Unveiling The Trend And Its Motivations | E188: https://menafn.com/1106880144/The-Surge-Of-Custom-Built-Villas-In-Palm-Jumeirah-Unveiling-The-Trend-And-Its-Motivations | F188: Betterhomes
A189: 45155 | B189: Tier 2 | C189: Khaleej Times | D189: The Surge Of Custom-Built Villas In Palm Jumeirah: Unveiling The Trend And Its Motivations | E189: https://www.khaleejtimes.com/business/the-surge-of-custom-built-villas-in-palm-jumeirah-unveiling-the-trend-and-its-motivations | F189: Betterhomes
A190: 45155 | B190: Tier 2 | C190: The National | D190: Where are the best places to live in Dubai with children? | E190: https://www.thenationalnews.com/uae/2023/08/24/best-area-live-dubai-family/ | F190: Betterhomes
A191: 45156 | B191: Tier 3 | C191: Russia Matters | D191: Russia in Review | E191: https://www.russiamatters.org/news/russia-review/russia-review-aug-18-25-2023 | F191: Betterhomes
A192: 45156 | B192: Tier 2 | C192: Business Insider | D192: Russia's economic woes have led to a flood of cash and sparked a real estate boom in the United Arab Emirates | E192: https://www.businessinsider.de/politik/international-politics/russlands-wirtschaftliche-probleme-haben-zu-flut-von-bargeld-gefuehrt-und-immobilienboom-in-den-vereinigten-arabischen-emiraten-ausgeloest/ | F192: Betterhomes
A193: 45159 | B193: Tier 1 | C193: The Wall Street Journal | D193: U.A.E. Cashes In on Russia’s Economic Woes | E193: https://www.wsj.com/world/russia/u-a-e-cashes-in-on-russias-economic-woes-52700157 | F193: Betterhomes
... A285: 45285 | B285: Tier 2 | C285: Zawya | D285: Dubai property owners increasingly opting for flipping as prices hit all-time high | E285: https://www.zawya.com/en/business/real-estate/dubai-property-owners-increasingly-opting-for-flipping-as-prices-hit-all-time-high-gowl4ibz | F285: Betterhomes
B471: Tier 2
B472: Tier 2

Sheet 2022
A1: Date | B1: Media Tier | C1: Media | D1: Title | E1: Link | F1: Brand
A2: 44586 | B2: Tier 2 | C2: Zawya | D2: CRC, Betterhomes Group company and Dubai's largest commercial real estate agency, released their 2021 Dubai Commercial Property Market Report | E2: https://www.zawya.com/uae/en/story/amp/ZAWYA20220125075208/ | F2: CRC
A3: 44587 | B3: Tier 2 | C3: Property News | D3: Betterhomes: Dubai real estate at all-time high after banner year in 2021 | E3: https://www.propertynews.ae/general/press-release/betterhomes-dubai-real-estate-at-all-time-high-after-banner-year-in-2021/ | F3: Betterhomes
A4: 44588 | B4: Tier 2 | C4: Khaleej Times | D4: Dubai: Real estate boom to continue; 36,000 residential units to come online in 2022 | E4: https://www.khaleejtimes.com/property/dubai-real-estate-boom-to-continue-36000-residential-units-to-come-online-in-2022 | F4: Betterhomes
A5: 44598 | B5: Tier 2 | C5: Arabian Business | D5: 2021 seen as ‘major turning point’ for Dubai office market after Covid shock | E5: https://www.arabianbusiness.com/industries/real-estate/2021-seen-as-major-turning-point-for-dubai-office-market-after-covid-shock | F5: CRC
A6: 44638 | B6: Tier 2 | C6: The National | D6: Top 7 mistakes to avoid when selling your home | E6: https://www.thenationalnews.com/weekend/2022/03/18/top-7-mistakes-to-avoid-when-selling-your-home/ | F6: Betterhomes
A7: 44669 | B7: Tier 2 | C7: Zawya | D7: Demand and prices on the rise for townhouses and apartments in Q1 2022 | E7: https://www.zawya.com/en/press-release/companies-news/demand-and-prices-on-the-rise-for-townhouses-and-apartments-in-q1-2022-dp9dk0s7 | F7: Betterhomes
A8: 44670 | B8: Tier 2 | C8: Gulf News | D8: In Dubai, villa owners find no takers for sudden price hikes of 10% and more | E8: https://gulfnews.com/business/property/in-dubai-villa-owners-find-no-takers-for-sudden-price-hikes-of-10-and-more-1.1650345406229 | F8: Betterhomes
A9: 44670 | B9: Tier 1 | C9: Bloomberg | D9: Russians Climb Dubai Property Ladder as Sanctions Imperil Wealth | E9: https://www.bloomberg.com/news/articles/2022-04-19/russians-climb-dubai-property-ladder-as-sanctions-imperil-wealth | F9: Betterhomes
A10: 44671 | B10: Tier 2 | C10: Arabian Business | D10: Dubai’s commercial property market soars as post Covid confidence leads to strongest quarter since 2016 | E10: https://www.arabianbusiness.com/money/wealth/money-wealth-real-estate/dubais-commercial-property-market-soars-as-post-covid-confidence-leads-to-strongest-quarter-since-2016 | F10: CRC
A11: 44673 | B11: Tier 2 | C11: The National | D11: Five renovations that could actually lower the value of your home | E11: https://www.thenationalnews.com/weekend/2022/04/22/five-renovations-that-could-actually-lower-the-value-of-your-home/ | F11: Betterhomes
A12: 44676 | B12: Tier 2 | C12: Arab news | D12: Dubai property purchases by Russians up 67% in Q1 of 2022 | E12: https://www.arabnews.com/node/2066971/business-economy | F12: Betterhomes
A13: 44676 | B13: Tier 1 | C13: Bloomberg | D13: Rising Oil Prices a Boon for Saudi Economy | E13: https://www.bloomberg.com/news/newsletters/2022-04-25/rising-oil-prices-a-boon-for-saudi-arabia-s-economy | F13: Betterhomes
... A89: 44783 | B89: Tier 1 | C89: Thomson Reuters | D89: Major Gulf bourses trade mixed; Abu Dhabi at record high | E89: https://www.reuters.com/world/middle-east/major-gulf-bourses-trade-mixed-abu-dhabi-record-high-2022-08-10/ | F89: Betterhomes
A90: 44783 | B90: Tier 2 | C90: Gulf News | D90: As rents rise 20-30%, more Dubai residents see better value in renewing contracts than chase new ones | E90: https://gulfnews.com/business/property/as-rents-rise-20-30-more-dubai-residents-see-better-value-in-renewing-contracts-than-chase-new-ones-1.1660102666420 | F90: Betterhomes | J90: #ef6078ff
A91: 44783 | B91: Tier 3 | C91: Bdnews24 (Bangladesh) | D91: Dubai's biggest bank gives staff a pay rise for inflation | E91: https://bdnews24.com/economy/pg5abbgrnq | F91: Betterhomes
A92: 44783 | B92: Tier 2 | C92: Arab News | D92: MIDEAST STOCKS-Major Gulf bourses trade mixed; Abu Dhabi at record high | E92: https://www.arabnews.com/node/2139816/business-economy | F92: Betterhomes
A93: 44784 | B93: Tier 3 | C93: Financial Investor | D93: Ryan Mahoney (Dubai, UAE): The CRC Commercial Property Market Report FY 2021 | E93: https://www.financialinvestor24.com/property/1903/ryan-mahoney-dubai-uae-the-crc-commercial-property-market-report-fy-2021/ | F93: CRC
A94: 44785 | B94: Tier 2 | C94: The National News | D94: How ‘Fomo’ is driving UAE residents to take out mortgages while they still can | E94: https://www.thenationalnews.com/weekend/2022/08/12/fomo-drives-uae-residents-to-take-out-mortgages-amid-rate-rises/ | F94: Betterhomes
A95: 44785 | B95: Tier 3 | C95: El Correo del Golfo (Spain) | D95: The largest bank in Dubai raises the salary of its employees | E95: https://www.elcorreo.ae/articulo/economia/banco-mas-grande-dubai-sube-sueldo-empleados/20220812090626148406.html | F95: Betterhomes
A96: 44787 | B96: Tier 2 | C96: Khaleej TImes | D96: New tenants to pay higher rents in Dubai | E96: https://www.khaleejtimes.com/business/new-tenants-to-pay-higher-rents-in-dubai | F96: Betterhomes
A97: 44788 | B97: Tier 2 | C97: Zawya | D97: New tenants to pay higher rents in Dubai | E97: https://www.zawya.com/en/business/real-estate/new-tenants-to-pay-higher-rents-in-dubai-tppmufae | F97: Betterhomes
A98: 44789 | B98: Tier 2 | C98: Gulf News | D98: Travelling for a month or two - can I put up my Dubai home for rent? | E98: https://gulfnews.com/living-in-uae/housing/travelling-for-a-month-or-two---can-i-put-up-my-dubai-home-for-rent-1.1660661106061 | F98: STR BH
A99: 44789 | B99: Tier 3 | C99: News Week (US) | D99: Wealthy Russians Are Racing To Buy Homes in Turkey—Here's Why | E99: https://www.newsweek.com/wealthy-russians-racing-buy-homes-turkey-why-explained-1734028 | F99: Betterhomes
A100: 44789 | B100: Tier 3 | C100: The Latest News (Germany) | D100: Wealthy Russians are racing to buy houses in Turkey — here's why | E100: https://www.theaktuellenews.com/nachrichten/wohlhabende-russen-rennen-um-den-kauf-von-haeusern-in-der-tuerkei-hier-ist-der-grund/ | F100: Betterhomes
A101: 44790 | B101: Tier 2 | C101: Zawya | D101: Dubai: Real estate firm’s name, escrow account, other details must on ads | E101: https://www.zawya.com/en/business/real-estate/dubai-real-estate-firms-name-escrow-account-other-details-must-on-ads-axl3oipj | F101: Betterhomes
A102: 44790 | B102: Tier 3 | C102: Ahval (Turkey) | D102: Wealthy Russians vying to purchase homes in Turkey | E102: https://ahvalnews.com/turkish-property/wealthy-russians-vying-purchase-homes-turkey | F102: Betterhomes
... A203: 44926 | B203: Tier 2 | C203: Gulf News | D203: UAE Corporate Tax: Businesses have some early preparations to do | E203: https://gulfnews.com/business/analysis/uae-corporate-tax-businesses-have-some-early-preparations-to-do-1.92961154 | F203: OpenHub

Sheet 2021
A1: Date | B1: Media Tier | C1: Media | D1: Title | E1: Link | F1: Brand
A2: 44197 | B2: - | C2: Better Living Magazine | D2: Hot properties | E2: Print | F2: Betterhomes
A3: 44256 | B3: - | C3: Better Living Magazine | D3: Hot properties | E3: Print | F3: Betterhomes
A4: 44308 | B4: Tier 3 | C4: PR.com | D4: Betterhomes Released Residential Property Market Report Q1 2021 | E4: https://www.pr.com/press-release/835148 | F4: Betterhomes
A5: 44308 | B5: Tier 2 | C5: Khaleej Times | D5: Dubai records 27% surge in Q1 property deals | E5: https://www.khaleejtimes.com/news/dubai-records-27-surge-in-q1-property-deals | F5: Betterhomes
A6: 44308 | B6: Tier 3 | C6: Springfiled properties | D6: Dubai records 27% surge in Q1 property deals | E6: https://www.springfield-re.com/dubai-records-27-surge-in-q1-property-deals | F6: Betterhomes
A7: 44321 | B7: Tier 3 | C7: Creativezone | D7: Dubai Real Estate: A 2021 Promising Outlook | E7: https://www.creativezone.ae/events/dubai-real-estate-a-2021-promising-outlook/ | F7: Betterhomes
A8: 44321 | B8: - | C8: Better Living Magazine | D8: Hot properties | E8: Print | F8: Betterhomes
A9: 44378 | B9: - | C9: Better Living Magazine | D9: Hot properties | E9: Print | F9: Betterhomes
A10: 44411 | B10: Tier 2 | C10: Zawaya | D10: Positive economic & employment sentiment in Dubai boosts property sales in H1 2021 | E10: https://www.zawya.com/uae/en/press-releases/story/Positive_economic__employment_sentiment_in_Dubai_boosts_property_sales_in_H1_2021-ZAWYA20210803062005/ | F10: Betterhomes
A11: 44411 | B11: Tier 2 | C11: Arabian Business | D11: Dubai broker sees surge in British property buyers amid UAE's latest expat incentives | E11: https://www.arabianbusiness.com/real-estate/466741-dubai-broker-sees-surge-in-british-property-buyers-amid-uaes-latest-expat-incentives | F11: Betterhomes
A12: 44411 | B12: Tier 2 | C12: Khaleej Times | D12: Dubai realty back in spotlight with deals hitting 10-year high | E12: https://www.khaleejtimes.com/property/dubai-realty-back-in-spotlight-with-deals-hitting-10-year-high | F12: Betterhomes
A13: 44440 | B13: - | C13: Better Living Magazine | D13: Hot properties | E13: Print | F13: Betterhomes
... A33: 44504 | B33: Tier 2 | C33: Property Finder | D33: Latest Prestige November 2021 issue in Gulf Business | E33: https://www.propertyfinder.ae/hub/agent-guides/latest-prestige-november-2021-issue-in-gulf-business/ | F33: Linda's
A34: 44506 | B34: Tier 2 | C34: The National | E34: https://www.thenationalnews.com/lifestyle/luxury/2021/11/06/dh75m-emirates-hills-villa-becomes-dubais-most-expensive-rental/ | F34: Betterhomes
A35: 44506 | B35: Tier 2 | C35: Radio Eye | D35: Hannah's 7.5m leasinf deal | E35: Business Breakfast | F35: Betterhomes
A36: 44507 | B36: Tier 2 | C36: Construction Week | D36: Betterhomes logs leasing deal at $1.76 million in Emirates Hills | E36: https://www.constructionweekonline.com/business/betterhomes-logs-leasing-deal-at-1-76-million-in-emirates-hills | F36: Betterhomes
A37: 44508 | B37: Tier 3 | C37: The Wall | E37: https://thewall.fyi/dubai-property-broker-seals-record-2m-leasing-deal-for-luxury-villa/ | F37: Betterhomes
A38: 44509 | B38: Tier 3 | C38: International Business Magazine | E38: https://intlbm.com/dubai-real-estate-market-clocks-its-highest-leasing-deal-worth-aed7-5-million/ | F38: Betterhomes
A39: 44509 | B39: Tier 3 | C39: Medium Value Strat | E39: https://medium.com/@valustrat/dh7-5m-emirates-hills-villa-becomes-dubais-most-expensive-rental-fdd55e5c53bd | F39: Betterhomes

Sheet 2024
A1: Date | B1: Media Tier | C1: Media | D1: Cost | E1: Reach | F1: Title | G1: Link | H1: Brand
A2: 45294 | B2: Tier 2 | C2: Construction Week | D2: 3000 | E2: 40000 | F2: The next wave: Top Dubai real estate trends forecasted in 2024 | G2: https://www.constructionweekonline.com/analysis/the-next-wave-top-dubai-real-estate-trends-forecasted-in-2024 | H2: Betterhomes
A3: 45299 | B3: Tier 2 | C3: Arabian Business | D3: 9500 | E3: 250000 | F3: Dubai real estate: Should you buy a timeshare? Experts weigh in | G3: https://www.arabianbusiness.com/industries/real-estate/dubai-real-estate-should-you-buy-a-timeshare-experts-weigh-in?utm_source=onesignal&utm_medium=push-notification&utm_campaign=pushnotification-traffic | H3: Betterhomes
A4: 45301 | B4: Tier 3 | C4: Super Guide Veronica (Netherlands) | F4: Dubai: Buying the Dream | G4: https://www.veronicasuperguide.nl/tv-tips/dubai-buying-the-dream?referrer=https%3A%2F%2Fwww.google.com%2F | H4: Betterhomes
A5: 45303 | B5: Tier 3 | C5: Business Insider India | F5: The Indian rich is buying property in Dubai – Tax benefits to rental yields, the driving forces at play | G5: https://www.businessinsider.in/personal-finance/news/the-indian-rich-is-buying-property-in-dubai-tax-benefits-to-rental-yields-the-driving-forces-at-play/articleshow/106767921.cms | H5: Betterhomes
A6: 45303 | B6: Tier 1 | C6: Mansion Global | D6: 10000 | E6: 1500000 | F6: Indian Buyers Drove International Sales in Dubai Last Year | G6: https://www.mansionglobal.com/articles/mansion-global-daily-tinder-co-founder-selling-modern-los-angeles-mansion-e5ce92bb | H6: Betterhomes
A7: 45306 | B7: Tier 2 | C7: Zawya | D7: 1000 | E7: 100000 | F7: Chestertons MENA appoints Rachel Soriano as Director of Training and Development | G7: https://www.zawya.com/en/press-release/people-in-the-news/chestertons-mena-appoints-rachel-soriano-as-director-of-training-and-development-o6fpwo0i | H7: Betterhomes
A8: 45306 | B8: Tier 3 | C8: Gulf Daily News - Bahrain | F8: Chestertons Mena names new training, development head | G8: https://www.gdnonline.com/Details/1300467 | H8: Betterhomes
A9: 45307 | B9: Tier 3 | C9: minfin.com.ua - Ukraine | F9: Sales of real estate in Dubai worth more than $25 million have doubled in a year | G9: https://minfin.com.ua/ua/2024/01/16/119753042/ | H9: Betterhomes
A10: 45308 | B10: Tier 3 | C10: Super Guide Veronica (Netherlands) | F10: Veronica Superguide's viewing tips for your TV evening: Steenrijk, Straatarm, Dubai: Buying the Dream and DNA Unknown | G10: https://www.veronicasuperguide.nl/nieuws/veronica-superguide-s-kijktips-voor-je-tv-avond-steenrijk-straatarm-dubai-buying-the-dream-en-dna-onbekend | H10: Betterhomes
A11: 45309 | B11: Tier 2 | C11: Khaleej Times | D11: 2200 | E11: 500000 | F11: Dubai property: End-users continue to rise | G11: https://www.khaleejtimes.com/hi/business/dubai-property-end-users-continue-to-rise | H11: Betterhomes
A12: 45310 | B12: Tier 2 | C12: Zawya | D12: 1000 | E12: 100000 | F12: Dubai property: End-users continue to rise | G12: https://www.zawya.com/en/business/real-estate/dubai-property-end-users-continue-to-rise-rhis0tpn | H12: Betterhomes
A13: 45311 | B13: Tier 2 | C13: Arabian Business | D13: 9500 | E13: 250000 | F13: Dubai real estate: Property sales shatter records in 2023 with over 120,000 transactions, says new report | G13: https://www.arabianbusiness.com/industries/real-estate/dubai-real-estate-property-sales-shatter-records-in-2023-with-over-120000-transactions-says-new-report | H13: Betterhomes
A14: 45312 | B14: Tier 3 | C14: Le Petit Journal (France) | F14: Real estate in Dubai: Real estate sales hit records in 2023 | G14: https://lepetitjournal.com/dubai/logement/immobilier-dubai-ventes-immobilieres-records-2023-377186 | H14: Betterhomes
A15: 45313 | B15: Tier 2 | C15: The National News | D15: 9300 | E15: 200000 | F15: One-cheque payments increasingly common in Dubai rental market | G15: https://www.thenationalnews.com/business/property/2024/01/20/one-cheque-payments-increasingly-common-in-dubai-rental-market/ | H15: Betterhomes
A16: 45313 | B16: Tier 2 | C16: Zawya | D16: 1000 | E16: 100000 | F16: Indians, Russians and British buyers are Dubai's top property investors in 2023 | G16: https://www.zawya.com/en/business/real-estate/indians-russians-and-british-buyers-are-dubais-top-property-investors-in-2023-lq6layv5 | H16: Betterhomes
A17: 45313 | B17: Tier 3 | C17: Bol News (Pakistan) | F17: Indians top Dubai real estate market, surpass Russians for first time | G17: https://www.bolnews.com/latest/2024/01/indians-top-dubai-real-estate-market-surpass-russians-for-first-time/ | H17: Betterhomes
A18: 45313 | B18: Tier 3 | C18: Business Recorder (Pakistan) | F18: 2023: Pakistanis remain among top 10 buyers of Dubai property, Indians top list | G18: https://www.brecorder.com/news/40285061 | H18: Betterhomes
A19: 45313 | B19: Tier 2 | C19: The National News | D19: 9300 | E19: 200000 | F19: Dubai developer Deyaar's 2023 profit jumps over threefold on higher revenue | G19: https://www.thenationalnews.com/business/markets/2024/01/22/dubai-developer-deyaars-2023-profit-jumps-over-threefold-on-higher-revenue/ | H19: Betterhomes
A20: 45315 | B20: Tier 2 | C20: The National News | D20: 9300 | E20: 200000 | F20: Dubai developers entice new buyers with favourable payment terms | G20: https://www.thenationalnews.com/business/property/2024/01/24/dubai-developers-entice-new-buyers-with-favourable-payment-terms/ | H20: Betterhomes
A21: 45315 | B21: Tier 2 | C21: The National News | D21: 9300 | E21: 200000 | F21: Golden visas: UAE 'cancels minimum down payment' for property investors | G21: https://www.thenationalnews.com/business/money/2024/01/24/golden-visa-dubai-property/ | H21: Betterhomes
A22: 45315 | B22: Tier 2 | C22: What's On | F22: UAE Golden Visa: Minimum down-payment no longer required for property investors | G22: https://whatson.ae/2024/01/uae-golden-visa-minimum-down-payment-no-longer-required-for-property-investors/ | H22: Betterhomes
A23: 45317 | B23: Tier 3 | C23: Investing.com | F23: Analysis-Dubai's property boom shows signs of fizzling out | G23: https://www.investing.com/news/stock-market-news/analysisdubais-property-boom-shows-signs-of-fizzling-out-3283664 | H23: Betterhomes
A24: 45317 | B24: Tier 1 | C24: Reuters | D24: 20000 | E24: 1000000 | F24: Dubai's property boom shows signs of fizzling out | G24: https://www.reuters.com/world/middle-east/dubais-property-boom-shows-signs-fizzling-out-2024-01-26/ | H24: Betterhomes
A25: 45317 | B25: Tier 3 | C25: The Edge Malaysia | F25: Dubai's property boom shows signs of fizzling out | G25: https://www.investing.com/news/stock-market-news/analysisdubais-property-boom-shows-signs-of-fizzling-out-3283664 | H25: Betterhomes
A26: 45317 | B26: Tier 3 | C26: IG (Ishradgul News) | F26: Dubai property boom shows signs of abating – Business & Finance IG News | G26: https://irshadgul.com/dubai-property-boom-shows-signs-of-abating-business-finance-ig-news/ | H26: Betterhomes
A27: 45317 | B27: Tier 3 | C27: Pi | F27: Dubai property boom shows signs of abating – Business & Finance IG News | G27: https://proiqra.com/dubais-real-estate-boom-shows-signs-of-faltering-business-finance-pi-news/ | H27: Betterhomes
A28: 45318 | B28: Tier 3 | C28: Gulf -Times | F28: Dubai’s property boom shows signs of fizzling out | G28: https://www.gulf-times.com/article/676262/opinion/dubais-property-boom-shows-signs-of-fizzling-out | H28: Betterhomes
A29: 45321 | B29: Tier 2 | C29: Zawya | D29: 1000 | E29: 100000 | F29: Top property management companies for renting homes in Dubai: who are they and why are they needed? | G29: https://www.zawya.com/en/press-release/research-and-studies/top-property-management-companies-for-renting-homes-in-dubai-who-are-they-and-why-are-they-needed-j3lw28q2 | H29: Betterhomes
A30: 45324 | B30: Tier 2 | C30: The National News | D30: 9300 | E30: 200000 | F30: Moving to a new home: Here's what you need to know about rent and utility bills | G30: https://www.thenationalnews.com/uae/2024/02/02/moving-to-a-new-home-heres-what-you-need-to-know-about-rent-and-utility-bills/ | H30: Betterhomes
A31: 45327 | B31: Tier 2 | C31: Khaleej Times | D31: 2200 | E31: 500000 | F31: UAE: Despite traffic, tenants move to bigger units in same emirate to enhance lifestyle | G31: https://www.khaleejtimes.com/business/realty/uae-despite-traffic-tenants-move-to-bigger-units-in-same-emirate-to-enhance-lifestyle | H31: Betterhomes
A32: 45327 | B32: Tier 3 | C32: Times Now (India) | F32: Is Dubai's Property Market Surge Fuelled By Indian Investors? | G32: https://www.timesnownews.com/india/is-dubais-property-market-surge-fuelled-by-indian-investors-article-107430142 | H32: Betterhomes
A33: 45338 | B33: Tier 2 | C33: CBS4 News | F33: Leading Real Estate Experts to Headline IPS 2024 | G33: https://cbs4indy.com/business/press-releases/ein-presswire/689099087/leading-real-estate-experts-to-headline-ips-2024/ | H33: Betterhomes
A34: 45340 | B34: Tier 2 | C34: Khaleej Times | D34: 2200 | E34: 500000 | F34: UAE: Golden Visa demand growing among European property investors | G34: https://www.khaleejtimes.com/business/realty/uae-golden-visa-demand-growing-among-european-property-investors
A35: 45340 | B35: Tier 3 | C35: Menafn | F35: Leading Real Estate Experts to Headline IPS 2024 | G35: https://menafn.com/1107865247/Leading-Real-Estate-Experts-to-Headline-IPS-2024
A36: 45344 | B36: Tier 2 | C36: Khaleej Times | D36: 2200 | E36: 500000 | F36: Up to 200% price increase: Why Dubai property buyers are now selling homes | G36: https://www.khaleejtimes.com/business/realty/up-to-200-return-dubai-property-turning-sellers-market-as-investors-take-advantage-of-3-year-pric | H36: Betterhomes
A37: 45344 | B37: Tier 2 | C37: The Circuit | F37: Russian buyers and a post-pandemic bump have also spurred house sales in the UAE. | G37: https://circuit.news/2024/02/22/dubai-now-a-sellers-market-after-surge-in-property-transactions/ | H37: Betterhomes
A38: 45344 | B38: Tier 2 | C38: The Circuit | F38: The Daily Circuit | G38: https://circuit.news/2024/02/22/the-daily-circuit-dubai-property-a-sellers-market-qatar-fishes-for-startups/ | H38: Betterhomes
A39: 45345 | B39: Tier 2 | C39: Akhbrna News | F39: Dubai announces up to a 200% increase in property prices | G39: https://english.akhbrna.co/uae-news/dubai-announces-up-to-a-200 | H39: Betterhomes
A40: 45345 | B40: Tier 3 | C40: PressReader | F40: Covid property buyer reap profit | G40: PressReader.com - Digital Newspaper & Magazine Subscriptions | H40: Betterhomes
A41: 45349 | B41: Tier 2 | C41: Arabian Business | D41: 9500 | E41: 250000 | F41: Dubai real estate: As off-plan property sales are booming, which are the best areas to invest in? | G41: https://www.arabianbusiness.com/industries/real-estate/dubai-real-estate-as-off-plan-property-sales-are-booming-which-are-the-best-areas-to-invest-in | H41: Betterhomes
A42: 45351 | B42: Tier 3 | C42: Finance Middle East | F42: Will Dubai continue its trend of record-breaking real estate transactions in 2024? | G42: https://www.financemiddleeast.com/__trashed/ | H42: Betterhomes
A43: 45357 | B43: Tier 2 | C43: Khaleej Times | D43: 2200 | E43: 500000 | F43: Dubai revises Rera calculator: Residents may see up to 20% increase in rent | G43: https://www.khaleejtimes.com/business/realty/dubai-rera-calculator-updated-will-rents-rise | H43: Betterhomes
A44: 45357 | B44: Tier 2 | C44: Zawya | D44: 1000 | E44: 100000 | F44: Dubai Rera calculator updated: Will rents rise? | G44: https://www.zawya.com/en/business/real-estate/dubai-rera-calculator-updated-will-rents-rise-woe9duj0 | H44: Betterhomes
A45: 45357 | B45: Tier 3 | C45: Business Outreach | F45: How Dubai’s Updated Rental Calculator Could Impact Tenants and Rents | G45: https://www.businessoutreach.in/how-dubais-updated-rental-calculator | H45: Betterhomes
A46: 45357 | B46: Tier 2 | C46: BNN Breaking | F46: Dubai's RERA Index Update Signals Rent Increases for Long-term Tenants: Insights from Industry Expert | G46: Dubai's RERA Index Update Signals Rent Increases for Long-term Ten… (bnnbreaking.com) | H46: Betterhomes
A47: 45357 | B47: Tier 3 | C47: MSN | F47: Dubai Rera calculator updated: Will rents rise? | G47: Dubai Rera calculator updated: Will rents rise? (msn.com) | H47: Betterhomes
A48: 45358 | B48: Tier 3 | C48: samaa.tv | F48: Dubai revised rents leave landlords happy, tenants sad | G48: https://www.samaa.tv/2087310962-dubai-revised-rents-leave-landlords-happy-tenants-sad | H48: Betterhomes
A49: 45360 | B49: Tier 2 | C49: The National News | D49: 9300 | E49: 200000 | F49: Dubai tenants face higher rents after Rera calculator reset | G49: https://www.thenationalnews.com/business/property/2024/03/09/dubai-tenants-face-higher-rents-after-rera-calculator-reset/ | H49: Betterhomes
A50: 45361 | B50: Tier 3 | C50: AGBI | F50: UAE businesses dispute predicted Ramadan downturn | G50: https://www.agbi.com/analysis/food-drink/2024/03/uae-businesses-dispute-predicted-ramadan-downturn/ | H50: Betterhomes
A51: 45362 | B51: Tier 2 | C51: Zawya | D51: 1000 | E51: 100000 | F51: Bayut recognises the "Real heroes of real estate" at the Bayut Awards 2023 | G51: https://www.zawya.com/en/press-release/events-and-conferences/bayut-recognises-the-real-heroes-of-real-estate-at-the-bayut-awards-2023-o8x8amf8 | H51: Betterhomes
A52: 45363 | B52: Tier 2 | C52: Dubai Chronicle | F52: Sterling Capital Real Estate Announces Its Premier Launch in Dubai | G52: https://www.dubaichronicle.com/2024/03/12/sterling-capital-real-estate-announces-its-premier-launch-in-dubai/ | H52: Betterhomes
A53: 45364 | B53: Tier 3 | C53: The Eastern Herald (India) | F53: Indians become largest real estate investors in Dubai | G53: https://easternherald.com/2024/03/12/indians-largest-real-estate-investors-dubai/ | H53: Betterhomes
A54: 45364 | B54: Tier 2 | C54: Khaleej Times | D54: 2200 | E54: 500000 | F54: Dubai to increase property sizes after change in Golden Visa criteria sparks demand | G54: https://www.khaleejtimes.com/business/realty/dubai-golden-visa-demand-prompts-investors-to-raise-budget-developers-to-increase-unit-sizes | H54: Betterhomes
A55: 45367 | B55: Tier 2 | C55: Arabian Business | D55: 9500 | E55: 250000 | F55: Dubai real estate: Should you invest in a villa, townhouse or apartment in 2024? Experts weigh in | G55: https://www.arabianbusiness.com/industries/real-estate/dubai-real-estate-should-you-invest-in-a-villa-townhouse-or-apartment-in-2024-experts-weigh-in | H55: Betterhomes
A56: 45368 | B56: Tier 3 | C56: Zawya | F56: Dubai: 5 most attractive off-plan investment opportunities in 2024 revealed | G56: https://www.zawya.com/en/business/real-estate/dubai-5-most-attractive-off-plan-investment-opportunities-in-2024-revealed-e8lr69xq | H56: Betterhomes
A57: 45368 | B57: Tier 3 | C57: MenaFn | F57: Dubai: 5 most attractive off-plan investment opportunities in 2024 revealed | G57: https://menafn.com/1107986712/Dubai-5-Most-Attractive-Off-Plan-Investment-Opportunities-In-2024-Revealed | H57: Betterhomes
A58: 45368 | B58: Tier 2 | C58: Khaleej Times | D58: 2200 | E58: 500000 | F58: Dubai: 5 most attractive off-plan investment opportunities in 2024 revealed | G58: https://www.khaleejtimes.com/business/realty/dubai-5-most-attractive-off-plan-investment-opportunities-in-2024-revealed | H58: Betterhomes
A59: 45370 | B59: Tier 3 | C59: Gulf News (online + print) | F59: Sharjah's new draft property law: Will a rental index replace current leasing terms? | G59: https://gulfnews.com/business/property/sharjahs-new-draft-property-law-will-a-rental-index-replace-current-leasing-terms-1.1710821855670 | H59: Betterhomes
A60: 45372 | B60: Tier 3 | C60: AGBI | F60: Dubai mortgage holders squeezed by end of low fixed rates | G60: https://www.agbi.com/real-estate/2024/03/dubai-mortgage-holders-squeezed-by-end-of-low-fixed-rates/ | H60: Lomond
A61: 45373 | B61: Tier 3 | C61: Finance Middle East | F61: Dubai’s top 11 high-yield investment hotspots unveiled | G61: https://www.financemiddleeast.com/dubais-top-11-high-yield-investment-hotspots-unveiled/ | H61: Betterhomes
A62: 45373 | B62: Tier 3 | C62: Finance Middle East - Lnkd | F62: Dubai’s bustling property sector | G62: https://www.linkedin.com/feed/update/urn:li:activity:7176805898206470145/ | H62: Betterhomes
A63: 45375 | B63: Tier 2 | C63: Khaleej Times | D63: 2200 | E63: 500000 | F63: Dubai: Rent-free months, other incentives dwindle for tenants amid high occupancy | G63: https://www.khaleejtimes.com/uae/dubai-rent-free-months-other-incentives-dwindle-for-tenants-amid-high-occupancy | H63: Betterhomes
A64: 45376 | B64: Tier 3 | C64: AGBI | F64: What Dubai’s united nations of property buyers want | G64: https://www.agbi.com/analysis/real-estate/2024/03/what-dubais-united-nations-of-property-buyers-want/ | H64: Betterhomes
A65: 45377 | B65: Tier 3 | C65: CW-Property | F65: CW Property presents Cityscape Conversation: Betterhomes Louis Harding confirmed as a speaker | G65: https://property.constructionweekonline.com/cw-property-presents-cityscape-conversation-betterhomes-louis-harding-confirmed-as-a-speaker/ | H65: Betterhomes
A66: 45379 | B66: Tier 1 | C66: Bloomberg | D66: 20000 | E66: 600000 | F66: Dubai Is Losing Its Allure For Wealthy Russians | G66: https://www.bloomberg.com/news/articles/2024-03-28/dubai-s-glitz-dims-for-russians-on-costs-us-sanction-pressures | H66: Betterhomes
A67: 45379 | B67: Tier 3 | C67: Osul Misr | F67: Dubai’s Glitz Dims for Russians On Costs، US Sanction Pressures | G67: https://www.osoulmisrmagazine.com/376544 | H67: Betterhomes
A68: 45388 | B68: Tier 2 | C68: AGBI | D68: 1000 | E68: 30000 | F68: Dubai developers tempt off-plan buyers with 1% payment | G68: https://www.agbi.com/analysis/real-estate/2024/04/dubai-developers-tempt-off-plan-buyers-with-1-percent-payment/ | H68: Offplan
A69: 45389 | B69: Tier 3 | C69: MSN.com | F69: Why are Indians keen to acquire expensive properties in Dubai and London? | G69: https://www.msn.com/en-in/money/topstories/why-are-indians-keen-to-acquire-expensive-properties-in-dubai-and-london/ar-BB1lcYQF | H69: Betterhomes
A70: 45390 | B70: Tier 2 | C70: Arabian Business | D70: 9500 | E70: 250000 | F70: Dubai real estate: Best property type to sell in 2024, experts reveal | G70: https://arabianbusiness.com/industries/real-estate/dubai-real-estate-best-property-type-to-sell-in-2024-experts-reveal | H70: Betterhomes
A71: 45390 | B71: Tier 2 | C71: What's On | F71: The first boxing event is taking place at Burj Khalifa this April | G71: https://whatson.ae/2024/04/the-first-boxing-event-is-taking-place-at-burj-khalifa-this-april/ | H71: Betterhomes
A72: 45392 | B72: Tier 2 | C72: Curly Tales | F72: This April, Dubai’s Burj Khalifa Will Host Its First Boxing Event At The Armani Pavilion | G72: https://curlytales.com/this-april-dubais-burj-khalifa-will-host-its-first-boxing-event-at-the-armani-pavilion/ | H72: Betterhomes
A73: 45392 | B73: Tier 3 | C73: The Siasat Daily | F73: Dubai’s Burj Khalifa set to host 1st-ever boxing event on April 21 | G73: https://www.siasat.com/dubais-burj-khalifa-set-to-host-1st-ever-boxing-event-on-april-21-3006904/ | H73: Betterhomes
A74: 45397 | B74: Tier 2 | C74: Arabian Business | D74: 9500 | E74: 250000 | F74: Dubai real estate: Indian investors spark new round of growth in property market, driven by 5-year visit visa | G74: https://www.arabianbusiness.com/industries/real-estate/dubai-real-estate-indian-investors-spark-new-round-of-growth-in-property-market-driven-by-5-year-visit-visa | H74: Betterhomes
A75: 45399 | B75: Tier 2 | C75: AGBI | D75: 1000 | E75: 30000 | F75: Rising prices risk making Dubai homes ‘unattainable’ | G75: https://www.agbi.com/analysis/real-estate/2024/04/dubai-rising-prices-risk-making-homes-unattainable-many/
A76: 45401 | B76: Tier 1 | C76: Yahoo | D76: 5000 | E76: 5000000 | F76: Dubai boom sees Russian cash, high rents and reborn projects | G76: https://ca.movies.yahoo.com/movies/dubai-boom-sees-russian-cash-071659155.html?guccounter=1&guce_referrer=aHR0cHM6Ly93d3cuZ29vZ2xlLmNvbS8&guce_referrer_sig=AQAAAAksfQY9lqCVuzDxRNuQ6bntXNfTntSlpG9B9Pc8Qyseiy1edDZ2i3eKN9M05DcF9V6jpIerCaDu00Y2AIXEeXb_YoeS4hWDrH3agmrBNQDKoNy-I8Rgtt8Sg8dcRChIsfFRvd0mzNZrbuSBVXH3L6v-AvC53XrDOpVoKsHlD6kl | H76: Betterhomes
A77: 45404 | B77: Tier 1 | C77: Bloomberg | D77: 20000 | E77: 600000 | F77: Russians Transform Dubai as They Flee Putin’s War: Photo Essay | G77: https://www.bloomberg.com/news/articles/2024-04-22/russians-transform-dubai-as-they-flee-putin-s-war-photo-essay | H77: Betterhomes
A78: 45406 | B78: Tier 2 | C78: Khaleej Times | D78: 2200 | E78: 500000 | F78: UAE: Landlords, developers to bear main cost of property damages after extreme weather | G78: https://www.khaleejtimes.com/uae/uae-landlords-developers-to-bear-primary-cost-for-property-damages-after-extreme-weather | H78: Betterhomes
A79: 45410 | B79: Tier 2 | C79: Arabian Business | D79: 9500 | E79: 250000 | F79: Dubai real estate: Property market shatters records with over 30,000 transactions in Q1 2024 | G79: https://www.arabianbusiness.com/industries/real-estate/dubai-real-estate-property-market-shatters-records-with-over-30000-transactions-in-q1-2024 | H79: Betterhomes
A80: 45410 | B80: Tier 3 | C80: Zawya | F80: Dubai: Why property prices, rentals will continue to rise next year also | G80: https://www.zawya.com/en/business/real-estate/dubai-why-property-prices-rentals-will-continue-to-rise-next-year-also-s7t8me42 | H80: Betterhomes
A81: 45410 | B81: Tier 2 | C81: Khaleej Times | D81: 2200 | E81: 500000 | F81: Dubai: Why property prices, rentals will continue to rise next year also | G81: https://www.khaleejtimes.com/uae/dubai-why-property-prices-rentals-will-continue-to-rise-next-year-also | H81: Betterhomes
A82: 45411 | B82: Tier 3 | C82: MENAFN | F82: Dubai: Tenants Prefer Online Bank Payments Over Cheques As Rents Rise | G82: https://menafn.com/1108149482/Dubai-Tenants-Prefer-Online-Bank-Payments-Over-Cheques-As-Rents-Rise | H82: Betterhomes
A83: 45411 | B83: Tier 2 | C83: Khaleej Times | D83: 2200 | E83: 500000 | F83: Dubai: Tenants Prefer Online Bank Payments Over Cheques As Rents Rise | G83: https://www.khaleejtimes.com/business/dubai-tenants-prefer-online-bank-payments-over-cheques-as-rents-rise | H83: Betterhomes
A84: 45411 | B84: Tier 2 | C84: Khaleej Times | D84: 2200 | E84: 500000 | F84: Dubai: Some landlords seek minimum lease duration as rentals continue upward trend | G84: https://www.khaleejtimes.com/business/realty/dubai-some-landlords-seek-minimum-lease-duration-as-rentals-continue-upward-trend | H84: Betterhomes
A85: 45411 | B85: Tier 3 | C85: Zawya | F85: Dubai: Some landlords seek minimum lease duration as rentals continue upward trend | G85: https://www.zawya.com/en/business/real-estate/dubai-some-landlords-seek-minimum-lease-duration-as-rentals-continue-upward-trend-kuh2n3l1 | H85: Betterhomes
A86: 45411 | B86: Tier 3 | C86: Zawya | F86: Dubai: Tenants Prefer Online Bank Payments Over Cheques As Rents Rise | G86: https://www.zawya.com/en/business/real-estate/dubai-tenants-prefer-online-bank-payments-over-cheques-as-rents-rise-nhzntvtp | H86: Betterhomes
A87: 45414 | B87: Tier 2 | C87: Arabian Business | D87: 9500 | E87: 250000 | F87: Dubai real estate: British investors overtake Indians, Russians in record numbers as they flock to UAE for Golden Visas, tax-free luxury living | G87: https://www.arabianbusiness.com/industries/real-estate/dubai-real-estate-british-investors-overtake-indians-russians-in-record-numbers-as-they-flock-to-uae-for-golden-visas-tax-free-luxury-living | H87: Betterhomes
A88: 45414 | B88: Tier 3 | C88: MENAFN | F88: UAE: New Airport Plan To Drive Property Demand, Prices In Dubai South | G88: https://menafn.com/1108168001/UAE-New-Airport-Plan-To-Drive-Property-Demand-Prices-In-Dubai-South | H88: Betterhomes
A89: 45414 | B89: Tier 2 | C89: Khaleej Times | D89: 2200 | E89: 500000 | F89: UAE: New Airport Plan To Drive Property Demand, Prices In Dubai South | G89: https://www.khaleejtimes.com/uae/uae-new-airport-plan-to-to-drive-property-demand-prices-in-dubai-south | H89: Betterhomes
A90: 45414 | B90: Tier 2 | C90: Zawya | D90: 1000 | E90: 100000 | F90: UAE: New Airport Plan To Drive Property Demand, Prices In Dubai South | G90: https://www.zawya.com/en/business/real-estate/uae-new-airport-plan-to-drive-property-demand-prices-in-dubai-south-adz9afik | H90: Betterhomes
A91: 45418 | B91: Tier 2 | C91: CW-Property | F91: Why are Dubai buyers snapping up homes worth millions in record time? | G91: https://property.constructionweekonline.com/why-are-dubai-buyers-snapping-up-homes-worth-millions-in-record-time/ | H91: Betterhomes
A92: 45418 | B92: Tier 2 | C92: Arabian Business | D92: 9500 | E92: 250000 | F92: Dubai real estate: JVC, Dubai Marina popularity booms as British buyers hunt for affordable apartments | G92: https://www.arabianbusiness.com/industries/real-estate/dubai-real-estate-jvc-dubai-marina-popularity-booms-as-british-buyers-hunt-for-affordable-apartments | H92: Betterhomes
A93: 45419 | B93: Tier 2 | C93: Yahoo | F93: Russia's MTS bank has UAE licence -central bank website | G93: https://ca.movies.yahoo.com/finance/news/russias-mts-bank-uae-licence-093910337.html | H93: Betterhomes
A94: 45420 | B94: Tier 2 | C94: Zawya | D94: 1000 | E94: 100000 | F94: CRC reveals top office areas in Q1 2024 | G94: https://www.zawya.com/en/press-release/research-and-studies/crc-reveals-top-office-areas-in-q1-2024-jls7jcgj | H94: CRC
A95: 45421 | B95: Tier 2 | C95: Arabian Business | D95: 9500 | E95: 250000 | F95: Dubai residents stop renting, start buying as mortgage payments start to ‘match’ rental costs: Experts | G95: https://www.arabianbusiness.com/industries/real-estate/dubai-residents-stop-renting-start-buying-as-mortgage-payments-start-to-match-rental-costs-experts | H95: Betterhomes
A96: 45421 | B96: Tier 2 | C96: CW-Property | F96: Revealed: Top 4 locations driving office demand in Dubai | G96: https://property.constructionweekonline.com/revealed-top-4-locations-driving-office-demand-in-dubai/ | H96: CRC
A97: 45423 | B97: Tier 2 | C97: Arabian Business | D97: 9500 | E97: 250000 | F97: Dubai real estate: Commercial property market sees growth in Q1 2024 | G97: https://www.arabianbusiness.com/industries/real-estate/dubai-real-estate-commercial-property-market-sees-growth-in-q1-2024 | H97: CRC
A98: 45424 | B98: Tier 3 | C98: MenaFN | F98: Dubai: New Office Spaces Being Pre-Leased As Demand Outstrips Supply | G98: https://menafn.com/1108203482/Dubai-New-Office-Spaces-Being-Pre-Leased-As-Demand-Outstrips-Supply | H98: CRC
A99: 45426 | B99: Tier 3 | C99: Business Recorder | F99: ‘Dubai Unlocked’: Pakistanis own properties worth $11bn in emirate city, report says | G99: https://www.brecorder.com/news/40303406 | H99: Betterhomes
A100: 45428 | B100: Tier 3 | C100: CW-Property | F100: Indian investors drive Dubai real estate boom | G100: https://property.constructionweekonline.com/indian-investors-drive-dubai-real-estate-boom/ | H100: Betterhomes
...

Sheet 2020
A1: Date | B1: Media Tier | C1: Media | D1: Title | E1: Link | F1: Brand
A2: 43935 | B2: - | C2: Trade Arabia | D2: Business as usual for movers in Dubai amid lockdown | E2: http://tradearabia.com/news/CONS_366645.html | F2: Betterhomes
A3: 44009 | B3: - | C3: Khaleej Times | D3: Residential rents in Dubai see a sharp drop, especially in these areas | E3: https://www.khaleejtimes.com/business/real-estate/residential-rents-in-dubai-see-a-sharp-drop-especially-in-these-areas-- | F3: Betterhomes
A4: 44042 | B4: - | C4: Zawaya | D4: How Dubai's new Route 2020 will drive demand for residential, commercial properties | E4: https://www.zawya.com/mena/en/business/story/How_Dubais_new_Route_2020_will_drive_demand_for_residential_commercial_properties-ZAWYA20200730052256/ | F4: Betterhomes
A5: 44105 | B5: - | C5: Gulf News | D5: Living in Jumeirah meant compounds with common pools, says Dubai’s villa lady | E5: https://gulfnews.com/business/property/living-in-jumeirah-meant-compounds-with-common-pools-says-dubais-villa-lady-1.1601554872716 | F5: Betterhomes
A6: 44109 | B6: - | C6: Construction Week | D6: Podcast: Dubai's new brokerage for working mothers | E6: https://www.constructionweekonline.com/business/267754-podcast-dubais-new-brokerage-for-working-mothers | F6: Betterhomes
A7: 43831 | B7: - | C7: Arabian Business | D7: The best of the best: All the major award winners from 2019 | E7: https://www.arabianbusiness.com/events/436138-the-best-of-the-best-all-the-major-award-winners-from-2019 | F7: Betterhomes
A8: 43920 | B8: - | C8: Arabian Business | D8: Coronavirus: What impact will Covid-19 have on Dubai's property market? | E8: https://www.arabianbusiness.com/property/443757-coronavirus-what-impact-will-covid-19-have-on-dubais-property-market | F8: Betterhomes
A9: 43915 | B9: - | C9: Global Business Outlook | D9: Dubai real estate market ‘will tremendously improve after Covid-19 | E9: https://www.globalbusinessoutlook.com/dubai-real-estate-market-will-tremendously-improve-after-covid-19/ | F9: Betterhomes
A10: 44091 | B10: - | C10: Euonews | D10: Gauging the impact of the global pandemic on the Real Estate market in Dubai | E10: https://www.euronews.com/2020/09/16/gauging-the-impact-of-the-global-pandemic-on-the-real-estate-market-in-dubai | F10: Betterhomes
A11: 44137 | B11: - | C11: Gulf News | D11: Dubai homeowner increased value of property with effective landscaping | E11: https://gulfnews.com/business/property/dubai-homeowner-increased-value-of-property-with-effective-landscaping-1.1604301168796 | F11: Betterhomes
A12: 43947 | B12: - | C12: Property Finder Blog | D12: Renting and Moving During Times of Crisis | E12: https://www.propertyfinder.ae/blog/renting-and-moving-during-crisis/ | F12: Betterhomes
A13: 43963 | B13: - | C13: European Life Magazine | D13: The Post- Crisis Outlook on the UAE Real Estate Market | E13: https://www.europeanlifemagazine.com/real-estate/the-post-crisis-outlook-on-the-uae-real-estate-market/ | F13: Betterhomes
... A15: 44089 | B15: - | C15: SME | D15: Betterhomes launches new real estate brokerage for working parents | E15: https://www.sme10x.com/10x-industry/betterhomes-launches-new-real-estate-brokerage-for-working-parents | F15: Betterhomes, Linda's

Sheet Concat
A1: =IFERROR(__xludf.DUMMYFUNCTION("QUERY({'2020'!A1:F15;'2021'!A2:F39;'2022'!A6:F203;'2023'!A6:F207},""SELECT * WHERE Col5 != 'Print'"")"),"Date") -> Date | B1: =IFERROR(__xludf.DUMMYFUNCTION("""COMPUTED_VALUE"""),"Media Tier") -> Media Tier | C1: =IFERROR(__xludf.DUMMYFUNCTION("""COMPUTED_VALUE"""),"Media") -> Media | D1: =IFERROR(__xludf.DUMMYFUNCTION("""COMPUTED_VALUE"""),"Title") -> Title | E1: =IFERROR(__xludf.DUMMYFUNCTION("""COMPUTED_VALUE"""),"Link") -> Link | F1: =IFERROR(__xludf.DUMMYFUNCTION("""COMPUTED_VALUE"""),"Brand") -> Brand
A2: =IFERROR(__xludf.DUMMYFUNCTION("""COMPUTED_VALUE"""),43935.0) -> 43935 | B2: =IFERROR(__xludf.DUMMYFUNCTION("""COMPUTED_VALUE"""),"-") -> - | C2: =IFERROR(__xludf.DUMMYFUNCTION("""COMPUTED_VALUE"""),"Trade Arabia") -> Trade Arabia | D2: =IFERROR(__xludf.DUMMYFUNCTION("""COMPUTED_VALUE"""),"Business as usual for movers in Dubai amid lockdown") -> Business as usual for movers in Dubai amid lockdown | E2: =IFERROR(__xludf.DUMMYFUNCTION("""COMPUTED_VALUE"""),"http://tradearabia.com/news/CONS_366645.html") -> http://tradearabia.com/news/CONS_366645.html | F2: =IFERROR(__xludf.DUMMYFUNCTION("""COMPUTED_VALUE"""),"Betterhomes") -> Betterhomes
A3: =IFERROR(__xludf.DUMMYFUNCTION("""COMPUTED_VALUE"""),44009.0) -> 44009 | B3: =IFERROR(__xludf.DUMMYFUNCTION("""COMPUTED_VALUE"""),"-") -> - | C3: =IFERROR(__xludf.DUMMYFUNCTION("""COMPUTED_VALUE"""),"Khaleej Times") -> Khaleej Times | D3: =IFERROR(__xludf.DUMMYFUNCTION("""COMPUTED_VALUE"""),"Residential rents in Dubai see a sharp drop, especially in these areas") -> Residential rents in Dubai see a sharp drop, especially in these areas | E3: =IFERROR(__xludf.DUMMYFUNCTION("""COMPUTED_VALUE"""),"https://www.khaleejtimes.com/business/real-estate/residential-rents-in-dubai-see-a-sharp-drop-especially-in-these-areas--") -> https://www.khaleejtimes.com/business/real-estate/residential-rents-in-dubai-see-a-sharp-drop-especially-in-these-areas-- | F3: =IFERROR(__xludf.DUMMYFUNCTION("""COMPUTED_VALUE"""),"Betterhomes") -> Betterhomes
A4: =IFERROR(__xludf.DUMMYFUNCTION("""COMPUTED_VALUE"""),44042.0) -> 44042 | B4: =IFERROR(__xludf.DUMMYFUNCTION("""COMPUTED_VALUE"""),"-") -> - | C4: =IFERROR(__xludf.DUMMYFUNCTION("""COMPUTED_VALUE"""),"Zawaya") -> Zawaya | D4: =IFERROR(__xludf.DUMMYFUNCTION("""COMPUTED_VALUE"""),"How Dubai's new Route 2020 will drive demand for residential, commercial properties") -> How Dubai's new Route 2020 will drive demand for residential, commercial properties | E4: =IFERROR(__xludf.DUMMYFUNCTION("""COMPUTED_VALUE"""),"https://www.zawya.com/mena/en/business/story/How_Dubais_new_Route_2020_will_drive_demand_for_residential_commercial_properties-ZAWYA20200730052256/") -> https://www.zawya.com/mena/en/business/story/How_Dubais_new_Route_2020_will_drive_demand_for_residential_commercial_properties-ZAWYA20200730052256/ | F4: =IFERROR(__xludf.DUMMYFUNCTION("""COMPUTED_VALUE"""),"Betterhomes") -> Betterhomes
A5: =IFERROR(__xludf.DUMMYFUNCTION("""COMPUTED_VALUE"""),44105.0) -> 44105 | B5: =IFERROR(__xludf.DUMMYFUNCTION("""COMPUTED_VALUE"""),"-") -> - | C5: =IFERROR(__xludf.DUMMYFUNCTION("""COMPUTED_VALUE"""),"Gulf News") -> Gulf News | D5: =IFERROR(__xludf.DUMMYFUNCTION("""COMPUTED_VALUE"""),"Living in Jumeirah meant compounds with common pools, says Dubai’s villa lady") -> Living in Jumeirah meant compounds with common pools, says Dubai’s villa lady | E5: =IFERROR(__xludf.DUMMYFUNCTION("""COMPUTED_VALUE"""),"https://gulfnews.com/business/property/living-in-jumeirah-meant-compounds-with-common-pools-says-dubais-villa-lady-1.1601554872716") -> https://gulfnews.com/business/property/living-in-jumeirah-meant-compounds-with-common-pools-says-dubais-villa-lady-1.1601554872716 | F5: =IFERROR(__xludf.DUMMYFUNCTION("""COMPUTED_VALUE"""),"Betterhomes") -> Betterhomes
A6: =IFERROR(__xludf.DUMMYFUNCTION("""COMPUTED_VALUE"""),44109.0) -> 44109 | B6: =IFERROR(__xludf.DUMMYFUNCTION("""COMPUTED_VALUE"""),"-") -> - | C6: =IFERROR(__xludf.DUMMYFUNCTION("""COMPUTED_VALUE"""),"Construction Week") -> Construction Week | D6: =IFERROR(__xludf.DUMMYFUNCTION("""COMPUTED_VALUE"""),"Podcast: Dubai's new brokerage for working mothers") -> Podcast: Dubai's new brokerage for working mothers | E6: =IFERROR(__xludf.DUMMYFUNCTION("""COMPUTED_VALUE"""),"https://www.constructionweekonline.com/business/267754-podcast-dubais-new-brokerage-for-working-mothers") -> https://www.constructionweekonline.com/business/267754-podcast-dubais-new-brokerage-for-working-mothers | F6: =IFERROR(__xludf.DUMMYFUNCTION("""COMPUTED_VALUE"""),"Betterhomes") -> Betterhomes
A7: =IFERROR(__xludf.DUMMYFUNCTION("""COMPUTED_VALUE"""),43831.0) -> 43831 | B7: =IFERROR(__xludf.DUMMYFUNCTION("""COMPUTED_VALUE"""),"-") -> - | C7: =IFERROR(__xludf.DUMMYFUNCTION("""COMPUTED_VALUE"""),"Arabian Business") -> Arabian Business | D7: =IFERROR(__xludf.DUMMYFUNCTION("""COMPUTED_VALUE"""),"The best of the best: All the major award winners from 2019") -> The best of the best: All the major award winners from 2019 | E7: =IFERROR(__xludf.DUMMYFUNCTION("""COMPUTED_VALUE"""),"https://www.arabianbusiness.com/events/436138-the-best-of-the-best-all-the-major-award-winners-from-2019") -> https://www.arabianbusiness.com/events/436138-the-best-of-the-best-all-the-major-award-winners-from-2019 | F7: =IFERROR(__xludf.DUMMYFUNCTION("""COMPUTED_VALUE"""),"Betterhomes") -> Betterhomes
A8: =IFERROR(__xludf.DUMMYFUNCTION("""COMPUTED_VALUE"""),43920.0) -> 43920 | B8: =IFERROR(__xludf.DUMMYFUNCTION("""COMPUTED_VALUE"""),"-") -> - | C8: =IFERROR(__xludf.DUMMYFUNCTION("""COMPUTED_VALUE"""),"Arabian Business") -> Arabian Business | D8: =IFERROR(__xludf.DUMMYFUNCTION("""COMPUTED_VALUE"""),"Coronavirus: What impact will Covid-19 have on Dubai's property market?") -> Coronavirus: What impact will Covid-19 have on Dubai's property market? | E8: =IFERROR(__xludf.DUMMYFUNCTION("""COMPUTED_VALUE"""),"https://www.arabianbusiness.com/property/443757-coronavirus-what-impact-will-covid-19-have-on-dubais-property-market") -> https://www.arabianbusiness.com/property/443757-coronavirus-what-impact-will-covid-19-have-on-dubais-property-market | F8: =IFERROR(__xludf.DUMMYFUNCTION("""COMPUTED_VALUE"""),"Betterhomes") -> Betterhomes
A9: =IFERROR(__xludf.DUMMYFUNCTION("""COMPUTED_VALUE"""),43915.0) -> 43915 | B9: =IFERROR(__xludf.DUMMYFUNCTION("""COMPUTED_VALUE"""),"-") -> - | C9: =IFERROR(__xludf.DUMMYFUNCTION("""COMPUTED_VALUE"""),"Global Business Outlook") -> Global Business Outlook | D9: =IFERROR(__xludf.DUMMYFUNCTION("""COMPUTED_VALUE"""),"Dubai real estate market ‘will tremendously improve after Covid-19") -> Dubai real estate market ‘will tremendously improve after Covid-19 | E9: =IFERROR(__xludf.DUMMYFUNCTION("""COMPUTED_VALUE"""),"https://www.globalbusinessoutlook.com/dubai-real-estate-market-will-tremendously-improve-after-covid-19/") -> https://www.globalbusinessoutlook.com/dubai-real-estate-market-will-tremendously-improve-after-covid-19/ | F9: =IFERROR(__xludf.DUMMYFUNCTION("""COMPUTED_VALUE"""),"Betterhomes") -> Betterhomes
A10: =IFERROR(__xludf.DUMMYFUNCTION("""COMPUTED_VALUE"""),44091.0) -> 44091 | B10: =IFERROR(__xludf.DUMMYFUNCTION("""COMPUTED_VALUE"""),"-") -> - | C10: =IFERROR(__xludf.DUMMYFUNCTION("""COMPUTED_VALUE"""),"Euonews") -> Euonews | D10: =IFERROR(__xludf.DUMMYFUNCTION("""COMPUTED_VALUE"""),"Gauging the impact of the global pandemic on the Real Estate market in Dubai") -> Gauging the impact of the global pandemic on the Real Estate market in Dubai | E10: =IFERROR(__xludf.DUMMYFUNCTION("""COMPUTED_VALUE"""),"https://www.euronews.com/2020/09/16/gauging-the-impact-of-the-global-pandemic-on-the-real-estate-market-in-dubai") -> https://www.euronews.com/2020/09/16/gauging-the-impact-of-the-global-pandemic-on-the-real-estate-market-in-dubai | F10: =IFERROR(__xludf.DUMMYFUNCTION("""COMPUTED_VALUE"""),"Betterhomes") -> Betterhomes
A11: =IFERROR(__xludf.DUMMYFUNCTION("""COMPUTED_VALUE"""),44137.0) -> 44137 | B11: =IFERROR(__xludf.DUMMYFUNCTION("""COMPUTED_VALUE"""),"-") -> - | C11: =IFERROR(__xludf.DUMMYFUNCTION("""COMPUTED_VALUE"""),"Gulf News") -> Gulf News | D11: =IFERROR(__xludf.DUMMYFUNCTION("""COMPUTED_VALUE"""),"Dubai homeowner increased value of property with effective landscaping") -> Dubai homeowner increased value of property with effective landscaping | E11: =IFERROR(__xludf.DUMMYFUNCTION("""COMPUTED_VALUE"""),"https://gulfnews.com/business/property/dubai-homeowner-increased-value-of-property-with-effective-landscaping-1.1604301168796") -> https://gulfnews.com/business/property/dubai-homeowner-increased-value-of-property-with-effective-landscaping-1.1604301168796 | F11: =IFERROR(__xludf.DUMMYFUNCTION("""COMPUTED_VALUE"""),"Betterhomes") -> Betterhomes
A12: =IFERROR(__xludf.DUMMYFUNCTION("""COMPUTED_VALUE"""),43947.0) -> 43947 | B12: =IFERROR(__xludf.DUMMYFUNCTION("""COMPUTED_VALUE"""),"-") -> - | C12: =IFERROR(__xludf.DUMMYFUNCTION("""COMPUTED_VALUE"""),"Property Finder Blog") -> Property Finder Blog | D12: =IFERROR(__xludf.DUMMYFUNCTION("""COMPUTED_VALUE"""),"Renting and Moving During Times of Crisis") -> Renting and Moving During Times of Crisis | E12: =IFERROR(__xludf.DUMMYFUNCTION("""COMPUTED_VALUE"""),"https://www.propertyfinder.ae/blog/renting-and-moving-during-crisis/") -> https://www.propertyfinder.ae/blog/renting-and-moving-during-crisis/ | F12: =IFERROR(__xludf.DUMMYFUNCTION("""COMPUTED_VALUE"""),"Betterhomes") -> Betterhomes
A13: =IFERROR(__xludf.DUMMYFUNCTION("""COMPUTED_VALUE"""),43963.0) -> 43963 | B13: =IFERROR(__xludf.DUMMYFUNCTION("""COMPUTED_VALUE"""),"-") -> - | C13: =IFERROR(__xludf.DUMMYFUNCTION("""COMPUTED_VALUE"""),"European Life Magazine") -> European Life Magazine | D13: =IFERROR(__xludf.DUMMYFUNCTION("""COMPUTED_VALUE"""),"The Post- Crisis Outlook on the UAE Real Estate Market") -> The Post- Crisis Outlook on the UAE Real Estate Market | E13: =IFERROR(__xludf.DUMMYFUNCTION("""COMPUTED_VALUE"""),"https://www.europeanlifemagazine.com/real-estate/the-post-crisis-outlook-on-the-uae-real-estate-market/") -> https://www.europeanlifemagazine.com/real-estate/the-post-crisis-outlook-on-the-uae-real-estate-market/ | F13: =IFERROR(__xludf.DUMMYFUNCTION("""COMPUTED_VALUE"""),"Betterhomes") -> Betterhomes
A14: =IFERROR(__xludf.DUMMYFUNCTION("""COMPUTED_VALUE"""),43873.0) -> 43873 | B14: =IFERROR(__xludf.DUMMYFUNCTION("""COMPUTED_VALUE"""),"-") -> - | C14: =IFERROR(__xludf.DUMMYFUNCTION("""COMPUTED_VALUE"""),"Property Finder Blog") -> Property Finder Blog | D14: =IFERROR(__xludf.DUMMYFUNCTION("""COMPUTED_VALUE"""),"Some more time before the market bottoms out") -> Some more time before the market bottoms out | E14: =IFERROR(__xludf.DUMMYFUNCTION("""COMPUTED_VALUE"""),"https://www.propertyfinder.ae/blog/some-more-time-before-the-market-bottoms-out/") -> https://www.propertyfinder.ae/blog/some-more-time-before-the-market-bottoms-out/ | F14: =IFERROR(__xludf.DUMMYFUNCTION("""COMPUTED_VALUE"""),"Betterhomes") -> Betterhomes
A15: =IFERROR(__xludf.DUMMYFUNCTION("""COMPUTED_VALUE"""),44089.0) -> 44089 | B15: =IFERROR(__xludf.DUMMYFUNCTION("""COMPUTED_VALUE"""),"-") -> - | C15: =IFERROR(__xludf.DUMMYFUNCTION("""COMPUTED_VALUE"""),"SME") -> SME | D15: =IFERROR(__xludf.DUMMYFUNCTION("""COMPUTED_VALUE"""),"Betterhomes launches new real estate brokerage for working parents") -> Betterhomes launches new real estate brokerage for working parents | E15: =IFERROR(__xludf.DUMMYFUNCTION("""COMPUTED_VALUE"""),"https://www.sme10x.com/10x-industry/betterhomes-launches-new-real-estate-brokerage-for-working-parents") -> https://www.sme10x.com/10x-industry/betterhomes-launches-new-real-estate-brokerage-for-working-parents | F15: =IFERROR(__xludf.DUMMYFUNCTION("""COMPUTED_VALUE"""),"Betterhomes, Linda's") -> Betterhomes, Linda's
A16: =IFERROR(__xludf.DUMMYFUNCTION("""COMPUTED_VALUE"""),44308.0) -> 44308 | B16: =IFERROR(__xludf.DUMMYFUNCTION("""COMPUTED_VALUE"""),"Tier 3") -> Tier 3 | C16: =IFERROR(__xludf.DUMMYFUNCTION("""COMPUTED_VALUE"""),"PR.com") -> PR.com | D16: =IFERROR(__xludf.DUMMYFUNCTION("""COMPUTED_VALUE"""),"Betterhomes Released Residential Property Market Report Q1 2021") -> Betterhomes Released Residential Property Market Report Q1 2021 | E16: =IFERROR(__xludf.DUMMYFUNCTION("""COMPUTED_VALUE"""),"https://www.pr.com/press-release/835148") -> https://www.pr.com/press-release/835148 | F16: =IFERROR(__xludf.DUMMYFUNCTION("""COMPUTED_VALUE"""),"Betterhomes") -> Betterhomes
A17: =IFERROR(__xludf.DUMMYFUNCTION("""COMPUTED_VALUE"""),44308.0) -> 44308 | B17: =IFERROR(__xludf.DUMMYFUNCTION("""COMPUTED_VALUE"""),"Tier 2") -> Tier 2 | C17: =IFERROR(__xludf.DUMMYFUNCTION("""COMPUTED_VALUE"""),"Khaleej Times ") -> Khaleej Times | D17: =IFERROR(__xludf.DUMMYFUNCTION("""COMPUTED_VALUE"""),"Dubai records 27% surge in Q1 property deals") -> Dubai records 27% surge in Q1 property deals | E17: =IFERROR(__xludf.DUMMYFUNCTION("""COMPUTED_VALUE"""),"https://www.khaleejtimes.com/news/dubai-records-27-surge-in-q1-property-deals") -> https://www.khaleejtimes.com/news/dubai-records-27-surge-in-q1-property-deals | F17: =IFERROR(__xludf.DUMMYFUNCTION("""COMPUTED_VALUE"""),"Betterhomes") -> Betterhomes
A18: =IFERROR(__xludf.DUMMYFUNCTION("""COMPUTED_VALUE"""),44308.0) -> 44308 | B18: =IFERROR(__xludf.DUMMYFUNCTION("""COMPUTED_VALUE"""),"Tier 3") -> Tier 3 | C18: =IFERROR(__xludf.DUMMYFUNCTION("""COMPUTED_VALUE"""),"Springfiled properties ") -> Springfiled properties | D18: =IFERROR(__xludf.DUMMYFUNCTION("""COMPUTED_VALUE"""),"Dubai records 27% surge in Q1 property deals") -> Dubai records 27% surge in Q1 property deals | E18: =IFERROR(__xludf.DUMMYFUNCTION("""COMPUTED_VALUE"""),"https://www.springfield-re.com/dubai-records-27-surge-in-q1-property-deals") -> https://www.springfield-re.com/dubai-records-27-surge-in-q1-property-deals | F18: =IFERROR(__xludf.DUMMYFUNCTION("""COMPUTED_VALUE"""),"Betterhomes") -> Betterhomes
A19: =IFERROR(__xludf.DUMMYFUNCTION("""COMPUTED_VALUE"""),44321.0) -> 44321 | B19: =IFERROR(__xludf.DUMMYFUNCTION("""COMPUTED_VALUE"""),"Tier 3") -> Tier 3 | C19: =IFERROR(__xludf.DUMMYFUNCTION("""COMPUTED_VALUE"""),"Creativezone ") -> Creativezone | D19: =IFERROR(__xludf.DUMMYFUNCTION("""COMPUTED_VALUE"""),"Dubai Real Estate: A 2021 Promising Outlook") -> Dubai Real Estate: A 2021 Promising Outlook | E19: =IFERROR(__xludf.DUMMYFUNCTION("""COMPUTED_VALUE"""),"https://www.creativezone.ae/events/dubai-real-estate-a-2021-promising-outlook/") -> https://www.creativezone.ae/events/dubai-real-estate-a-2021-promising-outlook/ | F19: =IFERROR(__xludf.DUMMYFUNCTION("""COMPUTED_VALUE"""),"Betterhomes") -> Betterhomes
A20: =IFERROR(__xludf.DUMMYFUNCTION("""COMPUTED_VALUE"""),44411.0) -> 44411 | B20: =IFERROR(__xludf.DUMMYFUNCTION("""COMPUTED_VALUE"""),"Tier 2") -> Tier 2 | C20: =IFERROR(__xludf.DUMMYFUNCTION("""COMPUTED_VALUE"""),"Zawaya") -> Zawaya | D20: =IFERROR(__xludf.DUMMYFUNCTION("""COMPUTED_VALUE"""),"Positive economic & employment sentiment in Dubai boosts property sales in H1 2021") -> Positive economic & employment sentiment in Dubai boosts property sales in H1 2021 | E20: =IFERROR(__xludf.DUMMYFUNCTION("""COMPUTED_VALUE"""),"https://www.zawya.com/uae/en/press-releases/story/Positive_economic__employment_sentiment_in_Dubai_boosts_property_sales_in_H1_2021-ZAWYA20210803062005/") -> https://www.zawya.com/uae/en/press-releases/story/Positive_economic__employment_sentiment_in_Dubai_boosts_property_sales_in_H1_2021-ZAWYA20210803062005/ | F20: =IFERROR(__xludf.DUMMYFUNCTION("""COMPUTED_VALUE"""),"Betterhomes") -> Betterhomes
A21: =IFERROR(__xludf.DUMMYFUNCTION("""COMPUTED_VALUE"""),44411.0) -> 44411 | B21: =IFERROR(__xludf.DUMMYFUNCTION("""COMPUTED_VALUE"""),"Tier 2") -> Tier 2 | C21: =IFERROR(__xludf.DUMMYFUNCTION("""COMPUTED_VALUE"""),"Arabian Business ") -> Arabian Business | D21: =IFERROR(__xludf.DUMMYFUNCTION("""COMPUTED_VALUE"""),"Dubai broker sees surge in British property buyers amid UAE's latest expat incentives") -> Dubai broker sees surge in British property buyers amid UAE's latest expat incentives | E21: =IFERROR(__xludf.DUMMYFUNCTION("""COMPUTED_VALUE"""),"https://www.arabianbusiness.com/real-estate/466741-dubai-broker-sees-surge-in-british-property-buyers-amid-uaes-latest-expat-incentives") -> https://www.arabianbusiness.com/real-estate/466741-dubai-broker-sees-surge-in-british-property-buyers-amid-uaes-latest-expat-incentives | F21: =IFERROR(__xludf.DUMMYFUNCTION("""COMPUTED_VALUE"""),"Betterhomes") -> Betterhomes
A22: =IFERROR(__xludf.DUMMYFUNCTION("""COMPUTED_VALUE"""),44411.0) -> 44411 | B22: =IFERROR(__xludf.DUMMYFUNCTION("""COMPUTED_VALUE"""),"Tier 2") -> Tier 2 | C22: =IFERROR(__xludf.DUMMYFUNCTION("""COMPUTED_VALUE"""),"Khaleej Times ") -> Khaleej Times | D22: =IFERROR(__xludf.DUMMYFUNCTION("""COMPUTED_VALUE"""),"Dubai realty back in spotlight with deals hitting 10-year high") -> Dubai realty back in spotlight with deals hitting 10-year high | E22: =IFERROR(__xludf.DUMMYFUNCTION("""COMPUTED_VALUE"""),"https://www.khaleejtimes.com/property/dubai-realty-back-in-spotlight-with-deals-hitting-10-year-high") -> https://www.khaleejtimes.com/property/dubai-realty-back-in-spotlight-with-deals-hitting-10-year-high | F22: =IFERROR(__xludf.DUMMYFUNCTION("""COMPUTED_VALUE"""),"Betterhomes") -> Betterhomes
A23: =IFERROR(__xludf.DUMMYFUNCTION("""COMPUTED_VALUE"""),44487.0) -> 44487 | B23: =IFERROR(__xludf.DUMMYFUNCTION("""COMPUTED_VALUE"""),"Tier 2") -> Tier 2 | C23: =IFERROR(__xludf.DUMMYFUNCTION("""COMPUTED_VALUE"""),"Zawaya") -> Zawaya | D23: =IFERROR(__xludf.DUMMYFUNCTION("""COMPUTED_VALUE"""),"Property market sets new records as prices continue to climb in Q3") -> Property market sets new records as prices continue to climb in Q3 | E23: =IFERROR(__xludf.DUMMYFUNCTION("""COMPUTED_VALUE"""),"https://www.zawya.com/mena/en/press-releases/story/Property_market_sets_new_records_as_prices_continue_to_climb_in_Q3-ZAWYA20211018115321/") -> https://www.zawya.com/mena/en/press-releases/story/Property_market_sets_new_records_as_prices_continue_to_climb_in_Q3-ZAWYA20211018115321/ | F23: =IFERROR(__xludf.DUMMYFUNCTION("""COMPUTED_VALUE"""),"Betterhomes") -> Betterhomes
A24: =IFERROR(__xludf.DUMMYFUNCTION("""COMPUTED_VALUE"""),44487.0) -> 44487 | B24: =IFERROR(__xludf.DUMMYFUNCTION("""COMPUTED_VALUE"""),"Tier 3") -> Tier 3 | C24: =IFERROR(__xludf.DUMMYFUNCTION("""COMPUTED_VALUE"""),"Liana Press") -> Liana Press | D24: =IFERROR(__xludf.DUMMYFUNCTION("""COMPUTED_VALUE"""),"Property market sets new records as prices continue to climb in Q3") -> Property market sets new records as prices continue to climb in Q3 | E24: =IFERROR(__xludf.DUMMYFUNCTION("""COMPUTED_VALUE"""),"https://www.lianapress.ae/releases/construction/property-market-sets-new-records-as-prices-continue-to-climb-in-q3.html") -> https://www.lianapress.ae/releases/construction/property-market-sets-new-records-as-prices-continue-to-climb-in-q3.html | F24: =IFERROR(__xludf.DUMMYFUNCTION("""COMPUTED_VALUE"""),"Betterhomes") -> Betterhomes
A25: =IFERROR(__xludf.DUMMYFUNCTION("""COMPUTED_VALUE"""),44488.0) -> 44488 | B25: =IFERROR(__xludf.DUMMYFUNCTION("""COMPUTED_VALUE"""),"Tier 3") -> Tier 3 | C25: =IFERROR(__xludf.DUMMYFUNCTION("""COMPUTED_VALUE"""),"UAE Business") -> UAE Business | D25: =IFERROR(__xludf.DUMMYFUNCTION("""COMPUTED_VALUE"""),"Property market sets new records as prices continue climb in Q3 2021") -> Property market sets new records as prices continue climb in Q3 2021 | E25: =IFERROR(__xludf.DUMMYFUNCTION("""COMPUTED_VALUE"""),"https://uaebusiness.com/2021/10/19/property-market-sets-new-records-as-prices-continue-to-climb-in-q3/") -> https://uaebusiness.com/2021/10/19/property-market-sets-new-records-as-prices-continue-to-climb-in-q3/ | F25: =IFERROR(__xludf.DUMMYFUNCTION("""COMPUTED_VALUE"""),"Betterhomes") -> Betterhomes
A26: =IFERROR(__xludf.DUMMYFUNCTION("""COMPUTED_VALUE"""),44488.0) -> 44488 | B26: =IFERROR(__xludf.DUMMYFUNCTION("""COMPUTED_VALUE"""),"Tier 2") -> Tier 2 | C26: =IFERROR(__xludf.DUMMYFUNCTION("""COMPUTED_VALUE"""),"Property News") -> Property News | D26: =IFERROR(__xludf.DUMMYFUNCTION("""COMPUTED_VALUE"""),"Property market sets new records as prices continue climb in Q3 2021") -> Property market sets new records as prices continue climb in Q3 2021 | E26: =IFERROR(__xludf.DUMMYFUNCTION("""COMPUTED_VALUE"""),"https://www.propertynews.ae/reports-updates/trends/property-market-sets-new-records-as-prices-continue-to-climb-in-q3/") -> https://www.propertynews.ae/reports-updates/trends/property-market-sets-new-records-as-prices-continue-to-climb-in-q3/ | F26: =IFERROR(__xludf.DUMMYFUNCTION("""COMPUTED_VALUE"""),"Betterhomes") -> Betterhomes
A27: =IFERROR(__xludf.DUMMYFUNCTION("""COMPUTED_VALUE"""),44488.0) -> 44488 | B27: =IFERROR(__xludf.DUMMYFUNCTION("""COMPUTED_VALUE"""),"Tier 2") -> Tier 2 | C27: =IFERROR(__xludf.DUMMYFUNCTION("""COMPUTED_VALUE"""),"Zawaya") -> Zawaya | D27: =IFERROR(__xludf.DUMMYFUNCTION("""COMPUTED_VALUE"""),"Property market sets new records as prices continue climb in Q3 2021") -> Property market sets new records as prices continue climb in Q3 2021 | E27: =IFERROR(__xludf.DUMMYFUNCTION("""COMPUTED_VALUE"""),"https://www.zawya.com/mena/en/story/amp/ZAWYA20211018115321/") -> https://www.zawya.com/mena/en/story/amp/ZAWYA20211018115321/ | F27: =IFERROR(__xludf.DUMMYFUNCTION("""COMPUTED_VALUE"""),"Betterhomes") -> Betterhomes
A28: =IFERROR(__xludf.DUMMYFUNCTION("""COMPUTED_VALUE"""),44489.0) -> 44489 | B28: =IFERROR(__xludf.DUMMYFUNCTION("""COMPUTED_VALUE"""),"Tier 2") -> Tier 2 | C28: =IFERROR(__xludf.DUMMYFUNCTION("""COMPUTED_VALUE"""),"Construction Week") -> Construction Week | D28: =IFERROR(__xludf.DUMMYFUNCTION("""COMPUTED_VALUE"""),"Dubai property market sees significant increase in sales transactions") -> Dubai property market sees significant increase in sales transactions | E28: =IFERROR(__xludf.DUMMYFUNCTION("""COMPUTED_VALUE"""),"https://www.constructionweekonline.com/news/crc-released-dubai-commercial-real-estate-market-report-q3-2021") -> https://www.constructionweekonline.com/news/crc-released-dubai-commercial-real-estate-market-report-q3-2021 | F28: =IFERROR(__xludf.DUMMYFUNCTION("""COMPUTED_VALUE"""),"CRC") -> CRC
A29: =IFERROR(__xludf.DUMMYFUNCTION("""COMPUTED_VALUE"""),44489.0) -> 44489 | B29: =IFERROR(__xludf.DUMMYFUNCTION("""COMPUTED_VALUE"""),"Tier 2") -> Tier 2 | C29: =IFERROR(__xludf.DUMMYFUNCTION("""COMPUTED_VALUE"""),"Zawaya") -> Zawaya | D29: =IFERROR(__xludf.DUMMYFUNCTION("""COMPUTED_VALUE"""),"CRC released Dubai Commercial Real Estate Market Report Q3 2021") -> CRC released Dubai Commercial Real Estate Market Report Q3 2021 | E29: =IFERROR(__xludf.DUMMYFUNCTION("""COMPUTED_VALUE"""),"https://www.zawya.com/mena/en/press-releases/story/CRC_released_Dubai_Commercial_Real_Estate_Market_Report_Q3_2021-ZAWYA20211020084549/") -> https://www.zawya.com/mena/en/press-releases/story/CRC_released_Dubai_Commercial_Real_Estate_Market_Report_Q3_2021-ZAWYA20211020084549/ | F29: =IFERROR(__xludf.DUMMYFUNCTION("""COMPUTED_VALUE"""),"CRC") -> CRC
A30: =IFERROR(__xludf.DUMMYFUNCTION("""COMPUTED_VALUE"""),44489.0) -> 44489 | B30: =IFERROR(__xludf.DUMMYFUNCTION("""COMPUTED_VALUE"""),"Tier 3") -> Tier 3 | C30: =IFERROR(__xludf.DUMMYFUNCTION("""COMPUTED_VALUE"""),"Industrial Real Estate News") -> Industrial Real Estate News | D30: =IFERROR(__xludf.DUMMYFUNCTION("""COMPUTED_VALUE"""),"CRC released Dubai Commercial Real Estate Market Report Q3 2021") -> CRC released Dubai Commercial Real Estate Market Report Q3 2021 | E30: =IFERROR(__xludf.DUMMYFUNCTION("""COMPUTED_VALUE"""),"https://industrialrealestatenews.top/crc-released-dubai-commercial-real-estate-market-report-q3-2021/") -> https://industrialrealestatenews.top/crc-released-dubai-commercial-real-estate-market-report-q3-2021/ | F30: =IFERROR(__xludf.DUMMYFUNCTION("""COMPUTED_VALUE"""),"CRC") -> CRC
A31: =IFERROR(__xludf.DUMMYFUNCTION("""COMPUTED_VALUE"""),44489.0) -> 44489 | B31: =IFERROR(__xludf.DUMMYFUNCTION("""COMPUTED_VALUE"""),"Tier 3") -> Tier 3 | C31: =IFERROR(__xludf.DUMMYFUNCTION("""COMPUTED_VALUE"""),"Facilities Management ") -> Facilities Management | D31: =IFERROR(__xludf.DUMMYFUNCTION("""COMPUTED_VALUE"""),"CRC released Dubai Commercial Real Estate Market Report Q3 2022") -> CRC released Dubai Commercial Real Estate Market Report Q3 2022 | E31: =IFERROR(__xludf.DUMMYFUNCTION("""COMPUTED_VALUE"""),"https://www.fm-middleeast.com/business/crc-released-dubai-commercial-real-estate-market-report-q3-2021") -> https://www.fm-middleeast.com/business/crc-released-dubai-commercial-real-estate-market-report-q3-2021 | F31: =IFERROR(__xludf.DUMMYFUNCTION("""COMPUTED_VALUE"""),"CRC") -> CRC
A32: =IFERROR(__xludf.DUMMYFUNCTION("""COMPUTED_VALUE"""),44489.0) -> 44489 | B32: =IFERROR(__xludf.DUMMYFUNCTION("""COMPUTED_VALUE"""),"Tier 2") -> Tier 2 | C32: =IFERROR(__xludf.DUMMYFUNCTION("""COMPUTED_VALUE"""),"Arabian Business") -> Arabian Business | D32: =IFERROR(__xludf.DUMMYFUNCTION("""COMPUTED_VALUE"""),"Is the pace of Dubai's recent property price hikes starting to slow?") -> Is the pace of Dubai's recent property price hikes starting to slow? | E32: =IFERROR(__xludf.DUMMYFUNCTION("""COMPUTED_VALUE"""),"https://www.arabianbusiness.com/industries-real-estate/469867-is-the-pace-of-dubais-recent-property-price-hikes-starting-to-slow") -> https://www.arabianbusiness.com/industries-real-estate/469867-is-the-pace-of-dubais-recent-property-price-hikes-starting-to-slow | F32: =IFERROR(__xludf.DUMMYFUNCTION("""COMPUTED_VALUE"""),"Betterhomes") -> Betterhomes
A33: =IFERROR(__xludf.DUMMYFUNCTION("""COMPUTED_VALUE"""),44490.0) -> 44490 | B33: =IFERROR(__xludf.DUMMYFUNCTION("""COMPUTED_VALUE"""),"Tier 2") -> Tier 2 | C33: =IFERROR(__xludf.DUMMYFUNCTION("""COMPUTED_VALUE"""),"Gulf News") -> Gulf News | D33: =IFERROR(__xludf.DUMMYFUNCTION("""COMPUTED_VALUE"""),"Better Homes plans global presence with more offices") -> Better Homes plans global presence with more offices | E33: =IFERROR(__xludf.DUMMYFUNCTION("""COMPUTED_VALUE"""),"https://gulfnews.com/business/property/better-homes-plans-global-presence-with-more-offices-1.253412") -> https://gulfnews.com/business/property/better-homes-plans-global-presence-with-more-offices-1.253412 | F33: =IFERROR(__xludf.DUMMYFUNCTION("""COMPUTED_VALUE"""),"Betterhomes") -> Betterhomes
A34: =IFERROR(__xludf.DUMMYFUNCTION("""COMPUTED_VALUE"""),44493.0) -> 44493 | B34: =IFERROR(__xludf.DUMMYFUNCTION("""COMPUTED_VALUE"""),"Tier 2") -> Tier 2 | C34: =IFERROR(__xludf.DUMMYFUNCTION("""COMPUTED_VALUE"""),"Khaleej Times") -> Khaleej Times | D34: =IFERROR(__xludf.DUMMYFUNCTION("""COMPUTED_VALUE"""),"Dubai: Low-interest rates boost mortgage transactions in 2021") -> Dubai: Low-interest rates boost mortgage transactions in 2021 | E34: =IFERROR(__xludf.DUMMYFUNCTION("""COMPUTED_VALUE"""),"https://www.khaleejtimes.com/business/dubai-low-interest-rates-boost-mortgage-transactions-in-2021") -> https://www.khaleejtimes.com/business/dubai-low-interest-rates-boost-mortgage-transactions-in-2021 | F34: =IFERROR(__xludf.DUMMYFUNCTION("""COMPUTED_VALUE"""),"Betterhomes") -> Betterhomes
A35: =IFERROR(__xludf.DUMMYFUNCTION("""COMPUTED_VALUE"""),44503.0) -> 44503 | B35: =IFERROR(__xludf.DUMMYFUNCTION("""COMPUTED_VALUE"""),"Tier 2") -> Tier 2 | C35: =IFERROR(__xludf.DUMMYFUNCTION("""COMPUTED_VALUE"""),"Arabian Business ") -> Arabian Business | D35: =IFERROR(__xludf.DUMMYFUNCTION("""COMPUTED_VALUE"""),"Dubai property broker seals record $2m leasing deal for luxury villa") -> Dubai property broker seals record $2m leasing deal for luxury villa | E35: =IFERROR(__xludf.DUMMYFUNCTION("""COMPUTED_VALUE"""),"https://www.arabianbusiness.com/real-estate/470612-dubai-property-broker-seals-record-2m-leasing-deal-for-luxury-villa") -> https://www.arabianbusiness.com/real-estate/470612-dubai-property-broker-seals-record-2m-leasing-deal-for-luxury-villa | F35: =IFERROR(__xludf.DUMMYFUNCTION("""COMPUTED_VALUE"""),"Betterhomes") -> Betterhomes
A36: =IFERROR(__xludf.DUMMYFUNCTION("""COMPUTED_VALUE"""),44504.0) -> 44504 | B36: =IFERROR(__xludf.DUMMYFUNCTION("""COMPUTED_VALUE"""),"Tier 2") -> Tier 2 | C36: =IFERROR(__xludf.DUMMYFUNCTION("""COMPUTED_VALUE"""),"Construction Week") -> Construction Week | D36: =IFERROR(__xludf.DUMMYFUNCTION("""COMPUTED_VALUE"""),"Betterhomes logs leasing deal at $1.76 million in Emirates Hills") -> Betterhomes logs leasing deal at $1.76 million in Emirates Hills | E36: =IFERROR(__xludf.DUMMYFUNCTION("""COMPUTED_VALUE"""),"https://www.constructionweekonline.com/business/betterhomes-logs-leasing-deal-at-1-76-million-in-emirates-hills") -> https://www.constructionweekonline.com/business/betterhomes-logs-leasing-deal-at-1-76-million-in-emirates-hills | F36: =IFERROR(__xludf.DUMMYFUNCTION("""COMPUTED_VALUE"""),"Betterhomes") -> Betterhomes
A37: =IFERROR(__xludf.DUMMYFUNCTION("""COMPUTED_VALUE"""),44503.0) -> 44503 | B37: =IFERROR(__xludf.DUMMYFUNCTION("""COMPUTED_VALUE"""),"Tier 3") -> Tier 3 | C37: =IFERROR(__xludf.DUMMYFUNCTION("""COMPUTED_VALUE"""),"UAE Business") -> UAE Business | D37: =IFERROR(__xludf.DUMMYFUNCTION("""COMPUTED_VALUE"""),"Dubai property market logs highest leasing deal at AED7.5M/year") -> Dubai property market logs highest leasing deal at AED7.5M/year | E37: =IFERROR(__xludf.DUMMYFUNCTION("""COMPUTED_VALUE"""),"https://uaebusiness.com/tag/better-homes-llc/") -> https://uaebusiness.com/tag/better-homes-llc/ | F37: =IFERROR(__xludf.DUMMYFUNCTION("""COMPUTED_VALUE"""),"Betterhomes") -> Betterhomes
A38: =IFERROR(__xludf.DUMMYFUNCTION("""COMPUTED_VALUE"""),44503.0) -> 44503 | B38: =IFERROR(__xludf.DUMMYFUNCTION("""COMPUTED_VALUE"""),"Tier 3") -> Tier 3 | C38: =IFERROR(__xludf.DUMMYFUNCTION("""COMPUTED_VALUE"""),"Liana Press") -> Liana Press | D38: =IFERROR(__xludf.DUMMYFUNCTION("""COMPUTED_VALUE"""),"Dubai property market logs highest leasing deal at AED7.5M/year") -> Dubai property market logs highest leasing deal at AED7.5M/year | E38: =IFERROR(__xludf.DUMMYFUNCTION("""COMPUTED_VALUE"""),"https://www.lianapress.ae/releases/construction/dubai-property-market-logs-highest-leasing-deal-at-aed7.5myear.html") -> https://www.lianapress.ae/releases/construction/dubai-property-market-logs-highest-leasing-deal-at-aed7.5myear.html | F38: =IFERROR(__xludf.DUMMYFUNCTION("""COMPUTED_VALUE"""),"Betterhomes") -> Betterhomes
A39: =IFERROR(__xludf.DUMMYFUNCTION("""COMPUTED_VALUE"""),44503.0) -> 44503 | B39: =IFERROR(__xludf.DUMMYFUNCTION("""COMPUTED_VALUE"""),"Tier 2") -> Tier 2 | C39: =IFERROR(__xludf.DUMMYFUNCTION("""COMPUTED_VALUE"""),"Zawaya") -> Zawaya | D39: =IFERROR(__xludf.DUMMYFUNCTION("""COMPUTED_VALUE"""),"Dubai property market logs highest leasing deal at AED7.5mln/year") -> Dubai property market logs highest leasing deal at AED7.5mln/year | E39: =IFERROR(__xludf.DUMMYFUNCTION("""COMPUTED_VALUE"""),"https://www.zawya.com/mena/en/press-releases/story/Dubai_property_market_logs_highest_leasing_deal_at_AED75mlnyear-ZAWYA20211103104849/") -> https://www.zawya.com/mena/en/press-releases/story/Dubai_property_market_logs_highest_leasing_deal_at_AED75mlnyear-ZAWYA20211103104849/ | F39: =IFERROR(__xludf.DUMMYFUNCTION("""COMPUTED_VALUE"""),"Betterhomes") -> Betterhomes
A40: =IFERROR(__xludf.DUMMYFUNCTION("""COMPUTED_VALUE"""),44504.0) -> 44504 | B40: =IFERROR(__xludf.DUMMYFUNCTION("""COMPUTED_VALUE"""),"Tier 2") -> Tier 2 | C40: =IFERROR(__xludf.DUMMYFUNCTION("""COMPUTED_VALUE"""),"Property Finder") -> Property Finder | D40: =IFERROR(__xludf.DUMMYFUNCTION("""COMPUTED_VALUE"""),"Latest Prestige November 2021 issue in Gulf Business") -> Latest Prestige November 2021 issue in Gulf Business | E40: =IFERROR(__xludf.DUMMYFUNCTION("""COMPUTED_VALUE"""),"https://www.propertyfinder.ae/hub/agent-guides/latest-prestige-november-2021-issue-in-gulf-business/") -> https://www.propertyfinder.ae/hub/agent-guides/latest-prestige-november-2021-issue-in-gulf-business/ | F40: =IFERROR(__xludf.DUMMYFUNCTION("""COMPUTED_VALUE"""),"Linda's") -> Linda's
A41: =IFERROR(__xludf.DUMMYFUNCTION("""COMPUTED_VALUE"""),44506.0) -> 44506 | B41: =IFERROR(__xludf.DUMMYFUNCTION("""COMPUTED_VALUE"""),"Tier 2") -> Tier 2 | C41: =IFERROR(__xludf.DUMMYFUNCTION("""COMPUTED_VALUE"""),"The National") -> The National | E41: =IFERROR(__xludf.DUMMYFUNCTION("""COMPUTED_VALUE"""),"https://www.thenationalnews.com/lifestyle/luxury/2021/11/06/dh75m-emirates-hills-villa-becomes-dubais-most-expensive-rental/") -> https://www.thenationalnews.com/lifestyle/luxury/2021/11/06/dh75m-emirates-hills-villa-becomes-dubais-most-expensive-rental/ | F41: =IFERROR(__xludf.DUMMYFUNCTION("""COMPUTED_VALUE"""),"Betterhomes") -> Betterhomes
A42: =IFERROR(__xludf.DUMMYFUNCTION("""COMPUTED_VALUE"""),44506.0) -> 44506 | B42: =IFERROR(__xludf.DUMMYFUNCTION("""COMPUTED_VALUE"""),"Tier 2") -> Tier 2 | C42: =IFERROR(__xludf.DUMMYFUNCTION("""COMPUTED_VALUE"""),"Radio Eye") -> Radio Eye | D42: =IFERROR(__xludf.DUMMYFUNCTION("""COMPUTED_VALUE"""),"Hannah's 7.5m leasinf deal") -> Hannah's 7.5m leasinf deal | E42: =IFERROR(__xludf.DUMMYFUNCTION("""COMPUTED_VALUE"""),"Business Breakfast") -> Business Breakfast | F42: =IFERROR(__xludf.DUMMYFUNCTION("""COMPUTED_VALUE"""),"Betterhomes") -> Betterhomes
A43: =IFERROR(__xludf.DUMMYFUNCTION("""COMPUTED_VALUE"""),44507.0) -> 44507 | B43: =IFERROR(__xludf.DUMMYFUNCTION("""COMPUTED_VALUE"""),"Tier 2") -> Tier 2 | C43: =IFERROR(__xludf.DUMMYFUNCTION("""COMPUTED_VALUE"""),"Construction Week") -> Construction Week | D43: =IFERROR(__xludf.DUMMYFUNCTION("""COMPUTED_VALUE"""),"Betterhomes logs leasing deal at $1.76 million in Emirates Hills") -> Betterhomes logs leasing deal at $1.76 million in Emirates Hills | E43: =IFERROR(__xludf.DUMMYFUNCTION("""COMPUTED_VALUE"""),"https://www.constructionweekonline.com/business/betterhomes-logs-leasing-deal-at-1-76-million-in-emirates-hills") -> https://www.constructionweekonline.com/business/betterhomes-logs-leasing-deal-at-1-76-million-in-emirates-hills | F43: =IFERROR(__xludf.DUMMYFUNCTION("""COMPUTED_VALUE"""),"Betterhomes") -> Betterhomes
A44: =IFERROR(__xludf.DUMMYFUNCTION("""COMPUTED_VALUE"""),44508.0) -> 44508 | B44: =IFERROR(__xludf.DUMMYFUNCTION("""COMPUTED_VALUE"""),"Tier 3") -> Tier 3 | C44: =IFERROR(__xludf.DUMMYFUNCTION("""COMPUTED_VALUE"""),"The Wall") -> The Wall | E44: =IFERROR(__xludf.DUMMYFUNCTION("""COMPUTED_VALUE"""),"https://thewall.fyi/dubai-property-broker-seals-record-2m-leasing-deal-for-luxury-villa/") -> https://thewall.fyi/dubai-property-broker-seals-record-2m-leasing-deal-for-luxury-villa/ | F44: =IFERROR(__xludf.DUMMYFUNCTION("""COMPUTED_VALUE"""),"Betterhomes") -> Betterhomes
A45: =IFERROR(__xludf.DUMMYFUNCTION("""COMPUTED_VALUE"""),44509.0) -> 44509 | B45: =IFERROR(__xludf.DUMMYFUNCTION("""COMPUTED_VALUE"""),"Tier 3") -> Tier 3 | C45: =IFERROR(__xludf.DUMMYFUNCTION("""COMPUTED_VALUE"""),"International Business Magazine") -> International Business Magazine | E45: =IFERROR(__xludf.DUMMYFUNCTION("""COMPUTED_VALUE"""),"https://intlbm.com/dubai-real-estate-market-clocks-its-highest-leasing-deal-worth-aed7-5-million/") -> https://intlbm.com/dubai-real-estate-market-clocks-its-highest-leasing-deal-worth-aed7-5-million/ | F45: =IFERROR(__xludf.DUMMYFUNCTION("""COMPUTED_VALUE"""),"Betterhomes") -> Betterhomes
A46: =IFERROR(__xludf.DUMMYFUNCTION("""COMPUTED_VALUE"""),44509.0) -> 44509 | B46: =IFERROR(__xludf.DUMMYFUNCTION("""COMPUTED_VALUE"""),"Tier 3") -> Tier 3 | C46: =IFERROR(__xludf.DUMMYFUNCTION("""COMPUTED_VALUE"""),"Medium Value Strat") -> Medium Value Strat | E46: =IFERROR(__xludf.DUMMYFUNCTION("""COMPUTED_VALUE"""),"https://medium.com/@valustrat/dh7-5m-emirates-hills-villa-becomes-dubais-most-expensive-rental-fdd55e5c53bd") -> https://medium.com/@valustrat/dh7-5m-emirates-hills-villa-becomes-dubais-most-expensive-rental-fdd55e5c53bd | F46: =IFERROR(__xludf.DUMMYFUNCTION("""COMPUTED_VALUE"""),"Betterhomes") -> Betterhomes
A47: =IFERROR(__xludf.DUMMYFUNCTION("""COMPUTED_VALUE"""),44638.0) -> 44638 | B47: =IFERROR(__xludf.DUMMYFUNCTION("""COMPUTED_VALUE"""),"Tier 2") -> Tier 2 | C47: =IFERROR(__xludf.DUMMYFUNCTION("""COMPUTED_VALUE"""),"The National") -> The National | D47: =IFERROR(__xludf.DUMMYFUNCTION("""COMPUTED_VALUE"""),"Top 7 mistakes to avoid when selling your home") -> Top 7 mistakes to avoid when selling your home | E47: =IFERROR(__xludf.DUMMYFUNCTION("""COMPUTED_VALUE"""),"https://www.thenationalnews.com/weekend/2022/03/18/top-7-mistakes-to-avoid-when-selling-your-home/") -> https://www.thenationalnews.com/weekend/2022/03/18/top-7-mistakes-to-avoid-when-selling-your-home/ | F47: =IFERROR(__xludf.DUMMYFUNCTION("""COMPUTED_VALUE"""),"Betterhomes") -> Betterhomes
A48: =IFERROR(__xludf.DUMMYFUNCTION("""COMPUTED_VALUE"""),44669.0) -> 44669 | B48: =IFERROR(__xludf.DUMMYFUNCTION("""COMPUTED_VALUE"""),"Tier 2") -> Tier 2 | C48: =IFERROR(__xludf.DUMMYFUNCTION("""COMPUTED_VALUE"""),"Zawya") -> Zawya | D48: =IFERROR(__xludf.DUMMYFUNCTION("""COMPUTED_VALUE"""),"Demand and prices on the rise for townhouses and apartments in Q1 2022") -> Demand and prices on the rise for townhouses and apartments in Q1 2022 | E48: =IFERROR(__xludf.DUMMYFUNCTION("""COMPUTED_VALUE"""),"https://www.zawya.com/en/press-release/companies-news/demand-and-prices-on-the-rise-for-townhouses-and-apartments-in-q1-2022-dp9dk0s7") -> https://www.zawya.com/en/press-release/companies-news/demand-and-prices-on-the-rise-for-townhouses-and-apartments-in-q1-2022-dp9dk0s7 | F48: =IFERROR(__xludf.DUMMYFUNCTION("""COMPUTED_VALUE"""),"Betterhomes") -> Betterhomes
A49: =IFERROR(__xludf.DUMMYFUNCTION("""COMPUTED_VALUE"""),44670.0) -> 44670 | B49: =IFERROR(__xludf.DUMMYFUNCTION("""COMPUTED_VALUE"""),"Tier 2") -> Tier 2 | C49: =IFERROR(__xludf.DUMMYFUNCTION("""COMPUTED_VALUE"""),"Gulf News") -> Gulf News | D49: =IFERROR(__xludf.DUMMYFUNCTION("""COMPUTED_VALUE"""),"In Dubai, villa owners find no takers for sudden price hikes of 10% and more") -> In Dubai, villa owners find no takers for sudden price hikes of 10% and more | E49: =IFERROR(__xludf.DUMMYFUNCTION("""COMPUTED_VALUE"""),"https://gulfnews.com/business/property/in-dubai-villa-owners-find-no-takers-for-sudden-price-hikes-of-10-and-more-1.1650345406229") -> https://gulfnews.com/business/property/in-dubai-villa-owners-find-no-takers-for-sudden-price-hikes-of-10-and-more-1.1650345406229 | F49: =IFERROR(__xludf.DUMMYFUNCTION("""COMPUTED_VALUE"""),"Betterhomes") -> Betterhomes
A50: =IFERROR(__xludf.DUMMYFUNCTION("""COMPUTED_VALUE"""),44670.0) -> 44670 | B50: =IFERROR(__xludf.DUMMYFUNCTION("""COMPUTED_VALUE"""),"Tier 1") -> Tier 1 | C50: =IFERROR(__xludf.DUMMYFUNCTION("""COMPUTED_VALUE"""),"Bloomberg") -> Bloomberg | D50: =IFERROR(__xludf.DUMMYFUNCTION("""COMPUTED_VALUE"""),"Russians Climb Dubai Property Ladder as Sanctions Imperil Wealth") -> Russians Climb Dubai Property Ladder as Sanctions Imperil Wealth | E50: =IFERROR(__xludf.DUMMYFUNCTION("""COMPUTED_VALUE"""),"https://www.bloomberg.com/news/articles/2022-04-19/russians-climb-dubai-property-ladder-as-sanctions-imperil-wealth") -> https://www.bloomberg.com/news/articles/2022-04-19/russians-climb-dubai-property-ladder-as-sanctions-imperil-wealth | F50: =IFERROR(__xludf.DUMMYFUNCTION("""COMPUTED_VALUE"""),"Betterhomes") -> Betterhomes
A51: =IFERROR(__xludf.DUMMYFUNCTION("""COMPUTED_VALUE"""),44671.0) -> 44671 | B51: =IFERROR(__xludf.DUMMYFUNCTION("""COMPUTED_VALUE"""),"Tier 2") -> Tier 2 | C51: =IFERROR(__xludf.DUMMYFUNCTION("""COMPUTED_VALUE"""),"Arabian Business ") -> Arabian Business | D51: =IFERROR(__xludf.DUMMYFUNCTION("""COMPUTED_VALUE"""),"Dubai’s commercial property market soars as post Covid confidence leads to strongest quarter since 2016") -> Dubai’s commercial property market soars as post Covid confidence leads to strongest quarter since 2016 | E51: =IFERROR(__xludf.DUMMYFUNCTION("""COMPUTED_VALUE"""),"https://www.arabianbusiness.com/money/wealth/money-wealth-real-estate/dubais-commercial-property-market-soars-as-post-covid-confidence-leads-to-strongest-quarter-since-2016") -> https://www.arabianbusiness.com/money/wealth/money-wealth-real-estate/dubais-commercial-property-market-soars-as-post-covid-confidence-leads-to-strongest-quarter-since-2016 | F51: =IFERROR(__xludf.DUMMYFUNCTION("""COMPUTED_VALUE"""),"CRC") -> CRC
A52: =IFERROR(__xludf.DUMMYFUNCTION("""COMPUTED_VALUE"""),44673.0) -> 44673 | B52: =IFERROR(__xludf.DUMMYFUNCTION("""COMPUTED_VALUE"""),"Tier 2") -> Tier 2 | C52: =IFERROR(__xludf.DUMMYFUNCTION("""COMPUTED_VALUE"""),"The National") -> The National | D52: =IFERROR(__xludf.DUMMYFUNCTION("""COMPUTED_VALUE"""),"Five renovations that could actually lower the value of your home") -> Five renovations that could actually lower the value of your home | E52: =IFERROR(__xludf.DUMMYFUNCTION("""COMPUTED_VALUE"""),"https://www.thenationalnews.com/weekend/2022/04/22/five-renovations-that-could-actually-lower-the-value-of-your-home/") -> https://www.thenationalnews.com/weekend/2022/04/22/five-renovations-that-could-actually-lower-the-value-of-your-home/ | F52: =IFERROR(__xludf.DUMMYFUNCTION("""COMPUTED_VALUE"""),"Betterhomes") -> Betterhomes
A53: =IFERROR(__xludf.DUMMYFUNCTION("""COMPUTED_VALUE"""),44676.0) -> 44676 | B53: =IFERROR(__xludf.DUMMYFUNCTION("""COMPUTED_VALUE"""),"Tier 2") -> Tier 2 | C53: =IFERROR(__xludf.DUMMYFUNCTION("""COMPUTED_VALUE"""),"Arab news") -> Arab news | D53: =IFERROR(__xludf.DUMMYFUNCTION("""COMPUTED_VALUE"""),"Dubai property purchases by Russians up 67% in Q1 of 2022") -> Dubai property purchases by Russians up 67% in Q1 of 2022 | E53: =IFERROR(__xludf.DUMMYFUNCTION("""COMPUTED_VALUE"""),"https://www.arabnews.com/node/2066971/business-economy") -> https://www.arabnews.com/node/2066971/business-economy | F53: =IFERROR(__xludf.DUMMYFUNCTION("""COMPUTED_VALUE"""),"Betterhomes") -> Betterhomes
A54: =IFERROR(__xludf.DUMMYFUNCTION("""COMPUTED_VALUE"""),44676.0) -> 44676 | B54: =IFERROR(__xludf.DUMMYFUNCTION("""COMPUTED_VALUE"""),"Tier 1") -> Tier 1 | C54: =IFERROR(__xludf.DUMMYFUNCTION("""COMPUTED_VALUE"""),"Bloomberg") -> Bloomberg | D54: =IFERROR(__xludf.DUMMYFUNCTION("""COMPUTED_VALUE"""),"Rising Oil Prices a Boon for Saudi Economy") -> Rising Oil Prices a Boon for Saudi Economy | E54: =IFERROR(__xludf.DUMMYFUNCTION("""COMPUTED_VALUE"""),"https://www.bloomberg.com/news/newsletters/2022-04-25/rising-oil-prices-a-boon-for-saudi-arabia-s-economy") -> https://www.bloomberg.com/news/newsletters/2022-04-25/rising-oil-prices-a-boon-for-saudi-arabia-s-economy | F54: =IFERROR(__xludf.DUMMYFUNCTION("""COMPUTED_VALUE"""),"Betterhomes") -> Betterhomes
A55: =IFERROR(__xludf.DUMMYFUNCTION("""COMPUTED_VALUE"""),44686.0) -> 44686 | B55: =IFERROR(__xludf.DUMMYFUNCTION("""COMPUTED_VALUE"""),"Tier 1") -> Tier 1 | C55: =IFERROR(__xludf.DUMMYFUNCTION("""COMPUTED_VALUE"""),"BBC News") -> BBC News | D55: =IFERROR(__xludf.DUMMYFUNCTION("""COMPUTED_VALUE"""),"Wealthy Russians flee to Dubai to avoid sanctions") -> Wealthy Russians flee to Dubai to avoid sanctions | E55: =IFERROR(__xludf.DUMMYFUNCTION("""COMPUTED_VALUE"""),"https://www.bbc.com/news/business-61257448") -> https://www.bbc.com/news/business-61257448 | F55: =IFERROR(__xludf.DUMMYFUNCTION("""COMPUTED_VALUE"""),"Betterhomes") -> Betterhomes
A56: =IFERROR(__xludf.DUMMYFUNCTION("""COMPUTED_VALUE"""),44686.0) -> 44686 | B56: =IFERROR(__xludf.DUMMYFUNCTION("""COMPUTED_VALUE"""),"Tier 2") -> Tier 2 | C56: =IFERROR(__xludf.DUMMYFUNCTION("""COMPUTED_VALUE"""),"Mirror") -> Mirror | D56: =IFERROR(__xludf.DUMMYFUNCTION("""COMPUTED_VALUE"""),"Russian firms and billionaires flee to Dubai to avoid sanctions over Putin's Ukraine war") -> Russian firms and billionaires flee to Dubai to avoid sanctions over Putin's Ukraine war | E56: =IFERROR(__xludf.DUMMYFUNCTION("""COMPUTED_VALUE"""),"https://www.mirror.co.uk/news/world-news/russian-firms-billionaires-flee-dubai-26885574") -> https://www.mirror.co.uk/news/world-news/russian-firms-billionaires-flee-dubai-26885574 | F56: =IFERROR(__xludf.DUMMYFUNCTION("""COMPUTED_VALUE"""),"Betterhomes") -> Betterhomes
A57: =IFERROR(__xludf.DUMMYFUNCTION("""COMPUTED_VALUE"""),44687.0) -> 44687 | B57: =IFERROR(__xludf.DUMMYFUNCTION("""COMPUTED_VALUE"""),"Tier 3") -> Tier 3 | C57: =IFERROR(__xludf.DUMMYFUNCTION("""COMPUTED_VALUE"""),"International Investment") -> International Investment | D57: =IFERROR(__xludf.DUMMYFUNCTION("""COMPUTED_VALUE"""),"Two thirds surge in Dubai property sales to Russians") -> Two thirds surge in Dubai property sales to Russians | E57: =IFERROR(__xludf.DUMMYFUNCTION("""COMPUTED_VALUE"""),"https://www.internationalinvestment.net/news/4049274/thirds-surge-dubai-property-sales-russians") -> https://www.internationalinvestment.net/news/4049274/thirds-surge-dubai-property-sales-russians | F57: =IFERROR(__xludf.DUMMYFUNCTION("""COMPUTED_VALUE"""),"Betterhomes") -> Betterhomes
A58: =IFERROR(__xludf.DUMMYFUNCTION("""COMPUTED_VALUE"""),44687.0) -> 44687 | B58: =IFERROR(__xludf.DUMMYFUNCTION("""COMPUTED_VALUE"""),"Tier 3") -> Tier 3 | C58: =IFERROR(__xludf.DUMMYFUNCTION("""COMPUTED_VALUE"""),"Arise news") -> Arise news | D58: =IFERROR(__xludf.DUMMYFUNCTION("""COMPUTED_VALUE"""),"Wealthy Russians Flee to Dubai to Avoid Sanctions") -> Wealthy Russians Flee to Dubai to Avoid Sanctions | E58: =IFERROR(__xludf.DUMMYFUNCTION("""COMPUTED_VALUE"""),"https://www.arise.tv/wealthy-russians-flee-to-dubai-to-avoid-sanctions/") -> https://www.arise.tv/wealthy-russians-flee-to-dubai-to-avoid-sanctions/ | F58: =IFERROR(__xludf.DUMMYFUNCTION("""COMPUTED_VALUE"""),"Betterhomes") -> Betterhomes
A59: =IFERROR(__xludf.DUMMYFUNCTION("""COMPUTED_VALUE"""),44687.0) -> 44687 | B59: =IFERROR(__xludf.DUMMYFUNCTION("""COMPUTED_VALUE"""),"Tier 2") -> Tier 2 | C59: =IFERROR(__xludf.DUMMYFUNCTION("""COMPUTED_VALUE"""),"Arab news") -> Arab news | D59: =IFERROR(__xludf.DUMMYFUNCTION("""COMPUTED_VALUE"""),"Russian billionaires arriving in UAE in 'unprecedented numbers'") -> Russian billionaires arriving in UAE in 'unprecedented numbers' | E59: =IFERROR(__xludf.DUMMYFUNCTION("""COMPUTED_VALUE"""),"https://www.arabnews.com/node/2076071/business-economy") -> https://www.arabnews.com/node/2076071/business-economy | F59: =IFERROR(__xludf.DUMMYFUNCTION("""COMPUTED_VALUE"""),"Betterhomes") -> Betterhomes
A60: =IFERROR(__xludf.DUMMYFUNCTION("""COMPUTED_VALUE"""),44693.0) -> 44693 | B60: =IFERROR(__xludf.DUMMYFUNCTION("""COMPUTED_VALUE"""),"Tier 3") -> Tier 3 | C60: =IFERROR(__xludf.DUMMYFUNCTION("""COMPUTED_VALUE"""),"UniverseNews Network") -> UniverseNews Network | D60: =IFERROR(__xludf.DUMMYFUNCTION("""COMPUTED_VALUE"""),"Ryan Mahoney (Dubai, UAE): CRC Market Report on Commercial Properties") -> Ryan Mahoney (Dubai, UAE): CRC Market Report on Commercial Properties | E60: =IFERROR(__xludf.DUMMYFUNCTION("""COMPUTED_VALUE"""),"https://www.universenewsnetwork.com/2022/05/12/ryan-mahoney-dubai-uae-crc-market-report-on-commercial-properties/") -> https://www.universenewsnetwork.com/2022/05/12/ryan-mahoney-dubai-uae-crc-market-report-on-commercial-properties/ | F60: =IFERROR(__xludf.DUMMYFUNCTION("""COMPUTED_VALUE"""),"CRC") -> CRC
A61: =IFERROR(__xludf.DUMMYFUNCTION("""COMPUTED_VALUE"""),44694.0) -> 44694 | B61: =IFERROR(__xludf.DUMMYFUNCTION("""COMPUTED_VALUE"""),"Tier 3") -> Tier 3 | C61: =IFERROR(__xludf.DUMMYFUNCTION("""COMPUTED_VALUE"""),"Business Mole") -> Business Mole | D61: =IFERROR(__xludf.DUMMYFUNCTION("""COMPUTED_VALUE"""),"Ryan Mahoney (Dubai, UAE): CRC Market Report on Commercial Properties") -> Ryan Mahoney (Dubai, UAE): CRC Market Report on Commercial Properties | E61: =IFERROR(__xludf.DUMMYFUNCTION("""COMPUTED_VALUE"""),"http://www.businessmole.com/ryan-mahoney-dubai-uae-crc-market-report-on-commercial-properties/") -> http://www.businessmole.com/ryan-mahoney-dubai-uae-crc-market-report-on-commercial-properties/ | F61: =IFERROR(__xludf.DUMMYFUNCTION("""COMPUTED_VALUE"""),"CRC") -> CRC
A62: =IFERROR(__xludf.DUMMYFUNCTION("""COMPUTED_VALUE"""),44700.0) -> 44700 | B62: =IFERROR(__xludf.DUMMYFUNCTION("""COMPUTED_VALUE"""),"Tier 2") -> Tier 2 | C62: =IFERROR(__xludf.DUMMYFUNCTION("""COMPUTED_VALUE"""),"Zawya") -> Zawya | D62: =IFERROR(__xludf.DUMMYFUNCTION("""COMPUTED_VALUE"""),"CRC, pulls off a three-floor office space deal, in One by Omniyat, Business Bay") -> CRC, pulls off a three-floor office space deal, in One by Omniyat, Business Bay | E62: =IFERROR(__xludf.DUMMYFUNCTION("""COMPUTED_VALUE"""),"https://www.zawya.com/en/press-release/companies-news/crc-pulls-off-a-three-floor-office-space-deal-in-one-by-omniyat-business-bay-xgtmuzna") -> https://www.zawya.com/en/press-release/companies-news/crc-pulls-off-a-three-floor-office-space-deal-in-one-by-omniyat-business-bay-xgtmuzna | F62: =IFERROR(__xludf.DUMMYFUNCTION("""COMPUTED_VALUE"""),"CRC") -> CRC
A63: =IFERROR(__xludf.DUMMYFUNCTION("""COMPUTED_VALUE"""),44700.0) -> 44700 | B63: =IFERROR(__xludf.DUMMYFUNCTION("""COMPUTED_VALUE"""),"Tier 3") -> Tier 3 | C63: =IFERROR(__xludf.DUMMYFUNCTION("""COMPUTED_VALUE"""),"Leadership News") -> Leadership News | D63: =IFERROR(__xludf.DUMMYFUNCTION("""COMPUTED_VALUE"""),"Ukraine War: Russians Flee To Dubai To Avoid Sanctions") -> Ukraine War: Russians Flee To Dubai To Avoid Sanctions | E63: =IFERROR(__xludf.DUMMYFUNCTION("""COMPUTED_VALUE"""),"https://leadership.ng/ukraine-war-russians-flee-to-dubai-to-avoid-sanctions/") -> https://leadership.ng/ukraine-war-russians-flee-to-dubai-to-avoid-sanctions/ | F63: =IFERROR(__xludf.DUMMYFUNCTION("""COMPUTED_VALUE"""),"Betterhomes") -> Betterhomes
A64: =IFERROR(__xludf.DUMMYFUNCTION("""COMPUTED_VALUE"""),44704.0) -> 44704 | B64: =IFERROR(__xludf.DUMMYFUNCTION("""COMPUTED_VALUE"""),"Tier 3") -> Tier 3 | C64: =IFERROR(__xludf.DUMMYFUNCTION("""COMPUTED_VALUE"""),"Cronella News") -> Cronella News | D64: =IFERROR(__xludf.DUMMYFUNCTION("""COMPUTED_VALUE"""),"To avoid sanctions, Russians flee to Dubai") -> To avoid sanctions, Russians flee to Dubai | E64: =IFERROR(__xludf.DUMMYFUNCTION("""COMPUTED_VALUE"""),"https://cronullanews.sydney/article/46343/to-avoid-sanctions-russians-flee-to-dubai/") -> https://cronullanews.sydney/article/46343/to-avoid-sanctions-russians-flee-to-dubai/ | F64: =IFERROR(__xludf.DUMMYFUNCTION("""COMPUTED_VALUE"""),"Betterhomes") -> Betterhomes
A65: =IFERROR(__xludf.DUMMYFUNCTION("""COMPUTED_VALUE"""),44708.0) -> 44708 | B65: =IFERROR(__xludf.DUMMYFUNCTION("""COMPUTED_VALUE"""),"Tier 2") -> Tier 2 | C65: =IFERROR(__xludf.DUMMYFUNCTION("""COMPUTED_VALUE"""),"The National") -> The National | D65: =IFERROR(__xludf.DUMMYFUNCTION("""COMPUTED_VALUE"""),"Nine questions to ask if you plan to rent or buy a property") -> Nine questions to ask if you plan to rent or buy a property | E65: =IFERROR(__xludf.DUMMYFUNCTION("""COMPUTED_VALUE"""),"https://www.thenationalnews.com/weekend/2022/05/27/nine-questions-to-ask-if-you-plan-to-rent-or-buy-a-property/") -> https://www.thenationalnews.com/weekend/2022/05/27/nine-questions-to-ask-if-you-plan-to-rent-or-buy-a-property/ | F65: =IFERROR(__xludf.DUMMYFUNCTION("""COMPUTED_VALUE"""),"Betterhomes") -> Betterhomes
A66: =IFERROR(__xludf.DUMMYFUNCTION("""COMPUTED_VALUE"""),44710.0) -> 44710 | B66: =IFERROR(__xludf.DUMMYFUNCTION("""COMPUTED_VALUE"""),"Tier 2") -> Tier 2 | C66: =IFERROR(__xludf.DUMMYFUNCTION("""COMPUTED_VALUE"""),"The National") -> The National | D66: =IFERROR(__xludf.DUMMYFUNCTION("""COMPUTED_VALUE"""),"What UAE families can do to keep down the cost of living") -> What UAE families can do to keep down the cost of living | E66: =IFERROR(__xludf.DUMMYFUNCTION("""COMPUTED_VALUE"""),"https://www.thenationalnews.com/uae/2022/05/29/what-uae-families-can-do-to-keep-down-the-cost-of-living/") -> https://www.thenationalnews.com/uae/2022/05/29/what-uae-families-can-do-to-keep-down-the-cost-of-living/ | F66: =IFERROR(__xludf.DUMMYFUNCTION("""COMPUTED_VALUE"""),"BH Mortgages") -> BH Mortgages
A67: =IFERROR(__xludf.DUMMYFUNCTION("""COMPUTED_VALUE"""),44711.0) -> 44711 | B67: =IFERROR(__xludf.DUMMYFUNCTION("""COMPUTED_VALUE"""),"Tier 2") -> Tier 2 | C67: =IFERROR(__xludf.DUMMYFUNCTION("""COMPUTED_VALUE"""),"Khaleej Times") -> Khaleej Times | D67: =IFERROR(__xludf.DUMMYFUNCTION("""COMPUTED_VALUE"""),"Dubai rents to pick up further in 2022") -> Dubai rents to pick up further in 2022 | E67: =IFERROR(__xludf.DUMMYFUNCTION("""COMPUTED_VALUE"""),"https://www.khaleejtimes.com/property/dubai-rents-to-pick-up-further-in-2022") -> https://www.khaleejtimes.com/property/dubai-rents-to-pick-up-further-in-2022 | F67: =IFERROR(__xludf.DUMMYFUNCTION("""COMPUTED_VALUE"""),"Betterhomes") -> Betterhomes
A68: =IFERROR(__xludf.DUMMYFUNCTION("""COMPUTED_VALUE"""),44711.0) -> 44711 | B68: =IFERROR(__xludf.DUMMYFUNCTION("""COMPUTED_VALUE"""),"Tier 2") -> Tier 2 | C68: =IFERROR(__xludf.DUMMYFUNCTION("""COMPUTED_VALUE"""),"Arabian Business ") -> Arabian Business | D68: =IFERROR(__xludf.DUMMYFUNCTION("""COMPUTED_VALUE"""),"The increase in interest rates has created an all-time high on mortgage applications") -> The increase in interest rates has created an all-time high on mortgage applications | E68: =IFERROR(__xludf.DUMMYFUNCTION("""COMPUTED_VALUE"""),"https://www.arabianbusiness.com/opinion/the-increase-in-interest-rates-has-created-an-all-time-high-on-mortgage-applications") -> https://www.arabianbusiness.com/opinion/the-increase-in-interest-rates-has-created-an-all-time-high-on-mortgage-applications | F68: =IFERROR(__xludf.DUMMYFUNCTION("""COMPUTED_VALUE"""),"BH Mortgages") -> BH Mortgages
A69: =IFERROR(__xludf.DUMMYFUNCTION("""COMPUTED_VALUE"""),44711.0) -> 44711 | B69: =IFERROR(__xludf.DUMMYFUNCTION("""COMPUTED_VALUE"""),"Tier 3") -> Tier 3 | C69: =IFERROR(__xludf.DUMMYFUNCTION("""COMPUTED_VALUE"""),"Mena FM") -> Mena FM | D69: =IFERROR(__xludf.DUMMYFUNCTION("""COMPUTED_VALUE"""),"Dubai Rents To Pick Up Further In 2022") -> Dubai Rents To Pick Up Further In 2022 | E69: =IFERROR(__xludf.DUMMYFUNCTION("""COMPUTED_VALUE"""),"https://menafn.com/1104294803/Dubai-Rents-To-Pick-Up-Further-In-2022") -> https://menafn.com/1104294803/Dubai-Rents-To-Pick-Up-Further-In-2022 | F69: =IFERROR(__xludf.DUMMYFUNCTION("""COMPUTED_VALUE"""),"Betterhomes") -> Betterhomes
A70: =IFERROR(__xludf.DUMMYFUNCTION("""COMPUTED_VALUE"""),44712.0) -> 44712 | B70: =IFERROR(__xludf.DUMMYFUNCTION("""COMPUTED_VALUE"""),"Tier 3") -> Tier 3 | C70: =IFERROR(__xludf.DUMMYFUNCTION("""COMPUTED_VALUE"""),"Reality Titbit") -> Reality Titbit | D70: =IFERROR(__xludf.DUMMYFUNCTION("""COMPUTED_VALUE"""),"Love Island's Andrew Le Page jets between Dubai and Guernsey as an estate agent") -> Love Island's Andrew Le Page jets between Dubai and Guernsey as an estate agent | E70: =IFERROR(__xludf.DUMMYFUNCTION("""COMPUTED_VALUE"""),"https://www.realitytitbit.com/dating/love-island/andrew-le-page-estate-agent") -> https://www.realitytitbit.com/dating/love-island/andrew-le-page-estate-agent | F70: =IFERROR(__xludf.DUMMYFUNCTION("""COMPUTED_VALUE"""),"Betterhomes") -> Betterhomes
A71: =IFERROR(__xludf.DUMMYFUNCTION("""COMPUTED_VALUE"""),44712.0) -> 44712 | B71: =IFERROR(__xludf.DUMMYFUNCTION("""COMPUTED_VALUE"""),"Tier 2") -> Tier 2 | C71: =IFERROR(__xludf.DUMMYFUNCTION("""COMPUTED_VALUE"""),"Whats On") -> Whats On | D71: =IFERROR(__xludf.DUMMYFUNCTION("""COMPUTED_VALUE"""),"A Dubai real estate agent is on the new series of Love Island") -> A Dubai real estate agent is on the new series of Love Island | E71: =IFERROR(__xludf.DUMMYFUNCTION("""COMPUTED_VALUE"""),"https://whatson.ae/2022/05/a-dubai-real-estate-agent-is-on-the-new-series-of-love-island/") -> https://whatson.ae/2022/05/a-dubai-real-estate-agent-is-on-the-new-series-of-love-island/ | F71: =IFERROR(__xludf.DUMMYFUNCTION("""COMPUTED_VALUE"""),"Betterhomes") -> Betterhomes
A72: =IFERROR(__xludf.DUMMYFUNCTION("""COMPUTED_VALUE"""),44713.0) -> 44713 | B72: =IFERROR(__xludf.DUMMYFUNCTION("""COMPUTED_VALUE"""),"Tier 3") -> Tier 3 | C72: =IFERROR(__xludf.DUMMYFUNCTION("""COMPUTED_VALUE"""),"Al Bawaba") -> Al Bawaba | D72: =IFERROR(__xludf.DUMMYFUNCTION("""COMPUTED_VALUE"""),"Bayut & Dubizzle Wow Real Estate Fraternity with the Region’s Biggest Proptech Summit, b3dxb 2022") -> Bayut & Dubizzle Wow Real Estate Fraternity with the Region’s Biggest Proptech Summit, b3dxb 2022 | E72: =IFERROR(__xludf.DUMMYFUNCTION("""COMPUTED_VALUE"""),"https://www.albawaba.com/business/pr/bayut-dubizzle-wow-real-estate-fraternity-region%E2%80%99s-biggest-proptech-summit-b3dxb-2022") -> https://www.albawaba.com/business/pr/bayut-dubizzle-wow-real-estate-fraternity-region%E2%80%99s-biggest-proptech-summit-b3dxb-2022 | F72: =IFERROR(__xludf.DUMMYFUNCTION("""COMPUTED_VALUE"""),"Betterhomes") -> Betterhomes
A73: =IFERROR(__xludf.DUMMYFUNCTION("""COMPUTED_VALUE"""),44714.0) -> 44714 | B73: =IFERROR(__xludf.DUMMYFUNCTION("""COMPUTED_VALUE"""),"Tier 2") -> Tier 2 | C73: =IFERROR(__xludf.DUMMYFUNCTION("""COMPUTED_VALUE"""),"Whats On") -> Whats On | D73: =IFERROR(__xludf.DUMMYFUNCTION("""COMPUTED_VALUE"""),"This Dubai bar is hosting a Love Island screening party") -> This Dubai bar is hosting a Love Island screening party | E73: =IFERROR(__xludf.DUMMYFUNCTION("""COMPUTED_VALUE"""),"https://whatson.ae/2022/06/dubai-bar-the-cheeky-camel-love-island-screening-party/") -> https://whatson.ae/2022/06/dubai-bar-the-cheeky-camel-love-island-screening-party/ | F73: =IFERROR(__xludf.DUMMYFUNCTION("""COMPUTED_VALUE"""),"Betterhomes") -> Betterhomes
A74: =IFERROR(__xludf.DUMMYFUNCTION("""COMPUTED_VALUE"""),44721.0) -> 44721 | B74: =IFERROR(__xludf.DUMMYFUNCTION("""COMPUTED_VALUE"""),"Tier 2") -> Tier 2 | C74: =IFERROR(__xludf.DUMMYFUNCTION("""COMPUTED_VALUE"""),"Zawya") -> Zawya | D74: =IFERROR(__xludf.DUMMYFUNCTION("""COMPUTED_VALUE"""),"CRC witnessed the demand for quality commercial office space hit its highest peak since 2016") -> CRC witnessed the demand for quality commercial office space hit its highest peak since 2016 | E74: =IFERROR(__xludf.DUMMYFUNCTION("""COMPUTED_VALUE"""),"https://www.zawya.com/en/press-release/companies-news/crc-witnessed-the-demand-for-quality-commercial-office-space-hit-its-highest-peak-since-2016-d8jtcq2t") -> https://www.zawya.com/en/press-release/companies-news/crc-witnessed-the-demand-for-quality-commercial-office-space-hit-its-highest-peak-since-2016-d8jtcq2t | F74: =IFERROR(__xludf.DUMMYFUNCTION("""COMPUTED_VALUE"""),"CRC") -> CRC
A75: =IFERROR(__xludf.DUMMYFUNCTION("""COMPUTED_VALUE"""),44721.0) -> 44721 | B75: =IFERROR(__xludf.DUMMYFUNCTION("""COMPUTED_VALUE"""),"Tier 2") -> Tier 2 | C75: =IFERROR(__xludf.DUMMYFUNCTION("""COMPUTED_VALUE"""),"ME Contruction News") -> ME Contruction News | D75: =IFERROR(__xludf.DUMMYFUNCTION("""COMPUTED_VALUE"""),"Grade A commercial real estate sees surge in May 2022 says CRC") -> Grade A commercial real estate sees surge in May 2022 says CRC | E75: =IFERROR(__xludf.DUMMYFUNCTION("""COMPUTED_VALUE"""),"https://meconstructionnews.com/52640/grade-a-commercial-real-estate-sees-surge-in-may-2022-says-crc") -> https://meconstructionnews.com/52640/grade-a-commercial-real-estate-sees-surge-in-may-2022-says-crc | F75: =IFERROR(__xludf.DUMMYFUNCTION("""COMPUTED_VALUE"""),"CRC") -> CRC
A76: =IFERROR(__xludf.DUMMYFUNCTION("""COMPUTED_VALUE"""),44724.0) -> 44724 | B76: =IFERROR(__xludf.DUMMYFUNCTION("""COMPUTED_VALUE"""),"Tier 2") -> Tier 2 | C76: =IFERROR(__xludf.DUMMYFUNCTION("""COMPUTED_VALUE"""),"The Guardian") -> The Guardian | D76: =IFERROR(__xludf.DUMMYFUNCTION("""COMPUTED_VALUE"""),"Blacklist Dubai over failure to crack down on Russian oligarchs, say campaigners") -> Blacklist Dubai over failure to crack down on Russian oligarchs, say campaigners | E76: =IFERROR(__xludf.DUMMYFUNCTION("""COMPUTED_VALUE"""),"https://www.theguardian.com/world/2022/jun/11/blacklist-dubai-uae-over-russian-oligarchs-say-ukraine-campaigners") -> https://www.theguardian.com/world/2022/jun/11/blacklist-dubai-uae-over-russian-oligarchs-say-ukraine-campaigners | F76: =IFERROR(__xludf.DUMMYFUNCTION("""COMPUTED_VALUE"""),"Betterhomes") -> Betterhomes
A77: =IFERROR(__xludf.DUMMYFUNCTION("""COMPUTED_VALUE"""),44724.0) -> 44724 | B77: =IFERROR(__xludf.DUMMYFUNCTION("""COMPUTED_VALUE"""),"Tier 3") -> Tier 3 | C77: =IFERROR(__xludf.DUMMYFUNCTION("""COMPUTED_VALUE"""),"The New Arab") -> The New Arab | D77: =IFERROR(__xludf.DUMMYFUNCTION("""COMPUTED_VALUE"""),"UAE a 'haven for oligarchs' that must be blacklisted:critics") -> UAE a 'haven for oligarchs' that must be blacklisted:critics | E77: =IFERROR(__xludf.DUMMYFUNCTION("""COMPUTED_VALUE"""),"https://english.alaraby.co.uk/news/uae-haven-oligarchs-must-be-blacklistedcritics") -> https://english.alaraby.co.uk/news/uae-haven-oligarchs-must-be-blacklistedcritics | F77: =IFERROR(__xludf.DUMMYFUNCTION("""COMPUTED_VALUE"""),"Betterhomes") -> Betterhomes
A78: =IFERROR(__xludf.DUMMYFUNCTION("""COMPUTED_VALUE"""),44727.0) -> 44727 | B78: =IFERROR(__xludf.DUMMYFUNCTION("""COMPUTED_VALUE"""),"Tier 3") -> Tier 3 | C78: =IFERROR(__xludf.DUMMYFUNCTION("""COMPUTED_VALUE"""),"Euroeporter") -> Euroeporter | D78: =IFERROR(__xludf.DUMMYFUNCTION("""COMPUTED_VALUE"""),"United Arab Emirates has emerged as a haven for Russians fleeing the impact of western sanctions - but how long will it last?") -> United Arab Emirates has emerged as a haven for Russians fleeing the impact of western sanctions - but how long will it last? | E78: =IFERROR(__xludf.DUMMYFUNCTION("""COMPUTED_VALUE"""),"https://www.eureporter.co/world/ukraine/2022/06/14/united-arab-emirates-has-emerged-as-a-haven-for-russians-fleeing-the-impact-of-western-sanctions-but-how-long-will-it-last/") -> https://www.eureporter.co/world/ukraine/2022/06/14/united-arab-emirates-has-emerged-as-a-haven-for-russians-fleeing-the-impact-of-western-sanctions-but-how-long-will-it-last/ | F78: =IFERROR(__xludf.DUMMYFUNCTION("""COMPUTED_VALUE"""),"Betterhomes") -> Betterhomes
A79: =IFERROR(__xludf.DUMMYFUNCTION("""COMPUTED_VALUE"""),44732.0) -> 44732 | B79: =IFERROR(__xludf.DUMMYFUNCTION("""COMPUTED_VALUE"""),"Tier 2") -> Tier 2 | C79: =IFERROR(__xludf.DUMMYFUNCTION("""COMPUTED_VALUE"""),"Zawya") -> Zawya | D79: =IFERROR(__xludf.DUMMYFUNCTION("""COMPUTED_VALUE"""),"Russian investors in Dubai real estate have doubled in 2022, top brokers say") -> Russian investors in Dubai real estate have doubled in 2022, top brokers say | E79: =IFERROR(__xludf.DUMMYFUNCTION("""COMPUTED_VALUE"""),"https://www.zawya.com/en/business/real-estate/russian-investors-in-dubai-real-estate-have-doubled-in-2022-top-brokers-say-cdr6sqp0") -> https://www.zawya.com/en/business/real-estate/russian-investors-in-dubai-real-estate-have-doubled-in-2022-top-brokers-say-cdr6sqp0 | F79: =IFERROR(__xludf.DUMMYFUNCTION("""COMPUTED_VALUE"""),"Betterhomes") -> Betterhomes
A80: =IFERROR(__xludf.DUMMYFUNCTION("""COMPUTED_VALUE"""),44732.0) -> 44732 | B80: =IFERROR(__xludf.DUMMYFUNCTION("""COMPUTED_VALUE"""),"Tier 2") -> Tier 2 | C80: =IFERROR(__xludf.DUMMYFUNCTION("""COMPUTED_VALUE"""),"Gulf News") -> Gulf News | D80: =IFERROR(__xludf.DUMMYFUNCTION("""COMPUTED_VALUE"""),"Dubai developers need to bring back longer post-handover payment plans to help offplan buyers") -> Dubai developers need to bring back longer post-handover payment plans to help offplan buyers | E80: =IFERROR(__xludf.DUMMYFUNCTION("""COMPUTED_VALUE"""),"https://gulfnews.com/business/property/dubai-developers-need-to-bring-back-longer-post-handover-payment-plans-to-help-offplan-buyers-1.1655783971158") -> https://gulfnews.com/business/property/dubai-developers-need-to-bring-back-longer-post-handover-payment-plans-to-help-offplan-buyers-1.1655783971158 | F80: =IFERROR(__xludf.DUMMYFUNCTION("""COMPUTED_VALUE"""),"BH Off-Plan") -> BH Off-Plan
A81: =IFERROR(__xludf.DUMMYFUNCTION("""COMPUTED_VALUE"""),44733.0) -> 44733 | B81: =IFERROR(__xludf.DUMMYFUNCTION("""COMPUTED_VALUE"""),"Tier 2") -> Tier 2 | C81: =IFERROR(__xludf.DUMMYFUNCTION("""COMPUTED_VALUE"""),"The National ") -> The National | D81: =IFERROR(__xludf.DUMMYFUNCTION("""COMPUTED_VALUE"""),"Has Dubai’s city centre turned towards Business Bay amid soaring property prices?") -> Has Dubai’s city centre turned towards Business Bay amid soaring property prices? | E81: =IFERROR(__xludf.DUMMYFUNCTION("""COMPUTED_VALUE"""),"https://www.thenationalnews.com/business/property/2022/06/21/has-dubais-city-centre-turned-towards-business-bay-amid-soaring-property-prices/") -> https://www.thenationalnews.com/business/property/2022/06/21/has-dubais-city-centre-turned-towards-business-bay-amid-soaring-property-prices/ | F81: =IFERROR(__xludf.DUMMYFUNCTION("""COMPUTED_VALUE"""),"Betterhomes") -> Betterhomes
A82: =IFERROR(__xludf.DUMMYFUNCTION("""COMPUTED_VALUE"""),44735.0) -> 44735 | B82: =IFERROR(__xludf.DUMMYFUNCTION("""COMPUTED_VALUE"""),"Tier 2") -> Tier 2 | C82: =IFERROR(__xludf.DUMMYFUNCTION("""COMPUTED_VALUE"""),"Zawya") -> Zawya | D82: =IFERROR(__xludf.DUMMYFUNCTION("""COMPUTED_VALUE"""),"Untapped areas remain ripe for luxury development amidst market boom") -> Untapped areas remain ripe for luxury development amidst market boom | E82: =IFERROR(__xludf.DUMMYFUNCTION("""COMPUTED_VALUE"""),"https://www.zawya.com/en/press-release/companies-news/untapped-areas-remain-ripe-for-luxury-development-amidst-market-boom-rk7x6fdr") -> https://www.zawya.com/en/press-release/companies-news/untapped-areas-remain-ripe-for-luxury-development-amidst-market-boom-rk7x6fdr | F82: =IFERROR(__xludf.DUMMYFUNCTION("""COMPUTED_VALUE"""),"Betterhomes") -> Betterhomes
A83: =IFERROR(__xludf.DUMMYFUNCTION("""COMPUTED_VALUE"""),44740.0) -> 44740 | B83: =IFERROR(__xludf.DUMMYFUNCTION("""COMPUTED_VALUE"""),"Tier 2") -> Tier 2 | C83: =IFERROR(__xludf.DUMMYFUNCTION("""COMPUTED_VALUE"""),"The National ") -> The National | D83: =IFERROR(__xludf.DUMMYFUNCTION("""COMPUTED_VALUE"""),"Is now the time to invest in UAE property? — 'Pocketful of Dirhams'") -> Is now the time to invest in UAE property? — 'Pocketful of Dirhams' | E83: =IFERROR(__xludf.DUMMYFUNCTION("""COMPUTED_VALUE"""),"https://www.thenationalnews.com/podcasts/pocketful-of-dirhams/2022/06/28/is-now-the-time-to-invest-in-uae-property-pocketful-of-dirhams/") -> https://www.thenationalnews.com/podcasts/pocketful-of-dirhams/2022/06/28/is-now-the-time-to-invest-in-uae-property-pocketful-of-dirhams/ | F83: =IFERROR(__xludf.DUMMYFUNCTION("""COMPUTED_VALUE"""),"Betterhomes") -> Betterhomes
A84: =IFERROR(__xludf.DUMMYFUNCTION("""COMPUTED_VALUE"""),44749.0) -> 44749 | B84: =IFERROR(__xludf.DUMMYFUNCTION("""COMPUTED_VALUE"""),"Tier 2") -> Tier 2 | C84: =IFERROR(__xludf.DUMMYFUNCTION("""COMPUTED_VALUE"""),"Zawya") -> Zawya | D84: =IFERROR(__xludf.DUMMYFUNCTION("""COMPUTED_VALUE"""),"Houza.com, the Dubai-based property portal appoints Jean-Pierre Mondalek as CEO") -> Houza.com, the Dubai-based property portal appoints Jean-Pierre Mondalek as CEO | E84: =IFERROR(__xludf.DUMMYFUNCTION("""COMPUTED_VALUE"""),"https://www.zawya.com/en/press-release/people-in-the-news/houzacom-the-dubai-based-property-portal-appoints-jean-pierre-mondalek-as-ceo-sj0mqcvm") -> https://www.zawya.com/en/press-release/people-in-the-news/houzacom-the-dubai-based-property-portal-appoints-jean-pierre-mondalek-as-ceo-sj0mqcvm | F84: =IFERROR(__xludf.DUMMYFUNCTION("""COMPUTED_VALUE"""),"Betterhomes") -> Betterhomes
A85: =IFERROR(__xludf.DUMMYFUNCTION("""COMPUTED_VALUE"""),44750.0) -> 44750 | B85: =IFERROR(__xludf.DUMMYFUNCTION("""COMPUTED_VALUE"""),"Tier 1") -> Tier 1 | C85: =IFERROR(__xludf.DUMMYFUNCTION("""COMPUTED_VALUE"""),"CNBC") -> CNBC | D85: =IFERROR(__xludf.DUMMYFUNCTION("""COMPUTED_VALUE"""),"Villas by the sea: Rich Russians fleeing sanctions are pumping up Dubai’s property sector") -> Villas by the sea: Rich Russians fleeing sanctions are pumping up Dubai’s property sector | E85: =IFERROR(__xludf.DUMMYFUNCTION("""COMPUTED_VALUE"""),"https://www.cnbc.com/2022/07/07/rich-russians-fleeing-sanctions-are-pumping-up-dubais-property-sector.html") -> https://www.cnbc.com/2022/07/07/rich-russians-fleeing-sanctions-are-pumping-up-dubais-property-sector.html | F85: =IFERROR(__xludf.DUMMYFUNCTION("""COMPUTED_VALUE"""),"Betterhomes") -> Betterhomes
A86: =IFERROR(__xludf.DUMMYFUNCTION("""COMPUTED_VALUE"""),44750.0) -> 44750 | B86: =IFERROR(__xludf.DUMMYFUNCTION("""COMPUTED_VALUE"""),"Tier 2") -> Tier 2 | C86: =IFERROR(__xludf.DUMMYFUNCTION("""COMPUTED_VALUE"""),"The National ") -> The National | D86: =IFERROR(__xludf.DUMMYFUNCTION("""COMPUTED_VALUE"""),"Are top Dubai property prices going above Dh300m?") -> Are top Dubai property prices going above Dh300m? | E86: =IFERROR(__xludf.DUMMYFUNCTION("""COMPUTED_VALUE"""),"https://www.thenationalnews.com/business/property/2022/07/08/are-top-dubai-property-prices-going-above-dh300m/") -> https://www.thenationalnews.com/business/property/2022/07/08/are-top-dubai-property-prices-going-above-dh300m/ | F86: =IFERROR(__xludf.DUMMYFUNCTION("""COMPUTED_VALUE"""),"Betterhomes") -> Betterhomes
A87: =IFERROR(__xludf.DUMMYFUNCTION("""COMPUTED_VALUE"""),44750.0) -> 44750 | B87: =IFERROR(__xludf.DUMMYFUNCTION("""COMPUTED_VALUE"""),"Tier 3") -> Tier 3 | C87: =IFERROR(__xludf.DUMMYFUNCTION("""COMPUTED_VALUE"""),"Kalgoorlie Miner") -> Kalgoorlie Miner | D87: =IFERROR(__xludf.DUMMYFUNCTION("""COMPUTED_VALUE"""),"Villas by the sea: Rich Russians fleeing sanctions are pumping up Dubai’s property sector") -> Villas by the sea: Rich Russians fleeing sanctions are pumping up Dubai’s property sector | E87: =IFERROR(__xludf.DUMMYFUNCTION("""COMPUTED_VALUE"""),"https://www.kalminer.com.au/business/cnbc/villas-by-the-sea-rich-russians-fleeing-sanctions-are-pumping-up-dubais-property-sector-c-7449496") -> https://www.kalminer.com.au/business/cnbc/villas-by-the-sea-rich-russians-fleeing-sanctions-are-pumping-up-dubais-property-sector-c-7449496 | F87: =IFERROR(__xludf.DUMMYFUNCTION("""COMPUTED_VALUE"""),"Betterhomes") -> Betterhomes
A88: =IFERROR(__xludf.DUMMYFUNCTION("""COMPUTED_VALUE"""),44755.0) -> 44755 | B88: =IFERROR(__xludf.DUMMYFUNCTION("""COMPUTED_VALUE"""),"Tier 2") -> Tier 2 | C88: =IFERROR(__xludf.DUMMYFUNCTION("""COMPUTED_VALUE"""),"Gulf News") -> Gulf News | D88: =IFERROR(__xludf.DUMMYFUNCTION("""COMPUTED_VALUE"""),"Planning to rent a new home in Dubai - then just do it fast") -> Planning to rent a new home in Dubai - then just do it fast | E88: =IFERROR(__xludf.DUMMYFUNCTION("""COMPUTED_VALUE"""),"https://gulfnews.com/business/property/planning-to-rent-a-new-home-in-dubai---then-just-do-it-fast-1.1657682956150") -> https://gulfnews.com/business/property/planning-to-rent-a-new-home-in-dubai---then-just-do-it-fast-1.1657682956150 | F88: =IFERROR(__xludf.DUMMYFUNCTION("""COMPUTED_VALUE"""),"Betterhomes") -> Betterhomes
A89: =IFERROR(__xludf.DUMMYFUNCTION("""COMPUTED_VALUE"""),44760.0) -> 44760 | B89: =IFERROR(__xludf.DUMMYFUNCTION("""COMPUTED_VALUE"""),"Tier 2") -> Tier 2 | C89: =IFERROR(__xludf.DUMMYFUNCTION("""COMPUTED_VALUE"""),"Arabian Business ") -> Arabian Business | D89: =IFERROR(__xludf.DUMMYFUNCTION("""COMPUTED_VALUE"""),"Dubai commercial real estate sales value jumps 89 percent in first half of 2022: Report") -> Dubai commercial real estate sales value jumps 89 percent in first half of 2022: Report | E89: =IFERROR(__xludf.DUMMYFUNCTION("""COMPUTED_VALUE"""),"https://www.arabianbusiness.com/money/wealth/money-wealth-real-estate/dubai-commercial-real-estate-sales-value-jumps-89-percent-in-first-half-of-2022-report") -> https://www.arabianbusiness.com/money/wealth/money-wealth-real-estate/dubai-commercial-real-estate-sales-value-jumps-89-percent-in-first-half-of-2022-report | F89: =IFERROR(__xludf.DUMMYFUNCTION("""COMPUTED_VALUE"""),"CRC") -> CRC
A90: =IFERROR(__xludf.DUMMYFUNCTION("""COMPUTED_VALUE"""),44761.0) -> 44761 | B90: =IFERROR(__xludf.DUMMYFUNCTION("""COMPUTED_VALUE"""),"Tier 2") -> Tier 2 | C90: =IFERROR(__xludf.DUMMYFUNCTION("""COMPUTED_VALUE"""),"Zawya") -> Zawya | D90: =IFERROR(__xludf.DUMMYFUNCTION("""COMPUTED_VALUE"""),"The commercial real estate market witnessed 89% growth in sales for H1 2022") -> The commercial real estate market witnessed 89% growth in sales for H1 2022 | E90: =IFERROR(__xludf.DUMMYFUNCTION("""COMPUTED_VALUE"""),"https://www.zawya.com/en/press-release/research-and-studies/the-commercial-real-estate-market-witnessed-89-growth-in-sales-for-h1-2022-yke1ratr") -> https://www.zawya.com/en/press-release/research-and-studies/the-commercial-real-estate-market-witnessed-89-growth-in-sales-for-h1-2022-yke1ratr | F90: =IFERROR(__xludf.DUMMYFUNCTION("""COMPUTED_VALUE"""),"CRC") -> CRC
A91: =IFERROR(__xludf.DUMMYFUNCTION("""COMPUTED_VALUE"""),44762.0) -> 44762 | B91: =IFERROR(__xludf.DUMMYFUNCTION("""COMPUTED_VALUE"""),"Tier 2") -> Tier 2 | C91: =IFERROR(__xludf.DUMMYFUNCTION("""COMPUTED_VALUE"""),"Dubai eye 103.8") -> Dubai eye 103.8 | D91: =IFERROR(__xludf.DUMMYFUNCTION("""COMPUTED_VALUE"""),"Market Report Interview ") -> Market Report Interview | E91: =IFERROR(__xludf.DUMMYFUNCTION("""COMPUTED_VALUE"""),"https://www.linkedin.com/posts/crc-property_head-of-crc-andrew-elliott-live-on-the-business-activity-6957618158002139136-Osgl?utm_source=linkedin_share&utm_medium=member_desktop_web") -> https://www.linkedin.com/posts/crc-property_head-of-crc-andrew-elliott-live-on-the-business-activity-6957618158002139136-Osgl?utm_source=linkedin_share&utm_medium=member_desktop_web | F91: =IFERROR(__xludf.DUMMYFUNCTION("""COMPUTED_VALUE"""),"CRC") -> CRC
A92: =IFERROR(__xludf.DUMMYFUNCTION("""COMPUTED_VALUE"""),44768.0) -> 44768 | B92: =IFERROR(__xludf.DUMMYFUNCTION("""COMPUTED_VALUE"""),"Tier 2") -> Tier 2 | C92: =IFERROR(__xludf.DUMMYFUNCTION("""COMPUTED_VALUE"""),"Gulf News") -> Gulf News | D92: =IFERROR(__xludf.DUMMYFUNCTION("""COMPUTED_VALUE"""),"In Dubai, residents find rent renewals offer cheaper option in H1-2022") -> In Dubai, residents find rent renewals offer cheaper option in H1-2022 | E92: =IFERROR(__xludf.DUMMYFUNCTION("""COMPUTED_VALUE"""),"https://gulfnews.com/business/property/in-dubai-residents-find-rent-renewals-offer-cheaper-option-in-h1-2022-1.89517839") -> https://gulfnews.com/business/property/in-dubai-residents-find-rent-renewals-offer-cheaper-option-in-h1-2022-1.89517839 | F92: =IFERROR(__xludf.DUMMYFUNCTION("""COMPUTED_VALUE"""),"Betterhomes") -> Betterhomes
A93: =IFERROR(__xludf.DUMMYFUNCTION("""COMPUTED_VALUE"""),44769.0) -> 44769 | B93: =IFERROR(__xludf.DUMMYFUNCTION("""COMPUTED_VALUE"""),"Tier 2") -> Tier 2 | C93: =IFERROR(__xludf.DUMMYFUNCTION("""COMPUTED_VALUE"""),"Dubai eye ") -> Dubai eye | D93: =IFERROR(__xludf.DUMMYFUNCTION("""COMPUTED_VALUE"""),"Market Report Interview ") -> Market Report Interview | E93: =IFERROR(__xludf.DUMMYFUNCTION("""COMPUTED_VALUE"""),"https://www.linkedin.com/posts/better-homes-llc_richard-waind-on-the-business-breakfast-activity-6958047289240117249-kP3m?utm_source=linkedin_share&utm_medium=member_desktop_web") -> https://www.linkedin.com/posts/better-homes-llc_richard-waind-on-the-business-breakfast-activity-6958047289240117249-kP3m?utm_source=linkedin_share&utm_medium=member_desktop_web | F93: =IFERROR(__xludf.DUMMYFUNCTION("""COMPUTED_VALUE"""),"Betterhomes") -> Betterhomes
A94: =IFERROR(__xludf.DUMMYFUNCTION("""COMPUTED_VALUE"""),44770.0) -> 44770 | B94: =IFERROR(__xludf.DUMMYFUNCTION("""COMPUTED_VALUE"""),"Tier 2") -> Tier 2 | C94: =IFERROR(__xludf.DUMMYFUNCTION("""COMPUTED_VALUE"""),"Khaleej Times") -> Khaleej Times | D94: =IFERROR(__xludf.DUMMYFUNCTION("""COMPUTED_VALUE"""),"Dubai remains prime target of property investors") -> Dubai remains prime target of property investors | E94: =IFERROR(__xludf.DUMMYFUNCTION("""COMPUTED_VALUE"""),"https://www.khaleejtimes.com/business/dubai-remains-prime-target-of-property-investors") -> https://www.khaleejtimes.com/business/dubai-remains-prime-target-of-property-investors | F94: =IFERROR(__xludf.DUMMYFUNCTION("""COMPUTED_VALUE"""),"Betterhomes") -> Betterhomes
A95: =IFERROR(__xludf.DUMMYFUNCTION("""COMPUTED_VALUE"""),44770.0) -> 44770 | B95: =IFERROR(__xludf.DUMMYFUNCTION("""COMPUTED_VALUE"""),"Tier 2") -> Tier 2 | C95: =IFERROR(__xludf.DUMMYFUNCTION("""COMPUTED_VALUE"""),"Zawya") -> Zawya | D95: =IFERROR(__xludf.DUMMYFUNCTION("""COMPUTED_VALUE"""),"Dubai remains prime target of property investors") -> Dubai remains prime target of property investors | E95: =IFERROR(__xludf.DUMMYFUNCTION("""COMPUTED_VALUE"""),"https://www.zawya.com/en/business/real-estate/dubai-remains-prime-target-of-property-investors-rx1gcgeg") -> https://www.zawya.com/en/business/real-estate/dubai-remains-prime-target-of-property-investors-rx1gcgeg | F95: =IFERROR(__xludf.DUMMYFUNCTION("""COMPUTED_VALUE"""),"Betterhomes") -> Betterhomes
A96: =IFERROR(__xludf.DUMMYFUNCTION("""COMPUTED_VALUE"""),44770.0) -> 44770 | B96: =IFERROR(__xludf.DUMMYFUNCTION("""COMPUTED_VALUE"""),"Tier 2") -> Tier 2 | C96: =IFERROR(__xludf.DUMMYFUNCTION("""COMPUTED_VALUE"""),"Zawya") -> Zawya | D96: =IFERROR(__xludf.DUMMYFUNCTION("""COMPUTED_VALUE"""),"Russians are fourth-largest homebuyers in Dubai this year") -> Russians are fourth-largest homebuyers in Dubai this year | E96: =IFERROR(__xludf.DUMMYFUNCTION("""COMPUTED_VALUE"""),"https://www.zawya.com/en/business/real-estate/russians-are-fourth-largest-homebuyers-in-dubai-this-year-llwluic0") -> https://www.zawya.com/en/business/real-estate/russians-are-fourth-largest-homebuyers-in-dubai-this-year-llwluic0 | F96: =IFERROR(__xludf.DUMMYFUNCTION("""COMPUTED_VALUE"""),"Betterhomes") -> Betterhomes
A97: =IFERROR(__xludf.DUMMYFUNCTION("""COMPUTED_VALUE"""),44771.0) -> 44771 | B97: =IFERROR(__xludf.DUMMYFUNCTION("""COMPUTED_VALUE"""),"Tier 1") -> Tier 1 | C97: =IFERROR(__xludf.DUMMYFUNCTION("""COMPUTED_VALUE"""),"Thomson Reuters") -> Thomson Reuters | D97: =IFERROR(__xludf.DUMMYFUNCTION("""COMPUTED_VALUE"""),"Dubai real estate sales surge 60% as investors, Russians snap up property") -> Dubai real estate sales surge 60% as investors, Russians snap up property | E97: =IFERROR(__xludf.DUMMYFUNCTION("""COMPUTED_VALUE"""),"https://www.reuters.com/markets/europe/dubai-real-estate-sales-surge-60-investors-russians-snap-up-property-2022-07-28/") -> https://www.reuters.com/markets/europe/dubai-real-estate-sales-surge-60-investors-russians-snap-up-property-2022-07-28/ | F97: =IFERROR(__xludf.DUMMYFUNCTION("""COMPUTED_VALUE"""),"Betterhomes") -> Betterhomes
A98: =IFERROR(__xludf.DUMMYFUNCTION("""COMPUTED_VALUE"""),44771.0) -> 44771 | B98: =IFERROR(__xludf.DUMMYFUNCTION("""COMPUTED_VALUE"""),"Tier 2") -> Tier 2 | C98: =IFERROR(__xludf.DUMMYFUNCTION("""COMPUTED_VALUE"""),"Construction Week") -> Construction Week | D98: =IFERROR(__xludf.DUMMYFUNCTION("""COMPUTED_VALUE"""),"Betterhomes reports 60% increase in total units sold in Dubai in H1 2022") -> Betterhomes reports 60% increase in total units sold in Dubai in H1 2022 | E98: =IFERROR(__xludf.DUMMYFUNCTION("""COMPUTED_VALUE"""),"https://www.constructionweekonline.com/business/betterhomes-report-h1-2022") -> https://www.constructionweekonline.com/business/betterhomes-report-h1-2022 | F98: =IFERROR(__xludf.DUMMYFUNCTION("""COMPUTED_VALUE"""),"Betterhomes") -> Betterhomes
A99: =IFERROR(__xludf.DUMMYFUNCTION("""COMPUTED_VALUE"""),44771.0) -> 44771 | B99: =IFERROR(__xludf.DUMMYFUNCTION("""COMPUTED_VALUE"""),"Tier 3") -> Tier 3 | C99: =IFERROR(__xludf.DUMMYFUNCTION("""COMPUTED_VALUE"""),"The Economic Times") -> The Economic Times | D99: =IFERROR(__xludf.DUMMYFUNCTION("""COMPUTED_VALUE"""),"Dubai real estate sales surge 60% as investors, Russians snap up property") -> Dubai real estate sales surge 60% as investors, Russians snap up property | E99: =IFERROR(__xludf.DUMMYFUNCTION("""COMPUTED_VALUE"""),"https://economictimes.indiatimes.com/news/international/uae/dubai-real-estate-sales-surge-60-as-investors-russians-snap-up-property/articleshow/93194871.cms?from=mdr") -> https://economictimes.indiatimes.com/news/international/uae/dubai-real-estate-sales-surge-60-as-investors-russians-snap-up-property/articleshow/93194871.cms?from=mdr | F99: =IFERROR(__xludf.DUMMYFUNCTION("""COMPUTED_VALUE"""),"Betterhomes") -> Betterhomes
A100: =IFERROR(__xludf.DUMMYFUNCTION("""COMPUTED_VALUE"""),44771.0) -> 44771 | B100: =IFERROR(__xludf.DUMMYFUNCTION("""COMPUTED_VALUE"""),"Tier 3") -> Tier 3 | C100: =IFERROR(__xludf.DUMMYFUNCTION("""COMPUTED_VALUE"""),"The Business Times") -> The Business Times | D100: =IFERROR(__xludf.DUMMYFUNCTION("""COMPUTED_VALUE"""),"Dubai real estate sales surge 60% as investors, Russians snap up property") -> Dubai real estate sales surge 60% as investors, Russians snap up property | E100: =IFERROR(__xludf.DUMMYFUNCTION("""COMPUTED_VALUE"""),"https://www.businesstimes.com.sg/real-estate/dubai-real-estate-sales-surge-60-as-investors-russians-snap-up-property") -> https://www.businesstimes.com.sg/real-estate/dubai-real-estate-sales-surge-60-as-investors-russians-snap-up-property | F100: =IFERROR(__xludf.DUMMYFUNCTION("""COMPUTED_VALUE"""),"Betterhomes") -> Betterhomes
...

Sheet Charts
C1: 2020 | D1: =C1+1 -> 2021 | E1: =D1+1 -> 2022 | F1: =E1+1 -> 2023
A2: 1 | B2: Jan | C2: =IFERROR(__xludf.DUMMYFUNCTION("QUERY(Concat!$A:$F,""SELECT COUNT(E) WHERE A >= date '""&TEXT(DATEVALUE(DATE(C$1,$A2,1)),""yyyy-mm-dd"")&""' AND A < date '""&TEXT(DATEVALUE(EDATE(DATE(C$1,$A2,1),1)),""yyyy-mm-dd"")&""' LABEL COUNT(E) '' "", 0)"),1.0) -> 1 | D2: =IFERROR(__xludf.DUMMYFUNCTION("QUERY(Concat!$A:$F,""SELECT COUNT(E) WHERE A >= date '""&TEXT(DATEVALUE(DATE(D$1,$A2,1)),""yyyy-mm-dd"")&""' AND A < date '""&TEXT(DATEVALUE(EDATE(DATE(D$1,$A2,1),1)),""yyyy-mm-dd"")&""' LABEL COUNT(E) '' "", 0)"),"#N/A") -> #N/A | E2: =IFERROR(__xludf.DUMMYFUNCTION("QUERY(Concat!$A:$F,""SELECT COUNT(E) WHERE A >= date '""&TEXT(DATEVALUE(DATE(E$1,$A2,1)),""yyyy-mm-dd"")&""' AND A < date '""&TEXT(DATEVALUE(EDATE(DATE(E$1,$A2,1),1)),""yyyy-mm-dd"")&""' LABEL COUNT(E) '' "", 0)"),"#N/A") -> #N/A | F2: =IFERROR(__xludf.DUMMYFUNCTION("QUERY(Concat!$A:$F,""SELECT COUNT(E) WHERE A >= date '""&TEXT(DATEVALUE(DATE(F$1,$A2,1)),""yyyy-mm-dd"")&""' AND A < date '""&TEXT(DATEVALUE(EDATE(DATE(F$1,$A2,1),1)),""yyyy-mm-dd"")&""' LABEL COUNT(E) '' "", 0)"),35.0) -> 35
A3: 2 | B3: Feb | C3: =IFERROR(__xludf.DUMMYFUNCTION("QUERY(Concat!$A:$F,""SELECT COUNT(E) WHERE A >= date '""&TEXT(DATEVALUE(DATE(C$1,$A3,1)),""yyyy-mm-dd"")&""' AND A < date '""&TEXT(DATEVALUE(EDATE(DATE(C$1,$A3,1),1)),""yyyy-mm-dd"")&""' LABEL COUNT(E) '' "", 0)"),1.0) -> 1 | D3: =IFERROR(__xludf.DUMMYFUNCTION("QUERY(Concat!$A:$F,""SELECT COUNT(E) WHERE A >= date '""&TEXT(DATEVALUE(DATE(D$1,$A3,1)),""yyyy-mm-dd"")&""' AND A < date '""&TEXT(DATEVALUE(EDATE(DATE(D$1,$A3,1),1)),""yyyy-mm-dd"")&""' LABEL COUNT(E) '' "", 0)"),"#N/A") -> #N/A | E3: =IFERROR(__xludf.DUMMYFUNCTION("QUERY(Concat!$A:$F,""SELECT COUNT(E) WHERE A >= date '""&TEXT(DATEVALUE(DATE(E$1,$A3,1)),""yyyy-mm-dd"")&""' AND A < date '""&TEXT(DATEVALUE(EDATE(DATE(E$1,$A3,1),1)),""yyyy-mm-dd"")&""' LABEL COUNT(E) '' "", 0)"),"#N/A") -> #N/A | F3: =IFERROR(__xludf.DUMMYFUNCTION("QUERY(Concat!$A:$F,""SELECT COUNT(E) WHERE A >= date '""&TEXT(DATEVALUE(DATE(F$1,$A3,1)),""yyyy-mm-dd"")&""' AND A < date '""&TEXT(DATEVALUE(EDATE(DATE(F$1,$A3,1),1)),""yyyy-mm-dd"")&""' LABEL COUNT(E) '' "", 0)"),27.0) -> 27
A4: 3 | B4: Mar | C4: =IFERROR(__xludf.DUMMYFUNCTION("QUERY(Concat!$A:$F,""SELECT COUNT(E) WHERE A >= date '""&TEXT(DATEVALUE(DATE(C$1,$A4,1)),""yyyy-mm-dd"")&""' AND A < date '""&TEXT(DATEVALUE(EDATE(DATE(C$1,$A4,1),1)),""yyyy-mm-dd"")&""' LABEL COUNT(E) '' "", 0)"),2.0) -> 2 | D4: =IFERROR(__xludf.DUMMYFUNCTION("QUERY(Concat!$A:$F,""SELECT COUNT(E) WHERE A >= date '""&TEXT(DATEVALUE(DATE(D$1,$A4,1)),""yyyy-mm-dd"")&""' AND A < date '""&TEXT(DATEVALUE(EDATE(DATE(D$1,$A4,1),1)),""yyyy-mm-dd"")&""' LABEL COUNT(E) '' "", 0)"),"#N/A") -> #N/A | E4: =IFERROR(__xludf.DUMMYFUNCTION("QUERY(Concat!$A:$F,""SELECT COUNT(E) WHERE A >= date '""&TEXT(DATEVALUE(DATE(E$1,$A4,1)),""yyyy-mm-dd"")&""' AND A < date '""&TEXT(DATEVALUE(EDATE(DATE(E$1,$A4,1),1)),""yyyy-mm-dd"")&""' LABEL COUNT(E) '' "", 0)"),1.0) -> 1 | F4: =IFERROR(__xludf.DUMMYFUNCTION("QUERY(Concat!$A:$F,""SELECT COUNT(E) WHERE A >= date '""&TEXT(DATEVALUE(DATE(F$1,$A4,1)),""yyyy-mm-dd"")&""' AND A < date '""&TEXT(DATEVALUE(EDATE(DATE(F$1,$A4,1),1)),""yyyy-mm-dd"")&""' LABEL COUNT(E) '' "", 0)"),23.0) -> 23
A5: 4 | B5: Apr | C5: =IFERROR(__xludf.DUMMYFUNCTION("QUERY(Concat!$A:$F,""SELECT COUNT(E) WHERE A >= date '""&TEXT(DATEVALUE(DATE(C$1,$A5,1)),""yyyy-mm-dd"")&""' AND A < date '""&TEXT(DATEVALUE(EDATE(DATE(C$1,$A5,1),1)),""yyyy-mm-dd"")&""' LABEL COUNT(E) '' "", 0)"),2.0) -> 2 | D5: =IFERROR(__xludf.DUMMYFUNCTION("QUERY(Concat!$A:$F,""SELECT COUNT(E) WHERE A >= date '""&TEXT(DATEVALUE(DATE(D$1,$A5,1)),""yyyy-mm-dd"")&""' AND A < date '""&TEXT(DATEVALUE(EDATE(DATE(D$1,$A5,1),1)),""yyyy-mm-dd"")&""' LABEL COUNT(E) '' "", 0)"),3.0) -> 3 | E5: =IFERROR(__xludf.DUMMYFUNCTION("QUERY(Concat!$A:$F,""SELECT COUNT(E) WHERE A >= date '""&TEXT(DATEVALUE(DATE(E$1,$A5,1)),""yyyy-mm-dd"")&""' AND A < date '""&TEXT(DATEVALUE(EDATE(DATE(E$1,$A5,1),1)),""yyyy-mm-dd"")&""' LABEL COUNT(E) '' "", 0)"),7.0) -> 7 | F5: =IFERROR(__xludf.DUMMYFUNCTION("QUERY(Concat!$A:$F,""SELECT COUNT(E) WHERE A >= date '""&TEXT(DATEVALUE(DATE(F$1,$A5,1)),""yyyy-mm-dd"")&""' AND A < date '""&TEXT(DATEVALUE(EDATE(DATE(F$1,$A5,1),1)),""yyyy-mm-dd"")&""' LABEL COUNT(E) '' "", 0)"),16.0) -> 16
